Workbook

Sheet Base Inversionistas
J3: 2025
A4: NO. | B4: NOMBRES | C4: NO. IDENTIFICACION | D4: NO. CELULAR | E4: LOCALIDAD | F4: No. Cuotas | G4: SALDO A DIC2024 | H4: FORMA | I4: TIPO DE MOVIMIENTO | J4: ENERO | K4: FEBRERO | L4: MARZO | M4: ABRIL | N4: MAYO | O4: JUNIO | P4: JULIO | Q4: AGOSTO | R4: SEPTIEMBRE | S4: OCTUBRE | T4: NOVIEMBRE | U4: DICIEMBRE | V4: ENERO | W4: Total_Aportes | X4: Cuotas_Calculadas | Y4: Meses_Con_Aporte | Z4: Cuotas_Enteras
A5: 1 | B5: ABNER GONZALEZ | C5: 9289920 | E5: Medellin | F5: 1 | G5: 859000 | H5: BCOL AHO | I5: CREDITO | N5: 800000 | R5: 400000 | S5: 0 | T5: 0 | U5: 0 | V5: =VLOOKUP(B5,'[1]INV. 2026'!$B:$J,9,0) -> 0 | W5: =SUM(J5:V5) -> 1200000 | X5: =W5/400000 -> 3 | Y5: =COUNTIF(J5:V5,">0") -> 2 | Z5: =ROUNDUP(X5,0) -> 3
A6: 2 | B6: ALBA MARINA ROMERO | I6: CREDITO | N6: 100000 | R6: 0 | S6: 0 | T6: 0 | U6: 0 | V6: =VLOOKUP(B6,'[1]INV. 2026'!$B:$J,9,0) -> 0 | W6: =SUM(J6:V6) -> 100000 | X6: =W6/400000 -> 0.25 | Y6: =COUNTIF(J6:V6,">0") -> 1 | Z6: =ROUNDUP(X6,0) -> 1
A7: 3 | B7: ANA MISAD | E7: BOGOTA | G7: 200000 | H7: EFECTIVO | I7: CREDITO | R7: 0 | S7: 0 | T7: 0 | U7: 0 | V7: =VLOOKUP(B7,'[1]INV. 2026'!$B:$J,9,0) -> 0 | W7: =SUM(J7:V7) -> 0 | X7: =W7/400000 -> 0 | Y7: =COUNTIF(J7:V7,">0") -> 0 | Z7: =ROUNDUP(X7,0) -> 0
A8: 4 | B8: ANA CORTES | E8: BOGOTA | G8: 0 | H8: EFECTIVO | I8: CREDITO | K8: 100000 | R8: 0 | S8: 0 | T8: 0 | U8: 0 | V8: =VLOOKUP(B8,'[1]INV. 2026'!$B:$J,9,0) -> 0 | W8: =SUM(J8:V8) -> 100000 | X8: =W8/400000 -> 0.25 | Y8: =COUNTIF(J8:V8,">0") -> 1 | Z8: =ROUNDUP(X8,0) -> 1
A9: 5 | B9: ANA MARIA PORTILLA CLAROS | C9: 1114621012 | D9: 3207945735 | E9: BOGOTA | G9: 1000000 | H9: BCOL AHO | I9: CREDITO | J9: 400000 | R9: 0 | S9: 0 | T9: 200000 | U9: 400000 | V9: =VLOOKUP(B9,'[1]INV. 2026'!$B:$J,9,0) -> 0 | W9: =SUM(J9:V9) -> 1000000 | X9: =W9/400000 -> 2.5 | Y9: =COUNTIF(J9:V9,">0") -> 3 | Z9: =ROUNDUP(X9,0) -> 3
A10: 6 | B10: ANDRES CASTRILLON "GIRARDOTA" | C10: 1035855590 | E10: Girardota | G10: 200000 | H10: BCOL AHO | I10: CREDITO | P10: 100000 | R10: 0 | S10: 0 | T10: 400000 | U10: 400000 | V10: =VLOOKUP(B10,'[1]INV. 2026'!$B:$J,9,0) -> 0 | W10: =SUM(J10:V10) -> 900000 | X10: =W10/400000 -> 2.25 | Y10: =COUNTIF(J10:V10,">0") -> 3 | Z10: =ROUNDUP(X10,0) -> 3
A11: 7 | B11: ANDRES MORENO | C11: 1077465696 | D11: 3207593131 | E11: CHOCO | I11: CREDITO | N11: 400000 | Q11: 400000 | R11: 0 | S11: 0 | T11: 0 | U11: 800000 | V11: =VLOOKUP(B11,'[1]INV. 2026'!$B:$J,9,0) -> 0 | W11: =SUM(J11:V11) -> 1600000 | X11: =W11/400000 -> 4 | Y11: =COUNTIF(J11:V11,">0") -> 3 | Z11: =ROUNDUP(X11,0) -> 4
A12: 8 | B12: ANGIE FINO | I12: CREDITO | O12: 1000000 | R12: 0 | S12: 0 | T12: 0 | U12: 0 | V12: =VLOOKUP(B12,'[1]INV. 2026'!$B:$J,9,0) -> 0 | W12: =SUM(J12:V12) -> 1000000 | X12: =W12/400000 -> 2.5 | Y12: =COUNTIF(J12:V12,">0") -> 1 | Z12: =ROUNDUP(X12,0) -> 3
A13: 9 | B13: ANONIMO | E13: BOGOTA | I13: CREDITO | N13: 380000 | O13: 200000 | R13: 0 | S13: 0 | T13: 0 | U13: 0 | V13: =VLOOKUP(B13,'[1]INV. 2026'!$B:$J,9,0) -> 0 | W13: =SUM(J13:V13) -> 580000 | X13: =W13/400000 -> 1.45 | Y13: =COUNTIF(J13:V13,">0") -> 2 | Z13: =ROUNDUP(X13,0) -> 2
A14: 10 | B14: BENITO HERRRA | F14: 3 | G14: 1200000 | H14: BCOL AHO | I14: CREDITO | R14: 0 | S14: 0 | T14: 400000 | U14: 0 | V14: =VLOOKUP(B14,'[1]INV. 2026'!$B:$J,9,0) -> 0 | W14: =SUM(J14:V14) -> 400000 | X14: =W14/400000 -> 1 | Y14: =COUNTIF(J14:V14,">0") -> 1 | Z14: =ROUNDUP(X14,0) -> 1
A15: 11 | B15: BIBIANA MONTOYA RODAS | G15: 1500000 | H15: BCOL AHO | I15: CREDITO | R15: 0 | S15: 0 | T15: 0 | U15: 0 | V15: =VLOOKUP(B15,'[1]INV. 2026'!$B:$J,9,0) -> 0 | W15: =SUM(J15:V15) -> 0 | X15: =W15/400000 -> 0 | Y15: =COUNTIF(J15:V15,">0") -> 0 | Z15: =ROUNDUP(X15,0) -> 0
A16: 12 | B16: BRAYER ALEXIS QUINTERO FERNANDEZ | E16: CUCUTA | G16: 820000 | H16: BCOL AHO | I16: CREDITO | L16: 400000 | Q16: 400000 | R16: 400000 | S16: 400000 | T16: 0 | U16: 400000 | V16: =VLOOKUP(B16,'[1]INV. 2026'!$B:$J,9,0) -> 400000 | W16: =SUM(J16:V16) -> 2400000 | X16: =W16/400000 -> 6 | Y16: =COUNTIF(J16:V16,">0") -> 6 | Z16: =ROUNDUP(X16,0) -> 6
A17: 13 | B17: CARLIS MICHELE PEREZ CANO | C17: 1095846194 | D17: 3022962452 | E17: BOGOTA | H17: BCOL AHO | I17: CREDITO | L17: 400000 | N17: 200000 | R17: 0 | S17: 0 | T17: 400000 | U17: 0 | V17: =VLOOKUP(B17,'[1]INV. 2026'!$B:$J,9,0) -> 0 | W17: =SUM(J17:V17) -> 1000000 | X17: =W17/400000 -> 2.5 | Y17: =COUNTIF(J17:V17,">0") -> 3 | Z17: =ROUNDUP(X17,0) -> 3
A18: 14 | B18: CARLOS CARRASCO | E18: BOGOTA | F18: 1 | G18: 1320000 | H18: EFECTIVO | I18: CREDITO | J18: 400000 | K18: 424000 | L18: 425000 | M18: 450000 | N18: 400000 | O18: 400000 | P18: 400000 | Q18: 400000 | R18: 400000 | S18: 400000 | T18: 400000 | U18: 400000 | V18: =VLOOKUP(B18,'[1]INV. 2026'!$B:$J,9,0) -> 400000 | W18: =SUM(J18:V18) -> 5299000 | X18: =W18/400000 -> 13.2475 | Y18: =COUNTIF(J18:V18,">0") -> 13 | Z18: =ROUNDUP(X18,0) -> 14
A19: 15 | B19: CARLOS PALMA | E19: BOGOTA | F19: 1 | G19: 1200000 | H19: EFECTIVO | I19: CREDITO | K19: 400000 | L19: 400000 | M19: 400000 | N19: 400000 | P19: 400000 | Q19: 400000 | R19: 0 | S19: 400000 | T19: 400000 | U19: 400000 | V19: =VLOOKUP(B19,'[1]INV. 2026'!$B:$J,9,0) -> 0 | W19: =SUM(J19:V19) -> 3600000 | X19: =W19/400000 -> 9 | Y19: =COUNTIF(J19:V19,">0") -> 9 | Z19: =ROUNDUP(X19,0) -> 9
A20: 16 | B20: CARLOS ANDRES COCUY | C20: 14797460 | D20: 3160438302 | E20: DOSQUEBRADAS | G20: 0 | H20: BCOL AHO | I20: CREDITO | J20: 400000 | K20: 400000 | L20: 400000 | M20: 400000 | N20: 400000 | O20: 400000 | P20: 400000 | Q20: 400000 | R20: 450000 | S20: 650000 | T20: 0 | U20: 900000 | V20: =VLOOKUP(B20,'[1]INV. 2026'!$B:$J,9,0) -> 0 | W20: =SUM(J20:V20) -> 5200000 | X20: =W20/400000 -> 13 | Y20: =COUNTIF(J20:V20,">0") -> 11 | Z20: =ROUNDUP(X20,0) -> 13
A21: 17 | B21: CAROLINA QUIROGA | G21: 0 | H21: BCOL AHO | I21: CREDITO | L21: 100000 | R21: 0 | S21: 0 | T21: 0 | U21: 0 | V21: =VLOOKUP(B21,'[1]INV. 2026'!$B:$J,9,0) -> 0 | W21: =SUM(J21:V21) -> 100000 | X21: =W21/400000 -> 0.25 | Y21: =COUNTIF(J21:V21,">0") -> 1 | Z21: =ROUNDUP(X21,0) -> 1
A22: 18 | B22: CESAR VERA | C22: 79333423 | D22: 3166268412 | E22: BOGOTA | F22: 3 | G22: 4000000 | H22: EFECTIVO | I22: CREDITO | J22: 800000 | K22: 2000000 | L22: 1200000 | M22: 1600000 | N22: 1200000 | O22: 1600000 | P22: 1700000 | Q22: 1200000 | R22: 1600000 | S22: 2000000 | T22: 2400000 | U22: 1600000 | V22: =VLOOKUP(B22,'[1]INV. 2026'!$B:$J,9,0) -> 1200000 | W22: =SUM(J22:V22) -> 20100000 | X22: =W22/400000 -> 50.25 | Y22: =COUNTIF(J22:V22,">0") -> 13 | Z22: =ROUNDUP(X22,0) -> 51
A23: 19 | B23: CLAUDIA ARCINIEGAS | G23: 0 | H23: BCOL AHO | I23: CREDITO | L23: 400000 | N23: 400000 | R23: 0 | S23: 0 | T23: 0 | U23: 0 | V23: =VLOOKUP(B23,'[1]INV. 2026'!$B:$J,9,0) -> 0 | W23: =SUM(J23:V23) -> 800000 | X23: =W23/400000 -> 2 | Y23: =COUNTIF(J23:V23,">0") -> 2 | Z23: =ROUNDUP(X23,0) -> 2
A24: 20 | B24: DANIEL VARGAS | E24: NEIVA | F24: 1 | G24: 1200000 | H24: BCOL AHO | I24: CREDITO | R24: 0 | S24: 0 | T24: 0 | U24: 0 | V24: =VLOOKUP(B24,'[1]INV. 2026'!$B:$J,9,0) -> 400000 | W24: =SUM(J24:V24) -> 400000 | X24: =W24/400000 -> 1 | Y24: =COUNTIF(J24:V24,">0") -> 1 | Z24: =ROUNDUP(X24,0) -> 1
A25: 21 | B25: DANIELA CASTO | G25: 0 | H25: BCOL AHO | I25: CREDITO | K25: 200000 | R25: 0 | S25: 0 | T25: 0 | U25: 0 | V25: =VLOOKUP(B25,'[1]INV. 2026'!$B:$J,9,0) -> 0 | W25: =SUM(J25:V25) -> 200000 | X25: =W25/400000 -> 0.5 | Y25: =COUNTIF(J25:V25,">0") -> 1 | Z25: =ROUNDUP(X25,0) -> 1
A26: 22 | B26: DAVID MAESTRE | G26: 1200000 | H26: BCOL AHO | I26: CREDITO | K26: 200000 | M26: 400000 | N26: 200000 | P26: 400000 | R26: 0 | S26: 0 | T26: 0 | U26: 0 | V26: =VLOOKUP(B26,'[1]INV. 2026'!$B:$J,9,0) -> 0 | W26: =SUM(J26:V26) -> 1200000 | X26: =W26/400000 -> 3 | Y26: =COUNTIF(J26:V26,">0") -> 4 | Z26: =ROUNDUP(X26,0) -> 3
A27: 23 | B27: DAVID MIRANDA | E27: BOGOTA | F27: 1 | G27: 400000 | H27: BCOL AHO | I27: CREDITO | J27: 400000 | K27: 0 | L27: 400000 | N27: 400000 | P27: 800000 | Q27: 400000 | R27: 400000 | S27: 400000 | T27: 400000 | U27: 400000 | V27: =VLOOKUP(B27,'[1]INV. 2026'!$B:$J,9,0) -> 0 | W27: =SUM(J27:V27) -> 4000000 | X27: =W27/400000 -> 10 | Y27: =COUNTIF(J27:V27,">0") -> 9 | Z27: =ROUNDUP(X27,0) -> 10
A28: 24 | B28: EDDWARD GARCIA | E28: BOGOTA | F28: 1 | G28: 240000 | H28: EFECTIVO | I28: CREDITO | R28: 0 | S28: 0 | T28: 0 | U28: 0 | V28: =VLOOKUP(B28,'[1]INV. 2026'!$B:$J,9,0) -> 0 | W28: =SUM(J28:V28) -> 0 | X28: =W28/400000 -> 0 | Y28: =COUNTIF(J28:V28,">0") -> 0 | Z28: =ROUNDUP(X28,0) -> 0
A29: 25 | B29: ERICA PLATA | C29: 60362206 | D29: 3165652640 | E29: LOS PATIOS | F29: 1 | G29: 200000 | H29: BCOL AHO 2 | I29: CREDITO | R29: 0 | S29: 0 | T29: 400000 | U29: 400000 | V29: =VLOOKUP(B29,'[1]INV. 2026'!$B:$J,9,0) -> 0 | W29: =SUM(J29:V29) -> 800000 | X29: =W29/400000 -> 2 | Y29: =COUNTIF(J29:V29,">0") -> 2 | Z29: =ROUNDUP(X29,0) -> 2
A30: 26 | B30: ERMILGEN RIAÑO | E30: BOGOTA | G30: 100000 | H30: EFECTIVO | I30: CREDITO | R30: 0 | S30: 0 | T30: 0 | U30: 0 | V30: =VLOOKUP(B30,'[1]INV. 2026'!$B:$J,9,0) -> 0 | W30: =SUM(J30:V30) -> 0 | X30: =W30/400000 -> 0 | Y30: =COUNTIF(J30:V30,">0") -> 0 | Z30: =ROUNDUP(X30,0) -> 0
A31: 27 | B31: ESTEBAN ISAZA MUÑOZ | C31: 88230239 | D31: 3123933769 | E31: PAMPLONA | F31: 1 | G31: 2860000 | H31: BCOL AHO 2 | I31: CREDITO | J31: 830000 | K31: 830000 | M31: 830000 | N31: 830000 | P31: 830000 | R31: 830000 | S31: 0 | T31: 605000 | U31: 1600000 | V31: =VLOOKUP(B31,'[1]INV. 2026'!$B:$J,9,0) -> 1600000 | W31: =SUM(J31:V31) -> 8785000 | X31: =W31/400000 -> 21.9625 | Y31: =COUNTIF(J31:V31,">0") -> 9 | Z31: =ROUNDUP(X31,0) -> 22
A32: 28 | B32: ESTHER TORRES | E32: BOGOTA | G32: 450000 | H32: EFECTIVO | I32: CREDITO | R32: 0 | S32: 0 | T32: 0 | U32: 0 | V32: =VLOOKUP(B32,'[1]INV. 2026'!$B:$J,9,0) -> 0 | W32: =SUM(J32:V32) -> 0 | X32: =W32/400000 -> 0 | Y32: =COUNTIF(J32:V32,">0") -> 0 | Z32: =ROUNDUP(X32,0) -> 0
A33: 29 | B33: EUSEBIO MONTES | F33: 1 | G33: 0 | H33: No Registra | I33: CREDITO | R33: 0 | S33: 0 | T33: 0 | U33: 0 | V33: =VLOOKUP(B33,'[1]INV. 2026'!$B:$J,9,0) -> 0 | W33: =SUM(J33:V33) -> 0 | X33: =W33/400000 -> 0 | Y33: =COUNTIF(J33:V33,">0") -> 0 | Z33: =ROUNDUP(X33,0) -> 0
A34: 30 | B34: FLOR ACUÑA | E34: BOGOTA | G34: 400000 | H34: BCOL AHO | I34: CREDITO | R34: 0 | S34: 0 | T34: 0 | U34: 0 | V34: =VLOOKUP(B34,'[1]INV. 2026'!$B:$J,9,0) -> 0 | W34: =SUM(J34:V34) -> 0 | X34: =W34/400000 -> 0 | Y34: =COUNTIF(J34:V34,">0") -> 0 | Z34: =ROUNDUP(X34,0) -> 0
A35: 31 | B35: FLOR SALAMANCA | C35: 23963745 | D35: 3142385522 | E35: BOGOTA | F35: 2 | G35: 4400000 | H35: BCOL AHO-EF | I35: CREDITO | J35: 1200000 | K35: 0 | L35: 1200000 | M35: 1200000 | O35: 1200000 | P35: 1600000 | Q35: 2000000 | R35: 0 | S35: 2000000 | T35: 3200000 | U35: 3600000 | V35: =VLOOKUP(B35,'[1]INV. 2026'!$B:$J,9,0) -> 3600000 | W35: =SUM(J35:V35) -> 20800000 | X35: =W35/400000 -> 52 | Y35: =COUNTIF(J35:V35,">0") -> 10 | Z35: =ROUNDUP(X35,0) -> 52
A36: 32 | B36: FRANCISCO VILLAMIL | E36: BOGOTA | G36: 0 | H36: EFECTIVO | I36: CREDITO | K36: 200000 | Q36: 400000 | R36: 400000 | S36: 400000 | T36: 400000 | U36: 400000 | V36: =VLOOKUP(B36,'[1]INV. 2026'!$B:$J,9,0) -> 400000 | W36: =SUM(J36:V36) -> 2600000 | X36: =W36/400000 -> 6.5 | Y36: =COUNTIF(J36:V36,">0") -> 7 | Z36: =ROUNDUP(X36,0) -> 7
A37: 33 | B37: FREIMAN JAIMES | C37: 13177594 | D37: 3107951023 | E37: OCAÑA | F37: 1 | G37: 0 | H37: No Registra | I37: CREDITO | R37: 400000 | S37: 400000 | T37: 0 | U37: 0 | V37: =VLOOKUP(B37,'[1]INV. 2026'!$B:$J,9,0) -> 0 | W37: =SUM(J37:V37) -> 800000 | X37: =W37/400000 -> 2 | Y37: =COUNTIF(J37:V37,">0") -> 2 | Z37: =ROUNDUP(X37,0) -> 2
A38: 34 | B38: GISEL DANIELA GUTIERREZ MURILLO | G38: 400000 | H38: BCOL AHO | I38: CREDITO | K38: 400000 | M38: 400000 | R38: 0 | S38: 0 | T38: 0 | U38: 0 | V38: =VLOOKUP(B38,'[1]INV. 2026'!$B:$J,9,0) -> 0 | W38: =SUM(J38:V38) -> 800000 | X38: =W38/400000 -> 2 | Y38: =COUNTIF(J38:V38,">0") -> 2 | Z38: =ROUNDUP(X38,0) -> 2
A39: 35 | B39: GUILLERMO MONSALVE | C39: 4803428 | D39: 3009838761 | E39: SINCELEJO | G39: 800000 | H39: BCOL AHO | I39: CREDITO | K39: 400000 | M39: 400000 | N39: 400000 | R39: 800000 | S39: 0 | T39: 1600000 | U39: 0 | V39: =VLOOKUP(B39,'[1]INV. 2026'!$B:$J,9,0) -> 0 | W39: =SUM(J39:V39) -> 3600000 | X39: =W39/400000 -> 9 | Y39: =COUNTIF(J39:V39,">0") -> 5 | Z39: =ROUNDUP(X39,0) -> 9
A40: 36 | B40: HERMES PATIÑO | C40: 93206783 | D40: 3125188563 | E40: SINCELEJO | G40: 800000 | H40: BCOL AHO | I40: CREDITO | J40: 400000 | K40: 400000 | M40: 400000 | N40: 400000 | O40: 400000 | P40: 400000 | Q40: 400000 | R40: 800000 | S40: 800000 | T40: 800000 | U40: 0 | V40: =VLOOKUP(B40,'[1]INV. 2026'!$B:$J,9,0) -> 0 | W40: =SUM(J40:V40) -> 5200000 | X40: =W40/400000 -> 13 | Y40: =COUNTIF(J40:V40,">0") -> 10 | Z40: =ROUNDUP(X40,0) -> 13
A41: 37 | B41: HUMBERTO OSPINO | C41: 72147202 | D41: 3126317467 | E41: ENVIGADO | G41: 1200000 | H41: BCOL AHO 2 | I41: CREDITO | L41: 800000 | M41: 400000 | O41: 400000 | R41: 0 | S41: 800000 | T41: 400000 | U41: 400000 | V41: =VLOOKUP(B41,'[1]INV. 2026'!$B:$J,9,0) -> 0 | W41: =SUM(J41:V41) -> 3200000 | X41: =W41/400000 -> 8 | Y41: =COUNTIF(J41:V41,">0") -> 6 | Z41: =ROUNDUP(X41,0) -> 8
A42: 38 | B42: IG. EN PTO. COLOMBIA | E42: Barranquilla | G42: 2812000 | H42: BCOL AHO | I42: CREDITO | J42: 1030000 | K42: 1020000 | N42: 1020000 | Q42: 640000 | R42: 0 | S42: 0 | T42: 0 | U42: 0 | V42: =VLOOKUP(B42,'[1]INV. 2026'!$B:$J,9,0) -> 0 | W42: =SUM(J42:V42) -> 3710000 | X42: =W42/400000 -> 9.275 | Y42: =COUNTIF(J42:V42,">0") -> 4 | Z42: =ROUNDUP(X42,0) -> 10
A43: 39 | B43: IG. EN BARRANQUILLA | C43: 8742974 | D43: 317889812 | E43: BARRANQUILLA | G43: 5200000 | H43: BCOL AHO | I43: CREDITO | J43: 4000000 | L43: 2000000 | M43: 2000000 | O43: 1600000 | P43: 903000 | R43: 3310000 | S43: 0 | T43: 800000 | U43: 395000 | V43: =VLOOKUP(B43,'[1]INV. 2026'!$B:$J,9,0) -> 2085000 | W43: =SUM(J43:V43) -> 17093000 | X43: =W43/400000 -> 42.7325 | Y43: =COUNTIF(J43:V43,">0") -> 9 | Z43: =ROUNDUP(X43,0) -> 43
A44: 40 | B44: IG. EN BAYUNCA JAVIER MIRANDA | E44: Bolivar | G44: 0 | H44: BCOL AHO | I44: CREDITO | J44: 400000 | R44: 200000 | S44: 0 | T44: 0 | U44: 0 | V44: =VLOOKUP(B44,'[1]INV. 2026'!$B:$J,9,0) -> 0 | W44: =SUM(J44:V44) -> 600000 | X44: =W44/400000 -> 1.5 | Y44: =COUNTIF(J44:V44,">0") -> 2 | Z44: =ROUNDUP(X44,0) -> 2
A45: 41 | B45: IG. EN BUCARAMANGA | C45: 900379577 | D45: 31844096518 | E45: Bucaramanga | I45: CREDITO | M45: 400000 | N45: 400000 | P45: 800000 | Q45: 525000 | R45: 4000000 | S45: 6400000 | T45: 7200000 | U45: 0 | V45: =VLOOKUP(B45,'[1]INV. 2026'!$B:$J,9,0) -> 0 | W45: =SUM(J45:V45) -> 19725000 | X45: =W45/400000 -> 49.3125 | Y45: =COUNTIF(J45:V45,">0") -> 7 | Z45: =ROUNDUP(X45,0) -> 50
A46: 42 | B46: IG. EN CARTAGO | E46: Cartago | F46: 1 | G46: 400000 | H46: BCOL AHO | I46: CREDITO | J46: 120000 | K46: 165000 | L46: 860000 | N46: 200000 | Q46: 100000 | R46: 1100000 | S46: 1150000 | T46: 0 | U46: 0 | V46: =VLOOKUP(B46,'[1]INV. 2026'!$B:$J,9,0) -> 0 | W46: =SUM(J46:V46) -> 3695000 | X46: =W46/400000 -> 9.2375 | Y46: =COUNTIF(J46:V46,">0") -> 7 | Z46: =ROUNDUP(X46,0) -> 10
A47: 43 | B47: IG. EN CORDOBA | E47: Cordoba | F47: 1 | G47: 2137600 | H47: BCOL AHO 2 | I47: CREDITO | N47: 800000 | P47: 3600000 | R47: 0 | S47: 6400000 | T47: 0 | U47: 0 | V47: =VLOOKUP(B47,'[1]INV. 2026'!$B:$J,9,0) -> 0 | W47: =SUM(J47:V47) -> 10800000 | X47: =W47/400000 -> 27 | Y47: =COUNTIF(J47:V47,">0") -> 3 | Z47: =ROUNDUP(X47,0) -> 27
A48: 44 | B48: IG. EN CUCUTA GUSTAVO LEON | C48: 16354014 | D48: 3133884161 | E48: CUCUTA | F48: 1 | G48: 2840000 | H48: BCOL AHO 2 | I48: CREDITO | J48: 400000 | K48: 400000 | L48: 800000 | M48: 400000 | N48: 800000 | O48: 1600000 | P48: 1600000 | Q48: 2000000 | R48: 2400000 | S48: 1200000 | T48: 1600000 | U48: 900000 | V48: =VLOOKUP(B48,'[1]INV. 2026'!$B:$J,9,0) -> 800000 | W48: =SUM(J48:V48) -> 14900000 | X48: =W48/400000 -> 37.25 | Y48: =COUNTIF(J48:V48,">0") -> 13 | Z48: =ROUNDUP(X48,0) -> 38
A49: 45 | B49: IG. EN DOSQUEBRADAS | E49: Dosquebradas | G49: 800000 | H49: BCOL AHO | I49: CREDITO | M49: 400000 | P49: 350000 | Q49: 400000 | R49: 400000 | S49: 0 | T49: 0 | U49: 350000 | V49: =VLOOKUP(B49,'[1]INV. 2026'!$B:$J,9,0) -> 0 | W49: =SUM(J49:V49) -> 1900000 | X49: =W49/400000 -> 4.75 | Y49: =COUNTIF(J49:V49,">0") -> 5 | Z49: =ROUNDUP(X49,0) -> 5
A50: 46 | B50: IG. EN EL D.C. | C50: 900299699 | D50: 3214118979 | E50: BOGOTA | G50: 3200000 | H50: TRASLADO | I50: CREDITO | J50: 800000 | K50: 800000 | L50: 800000 | M50: 800000 | N50: 2000000 | O50: 800000 | P50: 800000 | Q50: 800000 | R50: 3600000 | S50: 800000 | T50: 800000 | U50: 800000 | V50: =VLOOKUP(B50,'[1]INV. 2026'!$B:$J,9,0) -> 800000 | W50: =SUM(J50:V50) -> 14400000 | X50: =W50/400000 -> 36 | Y50: =COUNTIF(J50:V50,">0") -> 13 | Z50: =ROUNDUP(X50,0) -> 36
A51: 47 | B51: IG. EN GIRARDOT | E51: Girardot | G51: 220000 | H51: BCOL AHO 2 | I51: CREDITO | R51: 0 | S51: 0 | T51: 0 | U51: 0 | V51: =VLOOKUP(B51,'[1]INV. 2026'!$B:$J,9,0) -> 0 | W51: =SUM(J51:V51) -> 0 | X51: =W51/400000 -> 0 | Y51: =COUNTIF(J51:V51,">0") -> 0 | Z51: =ROUNDUP(X51,0) -> 0
A52: 48 | B52: IG. EN GIRARDOTA | E52: Girardota | G52: 400000 | H52: BCOL AHO | I52: CREDITO | K52: 400000 | L52: 400000 | M52: 400000 | N52: 1200000 | O52: 1200000 | P52: 2000000 | Q52: 1600000 | R52: 2800000 | S52: 0 | T52: 1600000 | U52: 1600000 | V52: =VLOOKUP(B52,'[1]INV. 2026'!$B:$J,9,0) -> 0 | W52: =SUM(J52:V52) -> 13200000 | X52: =W52/400000 -> 33 | Y52: =COUNTIF(J52:V52,">0") -> 10 | Z52: =ROUNDUP(X52,0) -> 33
A53: 49 | B53: IG. EN ITAGUI | E53: Itagui | G53: 1450000 | H53: BCOL AHO | I53: CREDITO | N53: 1600000 | R53: 0 | S53: 0 | T53: 0 | U53: 0 | V53: =VLOOKUP(B53,'[1]INV. 2026'!$B:$J,9,0) -> 0 | W53: =SUM(J53:V53) -> 1600000 | X53: =W53/400000 -> 4 | Y53: =COUNTIF(J53:V53,">0") -> 1 | Z53: =ROUNDUP(X53,0) -> 4
A54: 50 | B54: IG. EN ITSMINA | C54: 11809146 | D54: 3136811706 | E54: Itsmina | G54: 845000 | H54: BCOL AHO | I54: CREDITO | J54: 500000 | L54: 400000 | M54: 800000 | N54: 1200000 | Q54: 2400000 | R54: 0 | S54: 0 | T54: 1200000 | U54: 2400000 | V54: =VLOOKUP(B54,'[1]INV. 2026'!$B:$J,9,0) -> 800000 | W54: =SUM(J54:V54) -> 9700000 | X54: =W54/400000 -> 24.25 | Y54: =COUNTIF(J54:V54,">0") -> 8 | Z54: =ROUNDUP(X54,0) -> 25
A55: 51 | B55: IG. EN LA MINA | E55: La mina | G55: 800000 | H55: BCOL AHO | I55: CREDITO | N55: 400000 | Q55: 400000 | R55: 0 | S55: 0 | T55: 0 | U55: 0 | V55: =VLOOKUP(B55,'[1]INV. 2026'!$B:$J,9,0) -> 400000 | W55: =SUM(J55:V55) -> 1200000 | X55: =W55/400000 -> 3 | Y55: =COUNTIF(J55:V55,">0") -> 3 | Z55: =ROUNDUP(X55,0) -> 3
A56: 52 | B56: IG. EN MALAMBO | E56: Malambo | F56: 1 | G56: 850000 | H56: BCOL AHO 2 | I56: CREDITO | K56: 80000 | M56: 120000 | N56: 105000 | O56: 110000 | P56: 550000 | Q56: 150000 | R56: 110000 | S56: 0 | T56: 210000 | U56: 0 | V56: =VLOOKUP(B56,'[1]INV. 2026'!$B:$J,9,0) -> 400000 | W56: =SUM(J56:V56) -> 1835000 | X56: =W56/400000 -> 4.5875 | Y56: =COUNTIF(J56:V56,">0") -> 9 | Z56: =ROUNDUP(X56,0) -> 5
A57: 53 | B57: IG. EN MEDELLIN | E57: Medellin | I57: CREDITO | P57: 800000 | Q57: 1200000 | R57: 0 | S57: 0 | T57: 800000 | U57: 0 | V57: =VLOOKUP(B57,'[1]INV. 2026'!$B:$J,9,0) -> 0 | W57: =SUM(J57:V57) -> 2800000 | X57: =W57/400000 -> 7 | Y57: =COUNTIF(J57:V57,">0") -> 3 | Z57: =ROUNDUP(X57,0) -> 7
A58: 54 | B58: IG. EN NEIVA | E58: Neiva | G58: 400000 | H58: BCOL AHO | I58: CREDITO | J58: 400000 | M58: 1200000 | O58: 2400000 | P58: 1200000 | Q58: 1200000 | R58: 2400000 | S58: 0 | T58: 0 | U58: 0 | V58: =VLOOKUP(B58,'[1]INV. 2026'!$B:$J,9,0) -> 600000 | W58: =SUM(J58:V58) -> 9400000 | X58: =W58/400000 -> 23.5 | Y58: =COUNTIF(J58:V58,">0") -> 7 | Z58: =ROUNDUP(X58,0) -> 24
A59: 55 | B59: IG. EN OCAÑA | C59: 900420427-8 | E59: Ocaña | G59: 2800000 | H59: BCOL AHO | I59: CREDITO | J59: 800000 | K59: 800000 | L59: 800000 | M59: 800000 | P59: 1600000 | Q59: 1200000 | R59: 0 | S59: 1200000 | T59: 800000 | U59: 400000 | V59: =VLOOKUP(B59,'[1]INV. 2026'!$B:$J,9,0) -> 0 | W59: =SUM(J59:V59) -> 8400000 | X59: =W59/400000 -> 21 | Y59: =COUNTIF(J59:V59,">0") -> 9 | Z59: =ROUNDUP(X59,0) -> 21
A60: 56 | B60: IG. EN PEREIRA | E60: Pereira | F60: 2 | G60: 2800000 | H60: BCOL AHO 2 | I60: CREDITO | J60: 400000 | K60: 400000 | L60: 800000 | M60: 1200000 | N60: 1200000 | O60: 1200000 | P60: 800000 | Q60: 800000 | R60: 1200000 | S60: 1200000 | T60: 2000000 | U60: 800000 | V60: =VLOOKUP(B60,'[1]INV. 2026'!$B:$J,9,0) -> 0 | W60: =SUM(J60:V60) -> 12000000 | X60: =W60/400000 -> 30 | Y60: =COUNTIF(J60:V60,">0") -> 12 | Z60: =ROUNDUP(X60,0) -> 30
A61: 57 | B61: IG. EN QUIBDO | C61: 900371129 | D61: 3216464514 | E61: QUIBDO | G61: 400000 | H61: BCOL AHO | I61: CREDITO | L61: 800000 | R61: 0 | S61: 800000 | T61: 0 | U61: 0 | V61: =VLOOKUP(B61,'[1]INV. 2026'!$B:$J,9,0) -> 0 | W61: =SUM(J61:V61) -> 1600000 | X61: =W61/400000 -> 4 | Y61: =COUNTIF(J61:V61,">0") -> 2 | Z61: =ROUNDUP(X61,0) -> 4
A62: 58 | B62: IG. EN RIOHACHA | E62: Riohacha | H62: BCOL AHO | I62: CREDITO | M62: 440000 | R62: 0 | S62: 0 | T62: 0 | U62: 0 | V62: =VLOOKUP(B62,'[1]INV. 2026'!$B:$J,9,0) -> 0 | W62: =SUM(J62:V62) -> 440000 | X62: =W62/400000 -> 1.1 | Y62: =COUNTIF(J62:V62,">0") -> 1 | Z62: =ROUNDUP(X62,0) -> 2
A63: 59 | B63: IG. EN RIVERA | E63: Rivera | G63: 0 | H63: BCOL AHO | I63: CREDITO | J63: 100000 | K63: 100000 | L63: 100000 | N63: 100000 | O63: 170000 | P63: 170000 | R63: 170000 | S63: 170000 | T63: 170000 | U63: 0 | V63: =VLOOKUP(B63,'[1]INV. 2026'!$B:$J,9,0) -> 0 | W63: =SUM(J63:V63) -> 1250000 | X63: =W63/400000 -> 3.125 | Y63: =COUNTIF(J63:V63,">0") -> 9 | Z63: =ROUNDUP(X63,0) -> 4
A64: 60 | B64: IG. EN SINCELEJO | E64: Sincelejo | G64: 400000 | H64: BCOL AHO | I64: CREDITO | J64: 500000 | M64: 500000 | R64: 0 | S64: 0 | T64: 0 | U64: 0 | V64: =VLOOKUP(B64,'[1]INV. 2026'!$B:$J,9,0) -> 400000 | W64: =SUM(J64:V64) -> 1400000 | X64: =W64/400000 -> 3.5 | Y64: =COUNTIF(J64:V64,">0") -> 3 | Z64: =ROUNDUP(X64,0) -> 4
A65: 61 | B65: IG. EN SOLEDAD | E65: Soledad | G65: 2000000 | H65: BCOL AHO | I65: CREDITO | L65: 800000 | M65: 800000 | P65: 800000 | Q65: 800000 | R65: 2074000 | S65: 1050000 | T65: 0 | U65: 1200000 | V65: =VLOOKUP(B65,'[1]INV. 2026'!$B:$J,9,0) -> 0 | W65: =SUM(J65:V65) -> 7524000 | X65: =W65/400000 -> 18.81 | Y65: =COUNTIF(J65:V65,">0") -> 7 | Z65: =ROUNDUP(X65,0) -> 19
A66: 62 | B66: IG. EN STA MARTA JOSE LUIS TERAN | D66: 3233712038 | E66: Sta marta | G66: 200000 | H66: BCOL AHO | I66: CREDITO | J66: 602000 | L66: 322000 | M66: 197250 | N66: 600000 | Q66: 315000 | R66: 570000 | S66: 200000 | T66: 2000000 | U66: 2260000 | V66: =VLOOKUP(B66,'[1]INV. 2026'!$B:$J,9,0) -> 2130000 | W66: =SUM(J66:V66) -> 9196250 | X66: =W66/400000 -> 22.990625 | Y66: =COUNTIF(J66:V66,">0") -> 10 | Z66: =ROUNDUP(X66,0) -> 23
A67: 63 | B67: IG. EN SUAN | E67: Suan | G67: 800000 | H67: BCOL AHO | I67: CREDITO | J67: 400000 | M67: 400000 | N67: 400000 | O67: 275000 | P67: 400000 | Q67: 400000 | R67: 0 | S67: 400000 | T67: 0 | U67: 170000 | V67: =VLOOKUP(B67,'[1]INV. 2026'!$B:$J,9,0) -> 570000 | W67: =SUM(J67:V67) -> 3415000 | X67: =W67/400000 -> 8.5375 | Y67: =COUNTIF(J67:V67,">0") -> 9 | Z67: =ROUNDUP(X67,0) -> 9
A68: 64 | B68: IG. EN TURBACO | E68: Turbaco | G68: 400000 | H68: BCOL AHO | I68: CREDITO | N68: 3100000 | R68: 0 | S68: 0 | T68: 2204059 | U68: 0 | V68: =VLOOKUP(B68,'[1]INV. 2026'!$B:$J,9,0) -> 0 | W68: =SUM(J68:V68) -> 5304059 | X68: =W68/400000 -> 13.260148 | Y68: =COUNTIF(J68:V68,">0") -> 2 | Z68: =ROUNDUP(X68,0) -> 14
A69: 65 | B69: IG. EN UBATE | C69: 900384157 | D69: 3103160465 | E69: Ubate | G69: 3200000 | H69: BCOL AHO | I69: CREDITO | J69: 1600000 | L69: 1600000 | M69: 1600000 | N69: 1600000 | P69: 1600000 | Q69: 1600000 | R69: 1600000 | S69: 1600000 | T69: 1500000 | U69: 1200000 | V69: =VLOOKUP(B69,'[1]INV. 2026'!$B:$J,9,0) -> 4800000 | W69: =SUM(J69:V69) -> 20300000 | X69: =W69/400000 -> 50.75 | Y69: =COUNTIF(J69:V69,">0") -> 11 | Z69: =ROUNDUP(X69,0) -> 51
A70: 66 | B70: IG. EN VALLEDUPAR | C70: 900406774 | E70: Valledupar | G70: 3340000 | H70: BCOL AHO | I70: CREDITO | J70: 800000 | K70: 1495000 | L70: 3000000 | M70: 6400000 | P70: 6000000 | Q70: 6545000 | R70: 6400000 | S70: 7100000 | T70: 9500000 | U70: 11600000 | V70: =VLOOKUP(B70,'[1]INV. 2026'!$B:$J,9,0) -> 0 | W70: =SUM(J70:V70) -> 58840000 | X70: =W70/400000 -> 147.1 | Y70: =COUNTIF(J70:V70,">0") -> 10 | Z70: =ROUNDUP(X70,0) -> 148
A71: 67 | B71: IG. EN VILLAVICENCIO | E71: Villavicencio | H71: BCOL AHO | I71: CREDITO | M71: 200000 | N71: 400000 | P71: 560000 | R71: 950000 | S71: 0 | T71: 0 | U71: 0 | V71: =VLOOKUP(B71,'[1]INV. 2026'!$B:$J,9,0) -> 0 | W71: =SUM(J71:V71) -> 2110000 | X71: =W71/400000 -> 5.275 | Y71: =COUNTIF(J71:V71,">0") -> 4 | Z71: =ROUNDUP(X71,0) -> 6
A72: 68 | B72: IG. EN VILLA DEL ROSARIO | E72: Villa del Rosario | I72: CREDITO | O72: 1580000 | Q72: 2000000 | R72: 2000000 | S72: 0 | T72: 2000000 | U72: 0 | V72: =VLOOKUP(B72,'[1]INV. 2026'!$B:$J,9,0) -> 1200000 | W72: =SUM(J72:V72) -> 8780000 | X72: =W72/400000 -> 21.95 | Y72: =COUNTIF(J72:V72,">0") -> 5 | Z72: =ROUNDUP(X72,0) -> 22
A73: 69 | B73: IG. EN TULUA GUILLERMO HERRERA MURCIA | E73: Tulua | G73: 400000 | H73: BCOL AHO | I73: CREDITO | M73: 400000 | O73: 400000 | P73: 400000 | Q73: 400000 | R73: 400000 | S73: 0 | T73: 0 | U73: 400000 | V73: =VLOOKUP(B73,'[1]INV. 2026'!$B:$J,9,0) -> 0 | W73: =SUM(J73:V73) -> 2400000 | X73: =W73/400000 -> 6 | Y73: =COUNTIF(J73:V73,">0") -> 6 | Z73: =ROUNDUP(X73,0) -> 6
A74: 70 | B74: IG. EN ARMENIA | E74: Armenia | I74: CREDITO | N74: 400000 | O74: 400000 | P74: 400000 | R74: 400000 | S74: 400000 | T74: 0 | U74: 1600000 | V74: =VLOOKUP(B74,'[1]INV. 2026'!$B:$J,9,0) -> 0 | W74: =SUM(J74:V74) -> 3600000 | X74: =W74/400000 -> 9 | Y74: =COUNTIF(J74:V74,">0") -> 6 | Z74: =ROUNDUP(X74,0) -> 9
A75: 71 | B75: IG. EN CARTAGENA | E75: CARTAGENA | I75: CREDITO | N75: 2400000 | O75: 2890000 | Q75: 2000000 | R75: 0 | S75: 3600000 | T75: 800000 | U75: 400000 | V75: =VLOOKUP(B75,'[1]INV. 2026'!$B:$J,9,0) -> 0 | W75: =SUM(J75:V75) -> 12090000 | X75: =W75/400000 -> 30.225 | Y75: =COUNTIF(J75:V75,">0") -> 6 | Z75: =ROUNDUP(X75,0) -> 31
A76: 72 | B76: IG. EN LOS PATIOS | C76: 900474240-1 | D76: 3222616473 | E76: LOS PATIOS | I76: CREDITO | N76: 1600000 | O76: 2000000 | P76: 400000 | Q76: 1600000 | R76: 0 | S76: 1400000 | T76: 400000 | U76: 800000 | V76: =VLOOKUP(B76,'[1]INV. 2026'!$B:$J,9,0) -> 800000 | W76: =SUM(J76:V76) -> 9000000 | X76: =W76/400000 -> 22.5 | Y76: =COUNTIF(J76:V76,">0") -> 8 | Z76: =ROUNDUP(X76,0) -> 23
A77: 73 | B77: IG. EN MONTERIA y STA LUCIA | E77: Monteria | F77: 1 | G77: 1862400 | H77: BCOL AHO 2 | I77: CREDITO | K77: 1737600 | L77: 800000 | M77: 1200000 | N77: 2400000 | O77: 2400000 | Q77: 3600000 | R77: 0 | S77: 0 | T77: 0 | U77: 0 | V77: =VLOOKUP(B77,'[1]INV. 2026'!$B:$J,9,0) -> 2500000 | W77: =SUM(J77:V77) -> 14637600 | X77: =W77/400000 -> 36.594 | Y77: =COUNTIF(J77:V77,">0") -> 7 | Z77: =ROUNDUP(X77,0) -> 37
A78: 74 | B78: INDIRA ESTRADA | E78: BOGOTA | G78: 200000 | H78: EFECTIVO | I78: CREDITO | R78: 0 | S78: 0 | T78: 0 | U78: 0 | V78: =VLOOKUP(B78,'[1]INV. 2026'!$B:$J,9,0) -> 0 | W78: =SUM(J78:V78) -> 0 | X78: =W78/400000 -> 0 | Y78: =COUNTIF(J78:V78,">0") -> 0 | Z78: =ROUNDUP(X78,0) -> 0
A79: 75 | B79: ISABEL TORRIJAS | E79: Medellin | F79: 1 | G79: 50000 | H79: BCOL AHO 2 | I79: CREDITO | R79: 0 | S79: 0 | T79: 0 | U79: 0 | V79: =VLOOKUP(B79,'[1]INV. 2026'!$B:$J,9,0) -> 0 | W79: =SUM(J79:V79) -> 0 | X79: =W79/400000 -> 0 | Y79: =COUNTIF(J79:V79,">0") -> 0 | Z79: =ROUNDUP(X79,0) -> 0
A80: 76 | B80: JAMES GAMBOA | E80: BOGOTA | G80: 1762000 | H80: BCOL AHO | I80: CREDITO | R80: 0 | S80: 0 | T80: 0 | U80: 0 | V80: =VLOOKUP(B80,'[1]INV. 2026'!$B:$J,9,0) -> 0 | W80: =SUM(J80:V80) -> 0 | X80: =W80/400000 -> 0 | Y80: =COUNTIF(J80:V80,">0") -> 0 | Z80: =ROUNDUP(X80,0) -> 0
A81: 77 | B81: JAVIER BLOOM | E81: Medellin | G81: 800000 | H81: BCOL AHO | I81: CREDITO | R81: 0 | S81: 0 | T81: 0 | U81: 0 | V81: =VLOOKUP(B81,'[1]INV. 2026'!$B:$J,9,0) -> 0 | W81: =SUM(J81:V81) -> 0 | X81: =W81/400000 -> 0 | Y81: =COUNTIF(J81:V81,">0") -> 0 | Z81: =ROUNDUP(X81,0) -> 0
A82: 78 | B82: JEAN CARLOS BLANCO | C82: 1093783625 | D82: 3223202421 | E82: LOS PATIOS | G82: 1200000 | H82: BCOL AHO | I82: CREDITO | K82: 800000 | M82: 400000 | N82: 400000 | P82: 400000 | Q82: 400000 | R82: 400000 | S82: 800000 | T82: 800000 | U82: 400000 | V82: =VLOOKUP(B82,'[1]INV. 2026'!$B:$J,9,0) -> 400000 | W82: =SUM(J82:V82) -> 5200000 | X82: =W82/400000 -> 13 | Y82: =COUNTIF(J82:V82,">0") -> 10 | Z82: =ROUNDUP(X82,0) -> 13
A83: 79 | B83: JHOJAS QUINTERO | C83: 79477468 | D83: 3185861284 | E83: SOACHA | G83: 500000 | H83: BCOL AHO | I83: CREDITO | N83: 400000 | O83: 400000 | P83: 500000 | R83: 600000 | S83: 500000 | T83: 940000 | U83: 400000 | V83: =VLOOKUP(B83,'[1]INV. 2026'!$B:$J,9,0) -> 400000 | W83: =SUM(J83:V83) -> 4140000 | X83: =W83/400000 -> 10.35 | Y83: =COUNTIF(J83:V83,">0") -> 8 | Z83: =ROUNDUP(X83,0) -> 11
A84: 80 | B84: JHON ROJAS | C84: 12135690 | E84: Neiva | G84: 100000 | H84: BCOL AHO 2 | I84: CREDITO | O84: 400000 | R84: 0 | S84: 400000 | T84: 0 | U84: 400000 | V84: =VLOOKUP(B84,'[1]INV. 2026'!$B:$J,9,0) -> 0 | W84: =SUM(J84:V84) -> 1200000 | X84: =W84/400000 -> 3 | Y84: =COUNTIF(J84:V84,">0") -> 3 | Z84: =ROUNDUP(X84,0) -> 3
A85: 81 | B85: JOEL ARIAS | E85: Medellin | G85: 0 | H85: BCOL AHO | I85: CREDITO | K85: 420000 | R85: 0 | S85: 0 | T85: 0 | U85: 0 | V85: =VLOOKUP(B85,'[1]INV. 2026'!$B:$J,9,0) -> 0 | W85: =SUM(J85:V85) -> 420000 | X85: =W85/400000 -> 1.05 | Y85: =COUNTIF(J85:V85,">0") -> 1 | Z85: =ROUNDUP(X85,0) -> 2
A86: 82 | B86: JOHAN GOMEZ ZAPATA | C86: 1128400756 | D86: 3043640493 | E86: MEDELLIN | H86: BCOL AHO | I86: CREDITO | L86: 400000 | N86: 400000 | R86: 0 | S86: 800000 | T86: 0 | U86: 400000 | V86: =VLOOKUP(B86,'[1]INV. 2026'!$B:$J,9,0) -> 0 | W86: =SUM(J86:V86) -> 2000000 | X86: =W86/400000 -> 5 | Y86: =COUNTIF(J86:V86,">0") -> 4 | Z86: =ROUNDUP(X86,0) -> 5
A87: 83 | B87: JOHANA SANTIESTEBAN | I87: CREDITO | N87: 2000000 | O87: 2000000 | R87: 0 | S87: 0 | T87: 0 | U87: 0 | V87: =VLOOKUP(B87,'[1]INV. 2026'!$B:$J,9,0) -> 0 | W87: =SUM(J87:V87) -> 4000000 | X87: =W87/400000 -> 10 | Y87: =COUNTIF(J87:V87,">0") -> 2 | Z87: =ROUNDUP(X87,0) -> 10
A88: 84 | B88: JORGE GOMEZ | C88: 13838106 | D88: 3158359949 | E88: Bucaramanga | F88: 2 | G88: 0 | H88: No Registra | I88: CREDITO | L88: 1200000 | M88: 700000 | N88: 400000 | O88: 400000 | P88: 400000 | Q88: 400000 | R88: 400000 | S88: 400000 | T88: 0 | U88: 0 | V88: =VLOOKUP(B88,'[1]INV. 2026'!$B:$J,9,0) -> 0 | W88: =SUM(J88:V88) -> 4300000 | X88: =W88/400000 -> 10.75 | Y88: =COUNTIF(J88:V88,">0") -> 8 | Z88: =ROUNDUP(X88,0) -> 11
A89: 85 | B89: JORGE LUIS BARRIOS | C89: 91249777 | G89: 800000 | H89: BCOL AHO | I89: CREDITO | K89: 800000 | L89: 400000 | N89: 1200000 | P89: 400000 | R89: 0 | S89: 0 | T89: 0 | U89: 0 | V89: =VLOOKUP(B89,'[1]INV. 2026'!$B:$J,9,0) -> 0 | W89: =SUM(J89:V89) -> 2800000 | X89: =W89/400000 -> 7 | Y89: =COUNTIF(J89:V89,">0") -> 4 | Z89: =ROUNDUP(X89,0) -> 7
A90: 86 | B90: JORGE RODRIGUEZ | G90: 200000 | H90: BCOL AHO | I90: CREDITO | J90: 200000 | R90: 0 | S90: 0 | T90: 0 | U90: 0 | V90: =VLOOKUP(B90,'[1]INV. 2026'!$B:$J,9,0) -> 0 | W90: =SUM(J90:V90) -> 200000 | X90: =W90/400000 -> 0.5 | Y90: =COUNTIF(J90:V90,">0") -> 1 | Z90: =ROUNDUP(X90,0) -> 1
A91: 87 | B91: JOSE ELBERT GARZON | G91: 860000 | H91: BCOL AHO | I91: CREDITO | R91: 0 | S91: 0 | T91: 0 | U91: 0 | V91: =VLOOKUP(B91,'[1]INV. 2026'!$B:$J,9,0) -> 0 | W91: =SUM(J91:V91) -> 0 | X91: =W91/400000 -> 0 | Y91: =COUNTIF(J91:V91,">0") -> 0 | Z91: =ROUNDUP(X91,0) -> 0
A92: 88 | B92: JOSE ENRIQUE ARIAS PEREZ | C92: 15374739 | E92: MEDELLIN | G92: 840000 | H92: BCOL AHO 2 | I92: CREDITO | M92: 420000 | N92: 420000 | O92: 420000 | P92: 420000 | Q92: 420000 | R92: 400000 | S92: 400000 | T92: 400000 | U92: 0 | V92: =VLOOKUP(B92,'[1]INV. 2026'!$B:$J,9,0) -> 0 | W92: =SUM(J92:V92) -> 3300000 | X92: =W92/400000 -> 8.25 | Y92: =COUNTIF(J92:V92,">0") -> 8 | Z92: =ROUNDUP(X92,0) -> 9
A93: 89 | B93: JOSE GONZALEZ | F93: 1 | G93: 400000 | H93: BCOL AHO | I93: CREDITO | R93: 0 | S93: 0 | T93: 0 | U93: 0 | V93: =VLOOKUP(B93,'[1]INV. 2026'!$B:$J,9,0) -> 0 | W93: =SUM(J93:V93) -> 0 | X93: =W93/400000 -> 0 | Y93: =COUNTIF(J93:V93,">0") -> 0 | Z93: =ROUNDUP(X93,0) -> 0
A94: 90 | B94: JUAN VALENCIA | G94: 1600000 | H94: BCOL AHO 2 | I94: CREDITO | R94: 0 | S94: 0 | T94: 0 | U94: 0 | V94: =VLOOKUP(B94,'[1]INV. 2026'!$B:$J,9,0) -> 0 | W94: =SUM(J94:V94) -> 0 | X94: =W94/400000 -> 0 | Y94: =COUNTIF(J94:V94,">0") -> 0 | Z94: =ROUNDUP(X94,0) -> 0
A95: 91 | B95: JUAN C. MORENO | F95: 1 | G95: 400000 | H95: BCOL AHO | I95: CREDITO | M95: 400000 | N95: 400000 | Q95: 400000 | R95: 0 | S95: 0 | T95: 0 | U95: 0 | V95: =VLOOKUP(B95,'[1]INV. 2026'!$B:$J,9,0) -> 0 | W95: =SUM(J95:V95) -> 1200000 | X95: =W95/400000 -> 3 | Y95: =COUNTIF(J95:V95,">0") -> 3 | Z95: =ROUNDUP(X95,0) -> 3
A96: 92 | B96: JUAN GUILLERMO MUÑOZ GIRARDOTA | E96: Girardota | G96: 400000 | H96: BCOL AHO | I96: CREDITO | R96: 0 | S96: 0 | T96: 400000 | U96: 400000 | V96: =VLOOKUP(B96,'[1]INV. 2026'!$B:$J,9,0) -> 0 | W96: =SUM(J96:V96) -> 800000 | X96: =W96/400000 -> 2 | Y96: =COUNTIF(J96:V96,">0") -> 2 | Z96: =ROUNDUP(X96,0) -> 2
A97: 93 | B97: JUAN MINA | G97: 0 | I97: CREDITO | K97: 400000 | R97: 0 | S97: 0 | T97: 0 | U97: 0 | V97: =VLOOKUP(B97,'[1]INV. 2026'!$B:$J,9,0) -> 0 | W97: =SUM(J97:V97) -> 400000 | X97: =W97/400000 -> 1 | Y97: =COUNTIF(J97:V97,">0") -> 1 | Z97: =ROUNDUP(X97,0) -> 1
A98: 94 | B98: JUAN PABLO OLIVELLA | C98: 77037962 | D98: 3108469718 | E98: VALLEDUPAR | G98: 1600000 | H98: BCOL AHO | I98: CREDITO | L98: 1600000 | M98: 400000 | N98: 800000 | P98: 400000 | R98: 400000 | S98: 400000 | T98: 0 | U98: 2400000 | V98: =VLOOKUP(B98,'[1]INV. 2026'!$B:$J,9,0) -> 2400000 | W98: =SUM(J98:V98) -> 8800000 | X98: =W98/400000 -> 22 | Y98: =COUNTIF(J98:V98,">0") -> 8 | Z98: =ROUNDUP(X98,0) -> 22
A99: 95 | B99: JUAN PABLO OLIVELLA (HNO. DONG) | G99: 0 | H99: BCOL AHO | I99: CREDITO | L99: 10000000 | R99: 0 | S99: 0 | T99: 0 | U99: 0 | V99: =VLOOKUP(B99,'[1]INV. 2026'!$B:$J,9,0) -> 0 | W99: =SUM(J99:V99) -> 10000000 | X99: =W99/400000 -> 25 | Y99: =COUNTIF(J99:V99,">0") -> 1 | Z99: =ROUNDUP(X99,0) -> 25
A100: 96 | B100: JUAN SEBASTIAN MONTES PINZON | E100: ZIPAQUIRA | G100: 400000 | H100: BCOL AHO | I100: CREDITO | R100: 0 | S100: 0 | T100: 0 | U100: 400000 | V100: =VLOOKUP(B100,'[1]INV. 2026'!$B:$J,9,0) -> 0 | W100: =SUM(J100:V100) -> 400000 | X100: =W100/400000 -> 1 | Y100: =COUNTIF(J100:V100,">0") -> 1 | Z100: =ROUNDUP(X100,0) -> 1
A101: 97 | B101: JULIAN CADAVID | F101: 3 | G101: 0 | H101: No Registra | I101: CREDITO | R101: 0 | S101: 0 | T101: 0 | U101: 0 | V101: =VLOOKUP(B101,'[1]INV. 2026'!$B:$J,9,0) -> 0 | W101: =SUM(J101:V101) -> 0 | X101: =W101/400000 -> 0 | Y101: =COUNTIF(J101:V101,">0") -> 0 | Z101: =ROUNDUP(X101,0) -> 0
A102: 98 | B102: JULIAN FRANCO IG. B/MANGA | E102: Bucaramanga | H102: BCOL AHO | I102: CREDITO | L102: 400000 | R102: 400000 | S102: 0 | T102: 0 | U102: 0 | V102: =VLOOKUP(B102,'[1]INV. 2026'!$B:$J,9,0) -> 0 | W102: =SUM(J102:V102) -> 800000 | X102: =W102/400000 -> 2 | Y102: =COUNTIF(J102:V102,">0") -> 2 | Z102: =ROUNDUP(X102,0) -> 2
...

Sheet Gastos
A4: NO. | B4: CLASIF | C4: NOMBRES | D4: NO. IDENTIFICACION | E4: NO. CELULAR | F4: LOCALIDAD | G4: No. Cuotas | H4: SALDO A DIC2024 | I4: FORMA | J4: TIPO DE MOVIMIENTO | K4: ENERO | L4: FEBRERO | M4: MARZO | N4: ABRIL | O4: MAYO | P4: JUNIO | Q4: JULIO | R4: AGOSTO | S4: SEPTIEMBRE | T4: OCTUBRE | U4: NOVIEMBRE | V4: DICIEMBRE | W4: ENERO
A5: 1 | B5: OFRENDA | C5: OFRENDA JORGE LUIS BARRIOS | J5: CREDITO | Q5: -2600000
A6: =A5+1 -> 2 | B6: DEUDA FONDO | C6: DEUDA COLPORTAJE | J6: CREDITO | K6: -3000000 | L6: -3000000 | M6: -3000000 | N6: -3000000 | O6: -3000000 | P6: -3000000 | Q6: -3000000 | R6: -3000000 | S6: -3000000 | T6: -3000000 | U6: -3000000 | V6: -3000000
A7: =A6+1 -> 3 | B7: PAC | C7: APOYO CASA PAC | H7: -12000000 | J7: DEBITO | K7: -2700000 | L7: -3500000
A8: =A7+1 -> 4 | B8: PAC | C8: APOYO CASA PAC | H8: -5231807 | I8: BCOL AHO | J8: DEBITO
A9: =A8+1 -> 5 | B9: PAC | C9: APOYO CASA PAC | H9: -3500000 | I9: BCOL ALHO | J9: DEBITO
A10: =A9+1 -> 6 | B10: CEPEV | C10: APOYO CEPPEV | H10: 0 | I10: BCOL AHO | J10: DEBITO | K10: -5000000 | L10: -5000000 | M10: -5000000 | N10: -5000000 | O10: -5000000 | P10: -5000000 | Q10: -5000000
A11: =A10+1 -> 7 | B11: BRASIL | C11: APOYO HNOS. EN BRASIL | H11: -20000000 | I11: BCOL AHO | J11: DEBITO | N11: -592000
A12: =A11+1 -> 8 | B12: PAC | C12: APOYO PERU PAC | J12: DEBITO | L12: -1667500
A13: =A12+1 -> 9 | B13: PAC | C13: ARRIENDO CASA PAC | H13: 0 | I13: BCOL CTE | J13: DEBITO
A14: =A13+1 -> 10 | B14: PAC | C14: ARRIENDO CASA PAC | H14: 0 | J14: DEBITO
A15: =A14+1 -> 11 | B15: INVERSIONISTAS | C15: COMPRA CELULAR | H15: -6700000 | I15: BCOL AHO | J15: DEBITO | N15: -769900
A16: =A15+1 -> 12 | B16: PEDRO D | C16: ENTREGA RESERVA PEDRO DONG | J16: DEBITO | M16: -31000000 | N16: -31000000
A17: =A16+1 -> 13 | B17: EAV | C17: ENVIO EAV | H17: -12300000 | J17: DEBITO | N17: -12015000
A18: =A17+1 -> 14 | B18: COSTA RICA | C18: OBRA COSTA RICA | J18: DEBITO | L18: -4620900
A19: =A18+1 -> 15 | B19: OFRENDA | C19: OFRENDA A JONES COSTA | H19: -400000 | I19: BCOL AHO | J19: DEBITO | M19: -1100000
A20: =A19+1 -> 16 | B20: PAC | C20: PAGO DEUDA ARRIENDO PAC | H20: 0 | I20: BCOL AHO | J20: DEBITO
A21: =A20+1 -> 17 | B21: CUBA | C21: VIATICOS CUBA | I21: BCOL AHO | J21: DEBITO | K21: -1477000
A22: =A21+1 -> 18 | B22: OFRENDA | C22: VIATICOS EUROPA DAVID MAESTRE | H22: -6413915 | J22: DEBITO | N22: -2000000
A23: =A22+1 -> 19 | B23: OFRENDA | C23: VIATICOS JONES | H23: 0 | I23: EFECTIVO | J23: DEBITO | M23: -2846000
A24: =A23+1 -> 20 | B24: EAV | C24: VIATICOS EAV DE RESERVA PEDRO D | I24: BCOL AHO | J24: DEBITO | O24: -4229600
A25: =A24+1 -> 21 | B25: IVPT | C25: GASTOS IVPT | H25: 0 | I25: BCOL AHO | J25: DEBITO | O25: -22131200
A26: =A25+1 -> 22 | B26: PANAMA | C26: ENTREGA A DAVID MAESTRE PANAMA | J26: DEBITO | P26: -7000000
A27: =A26+1 -> 23 | B27: VUELOS | C27: ENTREGA A DAVID M RESERVA PEDRO | J27: DEBITO | P27: -5000000
A28: =A27+1 -> 24 | B28: CEPEV | C28: APOYO CENA CEPPEV | J28: DEBITO | P28: -3000000
A29: =A28+1 -> 25 | B29: PEDRO D | C29: ENTREGA RESERVA PEDRO DONG | J29: DEBITO | P29: -41400000
A30: =A29+1 -> 26 | B30: PANAMA | C30: APOYO PAC PANAMA | J30: DEBITO | P30: -1000000
A31: =A30+1 -> 27 | B31: VUELOS | C31: ENTREGA DAVID MIRANDA RESERVA PD | J31: DEBITO | Q31: -7598700
A32: =A31+1 -> 28 | B32: VUELOS | C32: ENTREGA DAVID MIRANDA RESERVA PD | J32: DEBITO | Q32: -3575640
A33: =A32+1 -> 29 | B33: PANAMA | C33: APOYO PAC PANAMA | J33: DEBITO | Q33: -1000000
A34: =A33+1 -> 30 | B34: PEDRO D | C34: ENTREGA RESERVA PEDRO DONG | J34: DEBITO | Q34: -20350000
A35: =A34+1 -> 31 | B35: PANAMA | C35: LUIS MIGUEL NARANJO APOYO PANAMA | J35: DEBITO | R35: -1000000
A36: =A35+1 -> 32 | B36: VUELOS | C36: VIATICOS COLPORTORES | J36: DEBITO | R36: -459000
A37: =A36+1 -> 33 | B37: OFRENDA | C37: APOYO LUIS GABRIEL BRASIL | J37: DEBITO | R37: -2375000
A38: =A37+1 -> 34 | B38: JULIO S | C38: VIATICOS ECUADOR JULIO SANCHEA | J38: DEBITO | R38: -3844290
A39: =A38+1 -> 35 | B39: PEDRO D | C39: ENTREGA PEDRO DONG | J39: DEBITO | R39: -12045000
A40: =A39+1 -> 36 | B40: EAV | C40: ENTREGA A ESTANCIA | J40: DEBITO | R40: -11190450
A41: =A40+1 -> 37 | B41: PANAMA | C41: APOYO PAC PANAMA | J41: DEBITO | R41: -1100000
A42: =A41+1 -> 38 | B42: JULIO S | C42: JULIO SANCHEZ VIATICOS LILMA | J42: DEBITO | S42: -2284620
A43: =A42+1 -> 39 | B43: CEPEV | C43: APOYO CEPPEV | J43: DEBITO | S43: -3200000
A44: =A43+1 -> 40 | B44: VUELOS | C44: VUELOS COLPORTORES PERU | J44: DEBITO | S44: -3433200
A45: =A44+1 -> 41 | B45: VUELOS | C45: VUELOS COLPORTORES PANAMA | J45: DEBITO | S45: -2416300
A46: =A45+1 -> 42 | B46: PANAMA | C46: LUIS MIGUEL NARANJO APOYO PANAMA | J46: DEBITO | T46: -900000
A47: =A46+1 -> 43 | B47: CEPEV | C47: APOYO CEPPEV BUCARAMANGA | J47: DEBITO | T47: -6000000
A48: =A47+1 -> 44 | B48: OFRENDA | C48: DAVID MAESTRE VIATICOS ECUADOR | J48: DEBITO | T48: -1561973
A49: =A48+1 -> 45 | B49: PEDRO D | C49: ENTREGA RESERVA PEDRO DONG | J49: DEBITO | T49: -29998000
A50: =A49+1 -> 46 | B50: VUELOS | C50: DAVID MIRANDA VUELOS COLPORTORES | J50: DEBITO | T50: -3488330
A51: =A50+1 -> 47 | B51: VUELOS | C51: LUIS MIGUEL NARANJO VUELO COLPORTOR | J51: DEBITO | T51: -572600
A52: =A51+1 -> 48 | B52: CEPEV | C52: IGLESIA EN B/MANGA APOYO VANS | J52: DEBITO | T52: -10000000
A53: =A52+1 -> 49 | B53: PANAMA | C53: LUIS MIGUEL NARANJO APOYO PANAMA | J53: DEBITO | T53: -6000000
A54: =A53+1 -> 50 | B54: PANAMA | C54: LUIS MIGUEL NARANJO APOYO PANAMA | J54: DEBITO | T54: -1000000
A55: 51 | B55: CUBA | C55: APOYO CUBA | J55: DEBITO | U55: -1400000
A56: 52 | B56: INVERSIONISTAS | C56: MOVIL INVERSIONISTAS | J56: DEBITO | U56: -41900
A57: 53 | B57: VUELOS | C57: DAVID MIRANDA VUELOS COLPORTORES | J57: DEBITO | U57: -8689840
A58: 54 | B58: INVERSIONISTAS | C58: MOVIL INVERSIONISTAS | J58: DEBITO | V58: -34200
A59: 55 | B59: PANAMA | C59: LUIS MIGUEL NARANJO APOYO PANAMA | J59: DEBITO | V59: -1000000
A60: 56 | B60: VALLEDUPAR | C60: IG. EN VALLEDUPAR APOYO COLPORTOR | J60: DEBITO | V60: -2000000
A61: 57 | B61: CEPEV | C61: IG. EN BUCARAM/APOYO | J61: DEBITO | V61: -1000000
A62: 58 | B62: PEDRO D | C62: ENTREGA PEDRO DONG | J62: DEBITO | V62: -60793350
C75: TOTAL GASTOS A OCT 17/2025 | H75: =SUM(H5:H74) -> -66545722 | K75: =SUM(K5:K74) -> -12177000 | L75: =SUM(L5:L74) -> -17788400 | M75: =SUM(M5:M74) -> -42946000 | N75: =SUM(N5:N74) -> -54376900 | O75: =SUM(O5:O74) -> -34360800 | P75: =SUM(P5:P74) -> -65400000 | Q75: =SUM(Q5:Q74) -> -43124340 | R75: =SUM(R5:R74) -> -35013740 | ... W75: =SUM(W5:W74) -> 0

Sheet Resumen 2025
A1: INDICADORES CLAVE
I2: OCT | J2: NOV | K2: DIC
A3: MES | B3: TOTAL APORTES | C3: INVERSIONISTAS ACTIVOS | E3: MES | F3: TOTAL GASTOS | H3: NUEVOS INV (OCT) | I3: =COUNTIFS('Base Inversionistas'!R5:R296,"=0",'Base Inversionistas'!S5:S296,">0") -> 34 | J3: =COUNTIFS('Base Inversionistas'!S5:S296,"=0",'Base Inversionistas'!T5:T296,">0") -> 81 | K3: =COUNTIFS('Base Inversionistas'!T5:T296,"=0",'Base Inversionistas'!U5:U296,">0") -> 39
A4: 2024 | B4: 102568000 | E4: 2024 | F4: ='Gastos 26'!H123 -> -66545722 | H4: BAJAS INV | I4: =COUNTIFS('Base Inversionistas'!R6:R297,">0",'Base Inversionistas'!S6:S297,"=0") -> 23 | J4: =COUNTIFS('Base Inversionistas'!S6:S297,">0",'Base Inversionistas'!T6:T297,"=0") -> 31 | K4: =COUNTIFS('Base Inversionistas'!T6:T297,">0",'Base Inversionistas'!U6:U297,"=0") -> 29
A5: ENERO | B5: =SUM('Base Inversionistas'!J5:J268) -> 23082000 | C5: =COUNTIF('Base Inversionistas'!J5:J268,">0") -> 32 | E5: ENERO | F5: =SUM('Gastos 26'!K5:K122) -> -14223540
A6: FEBRERO | B6: =SUM('Base Inversionistas'!K5:K268) -> 19771600 | C6: 37 | E6: FEBRERO | F6: -17788400
A7: MARZO | B7: =SUM('Base Inversionistas'!L5:L268) -> 40867000 | C7: 43 | E7: MARZO | F7: -42946000 | H7: CLASIFICACION GASTOS | I7: Suma de ENERO | J7: Suma de FEBRERO | K7: Suma de MARZO | L7: Suma de ABRIL | M7: Suma de MAYO | N7: Suma de JUNIO | O7: Suma de JULIO | P7: Suma de AGOSTO | Q7: Suma de SEPTIEMBRE | R7: Suma de OCTUBRE | S7: Suma de NOVIEMBRE | T7: Suma de DICIEMBRE | U7: TOTAL
A8: ABRIL | B8: =SUM('Base Inversionistas'!M5:M268) -> 42217250 | C8: 58 | E8: ABRIL | F8: -54376900 | H8: BRASIL | L8: -592000 | U8: =SUM(I8:S8) -> -592000
A9: MAYO | B9: =SUM('Base Inversionistas'!N5:N268) -> 53415000 | C9: 71 | E9: MAYO | F9: -34360800 | H9: CEPEV | I9: -5000000 | J9: -5000000 | K9: -5000000 | L9: -5000000 | M9: -5000000 | N9: -8000000 | O9: -5000000 | Q9: -3200000 | R9: -16000000 | T9: -1000000 | U9: =SUM(I9:S9) -> -57200000
A10: JUNIO | B10: =SUM('Base Inversionistas'!O5:O268) -> 34625000 | C10: 45 | E10: JUNIO | F10: -65400000 | H10: COSTA RICA | J10: -4620900 | U10: =SUM(I10:S10) -> -4620900
A11: JULIO | B11: =SUM('Base Inversionistas'!P5:P268) -> 47793000 | C11: 70 | E11: JULIO | F11: -43124340 | H11: CUBA | I11: -1477000 | S11: -1400000 | U11: =SUM(I11:S11) -> -2877000
A12: AGOSTO | B12: =SUM('Base Inversionistas'!Q5:Q268) -> 55225000 | C12: 68 | E12: AGOSTO | F12: -35013740 | H12: DEUDA FONDO | I12: -3000000 | J12: -3000000 | K12: -3000000 | L12: -3000000 | M12: -3000000 | N12: -3000000 | O12: -3000000 | P12: -3000000 | Q12: -3000000 | R12: -3000000 | S12: -3000000 | T12: -3000000 | U12: =SUM(I12:S12) -> -33000000
A13: SEPTIEMBRE | B13: =SUM('Base Inversionistas'!R5:R268) -> 63734000 | C13: 70 | E13: SEPTIEMBRE | F13: -14334120 | H13: EAV | L13: -12015000 | M13: -4229600 | P13: -11190450 | U13: =SUM(I13:S13) -> -27435050
A14: OCTUBRE | B14: ='Base Inversionistas'!S297 -> 70300000 | C14: =COUNTIF('Base Inversionistas'!S5:S268, ">0") -> 80 | E14: OCTUBRE | F14: =Gastos!T75 -> -62520903 | H14: INVERSIONISTAS | L14: -769900 | S14: -41900 | T14: -34200 | U14: =SUM(I14:S14) -> -811800
A15: NOVIEMBRE | B15: ='Base Inversionistas'!T297 -> 92819059 | C15: =COUNTIF('Base Inversionistas'!T5:T296, ">0") -> 130 | E15: NOVIEMBRE | F15: =Gastos!U75 -> -13131740 | H15: IVPT | M15: -22131200 | U15: =SUM(I15:S15) -> -22131200
A16: DICIEMBRE | B16: ='Base Inversionistas'!U297 -> 93925000 | C16: =COUNTIF('Base Inversionistas'!U6:U296, ">0") -> 140 | E16: DICIEMBRE | F16: =Gastos!V75 -> -67827550 | H16: JULIO S | P16: -3844290 | Q16: -2284620 | U16: =SUM(I16:S16) -> -6128910
A17: TOTALES | B17: =SUM(B4:B16) -> 740341909 | E17: TOTALES | F17: =SUM(F4:F16) -> -531593755 | H17: OFRENDA | K17: -3946000 | L17: -2000000 | O17: -2600000 | P17: -2375000 | R17: -1561973 | U17: =SUM(I17:S17) -> -12482973
A18: SALDO INVERSIONISTAS | B18: =B17+F17 -> 208748154 | H18: PAC | I18: -2700000 | J18: -5167500 | U18: =SUM(I18:S18) -> -7867500
H19: PANAMA | N19: -8000000 | O19: -1000000 | P19: -2100000 | R19: -7900000 | T19: -1000000 | U19: =SUM(I19:S19) -> -19000000
H20: PEDRO D | K20: -31000000 | L20: -31000000 | N20: -41400000 | O20: -20350000 | P20: -12045000 | R20: -29998000 | T20: -60793350 | U20: =SUM(I20:S20) -> -165793000
H21: VUELOS | N21: -5000000 | O21: -11174340 | P21: -459000 | Q21: -5849500 | R21: -4060930 | S21: -8689840 | U21: =SUM(I21:S21) -> -35233610
D22: =B16/A25 -> 234.8125 | H22: VALLEDUPAR | T22: -2000000 | U22: =SUM(I22:T22) -> -2000000
H23: Total general | I23: -12177000 | J23: -17788400 | K23: -42946000 | L23: -54376900 | M23: -34360800 | N23: -65400000 | O23: -43124340 | P23: -35013740 | Q23: -14334120 | R23: -62520903 | S23: -13131740 | T23: -67827550
A25: 400000
A26: Etiquetas de fila | B26: Cuenta de Cuotas_Enteras
A27: ANTIOQUIA | B27: 1
A28: Armenia | B28: 2
A29: Barranquilla | B29: 3
A30: Bayunca | B30: 2
A31: BOGOTA | B31: 38
A32: Bolivar | B32: 2
A33: Bucaramanga | B33: 5
A34: CALI | B34: 2
A35: CARTAGENA | B35: 6
A36: Cartago | B36: 1
A37: CERETÉ | B37: 3
A38: CHIGORODO | B38: 1
... A94: Total general | B94: 292

Sheet Base Inversionistas 26
J3: 2026
A4: NO. | B4: NOMBRES | C4: NO. IDENTIFICACION | D4: NO. CELULAR | E4: LOCALIDAD | F4: No. Cuotas | G4: SALDO A DIC2024 | H4: FORMA | I4: TIPO DE MOVIMIENTO | J4: ENERO | K4: FEBRERO | L4: MARZO | M4: ABRIL | N4: MAYO | O4: JUNIO | P4: JULIO | Q4: AGOSTO | R4: SEPTIEMBRE | S4: OCTUBRE | T4: NOVIEMBRE | U4: DICIEMBRE | V4: Total_Aportes | W4: Cuotas_Calculadas | X4: Meses_Con_Aporte | Y4: Cuotas_Enteras
A5: 1 | B5: ABNER GONZALEZ | C5: 9289920 | E5: Medellin | F5: 1 | G5: 2059000 | H5: BCOL AHO | I5: CREDITO | J5: 0 | K5: 0 | L5: 0 | M5: 0 | N5: 0 | O5: 0 | P5: 0 | Q5: 0 | R5: 0 | V5: =SUM(J5:U5) -> 0 | W5: =V5/400000 -> 0 | X5: =COUNTIF(J5:U5,">0") -> 0 | Y5: =ROUNDUP(W5,0) -> 0
A6: 2 | B6: ALBA MARINA ROMERO | G6: 100000 | I6: CREDITO | J6: 0 | K6: 0 | L6: 0 | M6: 0 | N6: 0 | O6: 0 | P6: 0 | Q6: 0 | R6: 0 | V6: =SUM(J6:U6) -> 0 | W6: =V6/400000 -> 0 | X6: =COUNTIF(J6:U6,">0") -> 0 | Y6: =ROUNDUP(W6,0) -> 0
A7: 3 | B7: ANA MISAD | E7: BOGOTA | G7: 200000 | H7: EFECTIVO | I7: CREDITO | J7: 0 | K7: 0 | L7: 0 | M7: 0 | N7: 0 | O7: 0 | P7: 0 | Q7: 0 | R7: 0 | V7: =SUM(J7:U7) -> 0 | W7: =V7/400000 -> 0 | X7: =COUNTIF(J7:U7,">0") -> 0 | Y7: =ROUNDUP(W7,0) -> 0
A8: 4 | B8: ANA CORTES | E8: BOGOTA | G8: 100000 | H8: EFECTIVO | I8: CREDITO | J8: 0 | K8: 0 | L8: 0 | M8: 0 | N8: 0 | O8: 0 | P8: 0 | Q8: 0 | R8: 0 | V8: =SUM(J8:U8) -> 0 | W8: =V8/400000 -> 0 | X8: =COUNTIF(J8:U8,">0") -> 0 | Y8: =ROUNDUP(W8,0) -> 0
A9: 5 | B9: ANA MARIA PORTILLA CLAROS | C9: 1114621012 | D9: 3207945735 | E9: BOGOTA | G9: 2000000 | H9: BCOL AHO | I9: CREDITO | J9: 0 | K9: 0 | L9: 0 | M9: 600000 | N9: 0 | O9: 0 | P9: 0 | Q9: 0 | R9: 0 | V9: =SUM(J9:U9) -> 600000 | W9: =V9/400000 -> 1.5 | X9: =COUNTIF(J9:U9,">0") -> 1 | Y9: =ROUNDUP(W9,0) -> 2
A10: 6 | B10: ANDRES CASTRILLON "GIRARDOTA" | C10: 1035855590 | D10: 3154949282 | E10: Girardota | G10: 1100000 | H10: BCOL AHO | I10: CREDITO | J10: 400000 | K10: 400000 | L10: 400000 | M10: 400000 | N10: 0 | O10: 400000 | P10: 0 | Q10: 0 | R10: 0 | V10: =SUM(J10:U10) -> 2000000 | W10: =V10/400000 -> 5 | X10: =COUNTIF(J10:U10,">0") -> 5 | Y10: =ROUNDUP(W10,0) -> 5
A11: 7 | B11: ANDRES MORENO ARRIAGA | C11: 1077465696 | D11: 3207593131 | E11: QUIBDO | G11: 1600000 | I11: CREDITO | J11: 0 | K11: 0 | L11: 0 | M11: 400000 | N11: 0 | O11: 800000 | P11: 0 | Q11: 0 | R11: 400000 | V11: =SUM(J11:U11) -> 1600000 | W11: =V11/400000 -> 4 | X11: =COUNTIF(J11:U11,">0") -> 3 | Y11: =ROUNDUP(W11,0) -> 4
A12: 8 | B12: ANGIE FINO | G12: 1000000 | I12: CREDITO | J12: 0 | K12: 0 | L12: 0 | M12: 0 | N12: 0 | O12: 0 | P12: 0 | Q12: 0 | R12: 0 | V12: =SUM(J12:U12) -> 0 | W12: =V12/400000 -> 0 | X12: =COUNTIF(J12:U12,">0") -> 0 | Y12: =ROUNDUP(W12,0) -> 0
A13: 9 | B13: ANONIMO | E13: BOGOTA | G13: 580000 | I13: CREDITO | J13: 0 | K13: 0 | L13: 0 | M13: 0 | N13: 0 | O13: 400000 | P13: 0 | Q13: 0 | R13: 0 | V13: =SUM(J13:U13) -> 400000 | W13: =V13/400000 -> 1 | X13: =COUNTIF(J13:U13,">0") -> 1 | Y13: =ROUNDUP(W13,0) -> 1
A14: 10 | B14: APOYO CASA PAC | G14: 0 | H14: BCOL AHO | I14: DEBITO | J14: 0 | K14: 0 | L14: 0 | M14: 0 | N14: 0 | O14: 0 | P14: 0 | Q14: 0 | R14: 0 | V14: =SUM(J14:U14) -> 0 | W14: =V14/400000 -> 0 | X14: =COUNTIF(J14:U14,">0") -> 0 | Y14: =ROUNDUP(W14,0) -> 0
A15: 11 | B15: BENITO HERRRA | E15: PTO. COLOM | F15: 3 | G15: 1600000 | H15: BCOL AHO | I15: CREDITO | J15: 0 | K15: 0 | L15: 0 | M15: 1600000 | N15: 0 | O15: 1200000 | P15: 1600000 | Q15: 0 | R15: 0 | V15: =SUM(J15:U15) -> 4400000 | W15: =V15/400000 -> 11 | X15: =COUNTIF(J15:U15,">0") -> 3 | Y15: =ROUNDUP(W15,0) -> 11
A16: 12 | B16: BIBIANA MONTOYA RODAS | G16: 1500000 | H16: BCOL AHO | I16: CREDITO | J16: 0 | K16: 0 | L16: 0 | M16: 0 | N16: 0 | O16: 0 | P16: 0 | Q16: 0 | R16: 0 | V16: =SUM(J16:U16) -> 0 | W16: =V16/400000 -> 0 | X16: =COUNTIF(J16:U16,">0") -> 0 | Y16: =ROUNDUP(W16,0) -> 0
A17: 13 | B17: BRAYER ALEXIS QUINTERO FERNANDEZ | C17: 1090395092 | E17: CUCUTA | G17: 2820000 | H17: BCOL AHO | I17: CREDITO | J17: 400000 | K17: 400000 | L17: 0 | M17: 1200000 | N17: 0 | O17: 400000 | P17: 400000 | Q17: 0 | R17: 0 | V17: =SUM(J17:U17) -> 2800000 | W17: =V17/400000 -> 7 | X17: =COUNTIF(J17:U17,">0") -> 5 | Y17: =ROUNDUP(W17,0) -> 7
A18: 14 | B18: CARLIS MICHELE PEREZ CANO | C18: 1095846194 | D18: 3022962452 | E18: BOGOTA | G18: 1000000 | H18: BCOL AHO | I18: CREDITO | J18: 400000 | K18: 400000 | L18: 0 | M18: 0 | N18: 0 | O18: 0 | P18: 0 | Q18: 0 | R18: 0 | V18: =SUM(J18:U18) -> 800000 | W18: =V18/400000 -> 2 | X18: =COUNTIF(J18:U18,">0") -> 2 | Y18: =ROUNDUP(W18,0) -> 2
A19: 15 | B19: CARLOS CARRASCO | E19: BOGOTA | F19: 1 | G19: 6219000 | H19: EFECTIVO | I19: CREDITO | J19: 400000 | K19: 400000 | L19: 400000 | M19: 400000 | N19: 400000 | O19: 600000 | P19: 0 | Q19: 400000 | R19: 400000 | V19: =SUM(J19:U19) -> 3400000 | W19: =V19/400000 -> 8.5 | X19: =COUNTIF(J19:U19,">0") -> 8 | Y19: =ROUNDUP(W19,0) -> 9
A20: 16 | B20: CARLOS PALMA | E20: BOGOTA | F20: 1 | G20: 4800000 | H20: EFECTIVO | I20: CREDITO | J20: 0 | K20: 800000 | L20: 400000 | M20: 400000 | N20: 400000 | O20: 0 | P20: 0 | Q20: 800000 | R20: 800000 | V20: =SUM(J20:U20) -> 3600000 | W20: =V20/400000 -> 9 | X20: =COUNTIF(J20:U20,">0") -> 6 | Y20: =ROUNDUP(W20,0) -> 9
A21: 17 | B21: CARLOS ANDRES COCUY | C21: 14797460 | D21: 3160438302 | E21: DOSQUEBRADAS | G21: 5200000 | H21: BCOL AHO | I21: CREDITO | J21: 450000 | K21: 450000 | L21: 500000 | M21: 600000 | N21: 0 | O21: 0 | P21: 600000 | Q21: 400000 | R21: 400000 | V21: =SUM(J21:U21) -> 3400000 | W21: =V21/400000 -> 8.5 | X21: =COUNTIF(J21:U21,">0") -> 7 | Y21: =ROUNDUP(W21,0) -> 9
A22: 18 | B22: CAROLINA QUIROGA | E22: BOGOTA | G22: 100000 | H22: BCOL AHO | I22: CREDITO | J22: 0 | K22: 0 | L22: 0 | M22: 400000 | N22: 400000 | O22: 0 | P22: 0 | Q22: 0 | R22: 0 | V22: =SUM(J22:U22) -> 800000 | W22: =V22/400000 -> 2 | X22: =COUNTIF(J22:U22,">0") -> 2 | Y22: =ROUNDUP(W22,0) -> 2
A23: 19 | B23: CESAR VERA | C23: 79333423 | D23: 3166268412 | E23: BOGOTA | F23: 3 | G23: 22900000 | H23: EFECTIVO | I23: CREDITO | J23: 2000000 | K23: 1600000 | L23: 1600000 | M23: 2000000 | N23: 800000 | O23: 4000000 | P23: 3100000 | Q23: 2400000 | R23: 800000 | V23: =SUM(J23:U23) -> 18300000 | W23: =V23/400000 -> 45.75 | X23: =COUNTIF(J23:U23,">0") -> 9 | Y23: =ROUNDUP(W23,0) -> 46
A24: 20 | B24: CLAUDIA ARCINIEGAS | E24: CUCUTA | G24: 800000 | H24: BCOL AHO | I24: CREDITO | J24: 0 | K24: 0 | L24: 0 | M24: 0 | N24: 400000 | O24: 0 | P24: 0 | Q24: 0 | R24: 0 | V24: =SUM(J24:U24) -> 400000 | W24: =V24/400000 -> 1 | X24: =COUNTIF(J24:U24,">0") -> 1 | Y24: =ROUNDUP(W24,0) -> 1
A25: 21 | B25: DANIEL VARGAS | E25: Neiva | F25: 1 | G25: 1200000 | H25: BCOL AHO | I25: CREDITO | J25: 400000 | K25: 600000 | L25: 600000 | M25: 0 | N25: 800000 | O25: 400000 | P25: 0 | Q25: 0 | R25: 0 | V25: =SUM(J25:U25) -> 2800000 | W25: =V25/400000 -> 7 | X25: =COUNTIF(J25:U25,">0") -> 5 | Y25: =ROUNDUP(W25,0) -> 7
A26: 22 | B26: DANIELA CASTO | G26: 200000 | H26: BCOL AHO | I26: CREDITO | J26: 0 | K26: 0 | L26: 0 | M26: 0 | N26: 0 | O26: 0 | P26: 0 | Q26: 0 | R26: 0 | V26: =SUM(J26:U26) -> 0 | W26: =V26/400000 -> 0 | X26: =COUNTIF(J26:U26,">0") -> 0 | Y26: =ROUNDUP(W26,0) -> 0
A27: 23 | B27: DAVID MAESTRE | G27: 2400000 | H27: BCOL AHO | I27: CREDITO | J27: 0 | K27: 0 | L27: 0 | M27: 0 | N27: 0 | O27: 0 | P27: 0 | Q27: 0 | R27: 0 | V27: =SUM(J27:U27) -> 0 | W27: =V27/400000 -> 0 | X27: =COUNTIF(J27:U27,">0") -> 0 | Y27: =ROUNDUP(W27,0) -> 0
A28: 24 | B28: DAVID MIRANDA | E28: BOGOTA | F28: 1 | G28: 4400000 | H28: BCOL AHO | I28: CREDITO | J28: 400000 | K28: 0 | L28: 0 | M28: 800000 | N28: 400000 | O28: 0 | P28: 1200000 | Q28: 0 | R28: 0 | V28: =SUM(J28:U28) -> 2800000 | W28: =V28/400000 -> 7 | X28: =COUNTIF(J28:U28,">0") -> 4 | Y28: =ROUNDUP(W28,0) -> 7
A29: 25 | B29: EDDWARD GARCIA | E29: BOGOTA | F29: 1 | G29: 240000 | H29: EFECTIVO | I29: CREDITO | J29: 0 | K29: 0 | L29: 0 | M29: 0 | N29: 0 | O29: 0 | P29: 0 | Q29: 0 | R29: 0 | V29: =SUM(J29:U29) -> 0 | W29: =V29/400000 -> 0 | X29: =COUNTIF(J29:U29,">0") -> 0 | Y29: =ROUNDUP(W29,0) -> 0
A30: 26 | B30: ERICA PLATA | C30: 60362206 | D30: 3165652640 | E30: LOS PATIOS | F30: 1 | G30: 1000000 | H30: BCOL AHO 2 | I30: CREDITO | J30: 0 | K30: 400000 | L30: 400000 | M30: 400000 | N30: 400000 | O30: 0 | P30: 0 | Q30: 0 | R30: 401000 | V30: =SUM(J30:U30) -> 2001000 | W30: =V30/400000 -> 5.0025 | X30: =COUNTIF(J30:U30,">0") -> 5 | Y30: =ROUNDUP(W30,0) -> 6
A31: 27 | B31: ERMILGEN RIAÑO | E31: BOGOTA | G31: 100000 | H31: EFECTIVO | I31: CREDITO | J31: 0 | K31: 0 | L31: 0 | M31: 0 | N31: 0 | O31: 0 | P31: 0 | Q31: 0 | R31: 0 | V31: =SUM(J31:U31) -> 0 | W31: =V31/400000 -> 0 | X31: =COUNTIF(J31:U31,">0") -> 0 | Y31: =ROUNDUP(W31,0) -> 0
A32: 28 | B32: ESTEBAN ISAZA MUÑOZ | C32: 88230239 | D32: 3123933769 | E32: PAMPLONA | F32: 1 | G32: 10045000 | H32: BCOL AHO 2 | I32: CREDITO | J32: 1600000 | K32: 1600000 | L32: 1400000 | M32: 1200000 | N32: 1200000 | O32: 1200000 | P32: 1200000 | Q32: 1200000 | R32: 1200000 | V32: =SUM(J32:U32) -> 11800000 | W32: =V32/400000 -> 29.5 | X32: =COUNTIF(J32:U32,">0") -> 9 | Y32: =ROUNDUP(W32,0) -> 30
A33: 29 | B33: ESTHER TORRES | E33: BOGOTA | G33: 450000 | H33: EFECTIVO | I33: CREDITO | J33: 0 | K33: 0 | L33: 0 | M33: 0 | N33: 0 | O33: 0 | P33: 0 | Q33: 0 | R33: 0 | V33: =SUM(J33:U33) -> 0 | W33: =V33/400000 -> 0 | X33: =COUNTIF(J33:U33,">0") -> 0 | Y33: =ROUNDUP(W33,0) -> 0
A34: 30 | B34: EUSEBIO MONTES | F34: 1 | G34: 0 | H34: No Registra | I34: CREDITO | J34: 0 | K34: 0 | L34: 0 | M34: 0 | N34: 0 | O34: 0 | P34: 0 | Q34: 0 | R34: 0 | V34: =SUM(J34:U34) -> 0 | W34: =V34/400000 -> 0 | X34: =COUNTIF(J34:U34,">0") -> 0 | Y34: =ROUNDUP(W34,0) -> 0
A35: 31 | B35: FLOR ACUÑA | E35: BOGOTA | G35: 400000 | H35: BCOL AHO | I35: CREDITO | J35: 0 | K35: 0 | L35: 0 | M35: 0 | N35: 0 | O35: 0 | P35: 0 | Q35: 0 | R35: 0 | V35: =SUM(J35:U35) -> 0 | W35: =V35/400000 -> 0 | X35: =COUNTIF(J35:U35,">0") -> 0 | Y35: =ROUNDUP(W35,0) -> 0
A36: 32 | B36: FLOR SALAMANCA | C36: 23963745 | D36: 3142385522 | E36: BOGOTA | F36: 2 | G36: 21600000 | H36: BCOL AHO-EF | I36: CREDITO | J36: 3600000 | K36: 3600000 | L36: 3600000 | M36: 5600000 | N36: 3600000 | O36: 3600000 | P36: 3600000 | Q36: 3600000 | R36: 4000000 | V36: =SUM(J36:U36) -> 34800000 | W36: =V36/400000 -> 87 | X36: =COUNTIF(J36:U36,">0") -> 9 | Y36: =ROUNDUP(W36,0) -> 87
A37: 33 | B37: FRANCISCO VILLAMIL | E37: BOGOTA | G37: 2200000 | H37: EFECTIVO | I37: CREDITO | J37: 400000 | K37: 400000 | L37: 400000 | M37: 400000 | N37: 400000 | O37: 400000 | P37: 400000 | Q37: 400000 | R37: 400000 | V37: =SUM(J37:U37) -> 3600000 | W37: =V37/400000 -> 9 | X37: =COUNTIF(J37:U37,">0") -> 9 | Y37: =ROUNDUP(W37,0) -> 9
A38: 34 | B38: FREIMAN JAIMES | C38: 13177594 | D38: 3107951023 | E38: OCAÑA | F38: 1 | G38: 800000 | H38: No Registra | I38: CREDITO | J38: 0 | K38: 0 | L38: 400000 | M38: 0 | N38: 400000 | O38: 0 | P38: 800000 | Q38: 400000 | R38: 600000 | V38: =SUM(J38:U38) -> 2600000 | W38: =V38/400000 -> 6.5 | X38: =COUNTIF(J38:U38,">0") -> 5 | Y38: =ROUNDUP(W38,0) -> 7
A39: 35 | B39: GISEL DANIELA GUTIERREZ MURILLO | G39: 1200000 | H39: BCOL AHO | I39: CREDITO | J39: 0 | K39: 0 | L39: 0 | M39: 0 | N39: 0 | O39: 0 | P39: 0 | Q39: 0 | R39: 0 | V39: =SUM(J39:U39) -> 0 | W39: =V39/400000 -> 0 | X39: =COUNTIF(J39:U39,">0") -> 0 | Y39: =ROUNDUP(W39,0) -> 0
A40: 36 | B40: GUILLERMO MONSALVE | C40: 4803428 | D40: 3009838761 | E40: SINCELEJO | G40: 4400000 | H40: BCOL AHO | I40: CREDITO | J40: 0 | K40: 1600000 | L40: 1600000 | M40: 0 | N40: 1600000 | O40: 1600000 | P40: 1600000 | Q40: 1600000 | R40: 1600000 | V40: =SUM(J40:U40) -> 11200000 | W40: =V40/400000 -> 28 | X40: =COUNTIF(J40:U40,">0") -> 7 | Y40: =ROUNDUP(W40,0) -> 28
A41: 37 | B41: HERMES PATIÑO | C41: 93206783 | D41: 3125188563 | E41: SINCELEJO | G41: 6000000 | H41: BCOL AHO | I41: CREDITO | J41: 0 | K41: 800000 | L41: 800000 | M41: 0 | N41: 0 | O41: 800000 | P41: 800000 | Q41: 800000 | R41: 800000 | V41: =SUM(J41:U41) -> 4800000 | W41: =V41/400000 -> 12 | X41: =COUNTIF(J41:U41,">0") -> 6 | Y41: =ROUNDUP(W41,0) -> 12
A42: 38 | B42: HUMBERTO OSPINO | C42: 72147202 | D42: 3126317467 | E42: ENVIGADO | G42: 4400000 | H42: BCOL AHO 2 | I42: CREDITO | J42: 0 | K42: 0 | L42: 0 | M42: 400000 | N42: 0 | O42: 0 | P42: 0 | Q42: 1600000 | R42: 0 | V42: =SUM(J42:U42) -> 2000000 | W42: =V42/400000 -> 5 | X42: =COUNTIF(J42:U42,">0") -> 2 | Y42: =ROUNDUP(W42,0) -> 5
A43: 39 | B43: IG. EN PTO. COLOMBIA | E43: Barranquilla | G43: 6522000 | H43: BCOL AHO | I43: CREDITO | J43: 0 | K43: 0 | L43: 0 | M43: 0 | N43: 0 | O43: 0 | P43: 0 | Q43: 0 | R43: 0 | V43: =SUM(J43:U43) -> 0 | W43: =V43/400000 -> 0 | X43: =COUNTIF(J43:U43,">0") -> 0 | Y43: =ROUNDUP(W43,0) -> 0
A44: 40 | B44: IG. EN BARRANQUILLA | C44: 8742974 | D44: 317889812 | E44: BARRANQUILLA | G44: 20208000 | H44: BCOL AHO | I44: CREDITO | J44: 2085000 | K44: 2000000 | L44: 1180000 | M44: 0 | N44: 2140000 | O44: 1430000 | P44: 0 | Q44: 1770000 | R44: 0 | V44: =SUM(J44:U44) -> 10605000 | W44: =V44/400000 -> 26.5125 | X44: =COUNTIF(J44:U44,">0") -> 6 | Y44: =ROUNDUP(W44,0) -> 27
A45: 41 | B45: IG. EN BAYUNCA JAVIER MIRANDA | E45: Bolivar | G45: 600000 | H45: BCOL AHO | I45: CREDITO | J45: 0 | K45: 0 | L45: 0 | M45: 400000 | N45: 0 | O45: 0 | P45: 0 | Q45: 0 | R45: 0 | V45: =SUM(J45:U45) -> 400000 | W45: =V45/400000 -> 1 | X45: =COUNTIF(J45:U45,">0") -> 1 | Y45: =ROUNDUP(W45,0) -> 1
A46: 42 | B46: IG. EN BUCARAMANGA | C46: 900379577 | D46: 31844096518 | E46: BUCARAMANGA | G46: 19725000 | I46: CREDITO | J46: 6000000 | K46: 15000000 | L46: 9000000 | M46: 6000000 | N46: 8800000 | O46: 0 | P46: 5600000 | Q46: 7200000 | R46: 0 | V46: =SUM(J46:U46) -> 57600000 | W46: =V46/400000 -> 144 | X46: =COUNTIF(J46:U46,">0") -> 7 | Y46: =ROUNDUP(W46,0) -> 144
A47: 43 | B47: IG. EN CARTAGO | E47: Cartago | F47: 1 | G47: 4095000 | H47: BCOL AHO | I47: CREDITO | J47: 0 | K47: 1950000 | L47: 400000 | M47: 1900000 | N47: 0 | O47: 0 | P47: 0 | Q47: 0 | R47: 0 | V47: =SUM(J47:U47) -> 4250000 | W47: =V47/400000 -> 10.625 | X47: =COUNTIF(J47:U47,">0") -> 3 | Y47: =ROUNDUP(W47,0) -> 11
A48: 44 | B48: IG. EN CORDOBA | E48: Cordoba | F48: 1 | G48: 12937600 | H48: BCOL AHO 2 | I48: CREDITO | J48: 0 | K48: 6800000 | L48: 7200000 | M48: 7200000 | N48: 8400000 | O48: 0 | P48: 0 | Q48: 0 | R48: 0 | V48: =SUM(J48:U48) -> 29600000 | W48: =V48/400000 -> 74 | X48: =COUNTIF(J48:U48,">0") -> 4 | Y48: =ROUNDUP(W48,0) -> 74
A49: 45 | B49: IG. EN CUCUTA GUSTAVO LEON | C49: 16354014 | D49: 3133884161 | E49: CUCUTA | F49: 1 | G49: 16940000 | H49: BCOL AHO 2 | I49: CREDITO | J49: 800000 | K49: 425000 | L49: 0 | M49: 1600000 | N49: 0 | O49: 800000 | P49: 0 | Q49: 800000 | R49: 0 | V49: =SUM(J49:U49) -> 4425000 | W49: =V49/400000 -> 11.0625 | X49: =COUNTIF(J49:U49,">0") -> 5 | Y49: =ROUNDUP(W49,0) -> 12
A50: 46 | B50: IG. EN DOSQUEBRADAS | E50: Dosquebradas | G50: 2700000 | H50: BCOL AHO | I50: CREDITO | J50: 0 | K50: 0 | L50: 160000 | M50: 70000 | N50: 120000 | O50: 250000 | P50: 270000 | Q50: 170000 | R50: 0 | V50: =SUM(J50:U50) -> 1040000 | W50: =V50/400000 -> 2.6 | X50: =COUNTIF(J50:U50,">0") -> 6 | Y50: =ROUNDUP(W50,0) -> 3
A51: 47 | B51: IG. EN EL D.C. | C51: 900299699 | D51: 3214118979 | E51: BOGOTA | G51: 16800000 | H51: TRASLADO | I51: CREDITO | J51: 800000 | K51: 800000 | L51: 800000 | M51: 800000 | N51: 800000 | O51: 800000 | P51: 800000 | Q51: 800000 | R51: 0 | V51: =SUM(J51:U51) -> 6400000 | W51: =V51/400000 -> 16 | X51: =COUNTIF(J51:U51,">0") -> 8 | Y51: =ROUNDUP(W51,0) -> 16
A52: 48 | B52: IG. EN GIRARDOT | C52: 901892495 | E52: Girardot | G52: 220000 | H52: BCOL AHO 2 | I52: CREDITO | J52: 0 | K52: 0 | L52: 0 | M52: 0 | N52: 400000 | O52: 0 | P52: 800000 | Q52: 0 | R52: 400000 | V52: =SUM(J52:U52) -> 1600000 | W52: =V52/400000 -> 4 | X52: =COUNTIF(J52:U52,">0") -> 3 | Y52: =ROUNDUP(W52,0) -> 4
A53: 49 | B53: IG. EN GIRARDOTA | E53: Girardota | G53: 13600000 | H53: BCOL AHO | I53: CREDITO | J53: 1200000 | K53: 2000000 | L53: 1200000 | M53: 1750000 | N53: 0 | O53: 1500000 | P53: 1200000 | Q53: 1600000 | R53: 0 | V53: =SUM(J53:U53) -> 10450000 | W53: =V53/400000 -> 26.125 | X53: =COUNTIF(J53:U53,">0") -> 7 | Y53: =ROUNDUP(W53,0) -> 27
A54: 50 | B54: IG. EN ITAGUI | E54: Itagui | G54: 3050000 | H54: BCOL AHO | I54: CREDITO | J54: 0 | K54: 0 | L54: 0 | M54: 2470000 | N54: 0 | O54: 0 | P54: 0 | Q54: 0 | R54: 0 | V54: =SUM(J54:U54) -> 2470000 | W54: =V54/400000 -> 6.175 | X54: =COUNTIF(J54:U54,">0") -> 1 | Y54: =ROUNDUP(W54,0) -> 7
A55: 51 | B55: IG. EN ITSMINA | C55: 11809146 | D55: 3136811706 | E55: Itsmina | G55: 9745000 | H55: BCOL AHO | I55: CREDITO | J55: 800000 | K55: 0 | L55: 2400000 | M55: 1200000 | N55: 0 | O55: 1200000 | P55: 2800000 | Q55: 1600000 | R55: 0 | V55: =SUM(J55:U55) -> 10000000 | W55: =V55/400000 -> 25 | X55: =COUNTIF(J55:U55,">0") -> 6 | Y55: =ROUNDUP(W55,0) -> 25
A56: 52 | B56: IG. EN LA MINA | E56: La mina | G56: 1600000 | H56: BCOL AHO | I56: CREDITO | J56: 400000 | K56: 400000 | L56: 0 | M56: 0 | N56: 400000 | O56: 0 | P56: 0 | Q56: 0 | R56: 0 | V56: =SUM(J56:U56) -> 1200000 | W56: =V56/400000 -> 3 | X56: =COUNTIF(J56:U56,">0") -> 3 | Y56: =ROUNDUP(W56,0) -> 3
A57: 53 | B57: IG. EN MALAMBO | E57: Malambo | F57: 1 | G57: 2285000 | H57: BCOL AHO 2 | I57: CREDITO | J57: 400000 | K57: 0 | L57: 0 | M57: 400000 | N57: 400000 | O57: 0 | P57: 0 | Q57: 400000 | R57: 0 | V57: =SUM(J57:U57) -> 1600000 | W57: =V57/400000 -> 4 | X57: =COUNTIF(J57:U57,">0") -> 4 | Y57: =ROUNDUP(W57,0) -> 4
A58: 54 | B58: IG. EN MEDELLIN | E58: Medellin | G58: 2800000 | H58: BCOL AHO | I58: CREDITO | J58: 0 | K58: 0 | L58: 400000 | M58: 0 | N58: 0 | O58: 0 | P58: 0 | Q58: 400000 | R58: 400000 | V58: =SUM(J58:U58) -> 1200000 | W58: =V58/400000 -> 3 | X58: =COUNTIF(J58:U58,">0") -> 3 | Y58: =ROUNDUP(W58,0) -> 3
A59: 55 | B59: IG. EN NEIVA | E59: Neiva | G59: 9200000 | H59: BCOL AHO | I59: CREDITO | J59: 600000 | K59: 600000 | L59: 2000000 | M59: 0 | N59: 0 | O59: 600000 | P59: 3600000 | Q59: 3600000 | R59: 800000 | V59: =SUM(J59:U59) -> 11800000 | W59: =V59/400000 -> 29.5 | X59: =COUNTIF(J59:U59,">0") -> 7 | Y59: =ROUNDUP(W59,0) -> 30
A60: 56 | B60: IG. EN OCAÑA | C60: 900420427-8 | E60: Ocaña | G60: 11200000 | H60: BCOL AHO | I60: CREDITO | J60: 0 | K60: 1200000 | L60: 2000000 | M60: 1600000 | N60: 0 | O60: 800000 | P60: 1200000 | Q60: 0 | R60: 0 | V60: =SUM(J60:U60) -> 6800000 | W60: =V60/400000 -> 17 | X60: =COUNTIF(J60:U60,">0") -> 5 | Y60: =ROUNDUP(W60,0) -> 17
A61: 57 | B61: IG. EN PEREIRA | E61: Pereira | F61: 2 | G61: 14800000 | H61: BCOL AHO 2 | I61: CREDITO | J61: 0 | K61: 400000 | L61: 1200000 | M61: 400000 | N61: 0 | O61: 1600000 | P61: 900000 | Q61: 400000 | R61: 2000000 | V61: =SUM(J61:U61) -> 6900000 | W61: =V61/400000 -> 17.25 | X61: =COUNTIF(J61:U61,">0") -> 7 | Y61: =ROUNDUP(W61,0) -> 18
A62: 58 | B62: IG. EN QUIBDO | C62: 900371129 | D62: 3216464514 | E62: QUIBDO | G62: 2400000 | H62: BCOL AHO | I62: CREDITO | J62: 800000 | K62: 4800000 | L62: 1200000 | M62: 400000 | N62: 400000 | O62: 400000 | P62: 800000 | Q62: 0 | R62: 0 | V62: =SUM(J62:U62) -> 8800000 | W62: =V62/400000 -> 22 | X62: =COUNTIF(J62:U62,">0") -> 7 | Y62: =ROUNDUP(W62,0) -> 22
A63: 59 | B63: IG. EN RIOHACHA | E63: Riohacha | G63: 440000 | H63: BCOL AHO | I63: CREDITO | J63: 0 | K63: 0 | L63: 0 | M63: 0 | N63: 0 | O63: 0 | P63: 0 | Q63: 0 | R63: 0 | V63: =SUM(J63:U63) -> 0 | W63: =V63/400000 -> 0 | X63: =COUNTIF(J63:U63,">0") -> 0 | Y63: =ROUNDUP(W63,0) -> 0
A64: 60 | B64: IG. EN RIVERA | E64: Rivera | G64: 1250000 | H64: BCOL AHO | I64: CREDITO | J64: 0 | K64: 100000 | L64: 0 | M64: 100000 | N64: 400000 | O64: 0 | P64: 0 | Q64: 240000 | R64: 310000 | V64: =SUM(J64:U64) -> 1150000 | W64: =V64/400000 -> 2.875 | X64: =COUNTIF(J64:U64,">0") -> 5 | Y64: =ROUNDUP(W64,0) -> 3
A65: 61 | B65: IG. EN SINCELEJO | E65: Sincelejo | G65: 1400000 | H65: BCOL AHO | I65: CREDITO | J65: 400000 | K65: 400000 | L65: 0 | M65: 400000 | N65: 0 | O65: 0 | P65: 0 | Q65: 0 | R65: 0 | V65: =SUM(J65:U65) -> 1200000 | W65: =V65/400000 -> 3 | X65: =COUNTIF(J65:U65,">0") -> 3 | Y65: =ROUNDUP(W65,0) -> 3
A66: 62 | B66: IG. EN SOLEDAD | E66: Soledad | G66: 9524000 | H66: BCOL AHO | I66: CREDITO | J66: 0 | K66: 0 | L66: 0 | M66: 2800000 | N66: 0 | O66: 1600000 | P66: 1600000 | Q66: 1600000 | R66: 0 | V66: =SUM(J66:U66) -> 7600000 | W66: =V66/400000 -> 19 | X66: =COUNTIF(J66:U66,">0") -> 4 | Y66: =ROUNDUP(W66,0) -> 19
A67: 63 | B67: IG. EN STA MARTA JOSE LUIS TERAN | C67: 900-380-4931 | D67: 3233712038 | E67: Sta marta | G67: 7266250 | H67: BCOL AHO | I67: CREDITO | J67: 2130000 | K67: 2135000 | L67: 2080000 | M67: 0 | N67: 1910000 | O67: 2070000 | P67: 2100000 | Q67: 1900000 | R67: 2280000 | V67: =SUM(J67:U67) -> 16605000 | W67: =V67/400000 -> 41.5125 | X67: =COUNTIF(J67:U67,">0") -> 8 | Y67: =ROUNDUP(W67,0) -> 42
A68: 64 | B68: IG. EN SUAN | E68: Suan | G68: 3645000 | H68: BCOL AHO | I68: CREDITO | J68: 570000 | K68: 400000 | L68: 0 | M68: 0 | N68: 0 | O68: 0 | P68: 400000 | Q68: 400000 | R68: 400000 | V68: =SUM(J68:U68) -> 2170000 | W68: =V68/400000 -> 5.425 | X68: =COUNTIF(J68:U68,">0") -> 5 | Y68: =ROUNDUP(W68,0) -> 6
A69: 65 | B69: IG. EN TURBACO | E69: Turbaco | G69: 5704059 | H69: BCOL AHO | I69: CREDITO | J69: 0 | K69: 2254243 | L69: 0 | M69: 0 | N69: 0 | O69: 0 | P69: 0 | Q69: 0 | R69: 0 | V69: =SUM(J69:U69) -> 2254243 | W69: =V69/400000 -> 5.6356075 | X69: =COUNTIF(J69:U69,">0") -> 1 | Y69: =ROUNDUP(W69,0) -> 6
A70: 66 | B70: IG. EN UBATE | C70: 900384157 | D70: 3103160465 | E70: Ubate | G70: 18700000 | H70: BCOL AHO | I70: CREDITO | J70: 4800000 | K70: 5440000 | L70: 5000000 | M70: 6000000 | N70: 0 | O70: 5060000 | P70: 4300000 | Q70: 850000 | R70: 720000 | V70: =SUM(J70:U70) -> 32170000 | W70: =V70/400000 -> 80.425 | X70: =COUNTIF(J70:U70,">0") -> 8 | Y70: =ROUNDUP(W70,0) -> 81
A71: 67 | B71: IG. EN VALLEDUPAR | C71: 900406774 | E71: Valledupar | G71: 62180000 | H71: BCOL AHO | I71: CREDITO | J71: 0 | K71: 10006000 | L71: 0 | M71: 12000000 | N71: 12400000 | O71: 10214000 | P71: 10000000 | Q71: 11000000 | R71: 0 | V71: =SUM(J71:U71) -> 65620000 | W71: =V71/400000 -> 164.05 | X71: =COUNTIF(J71:U71,">0") -> 6 | Y71: =ROUNDUP(W71,0) -> 165
A72: 68 | B72: IG. EN VILLAVICENCIO | E72: VILLAVICENCIO | G72: 2110000 | H72: BCOL AHO | I72: CREDITO | J72: 0 | K72: 0 | L72: 0 | M72: 0 | N72: 0 | O72: 0 | P72: 0 | Q72: 0 | R72: 0 | V72: =SUM(J72:U72) -> 0 | W72: =V72/400000 -> 0 | X72: =COUNTIF(J72:U72,">0") -> 0 | Y72: =ROUNDUP(W72,0) -> 0
A73: 69 | B73: IG. EN VILLA DEL ROSARIO | E73: V. ROSARIO | G73: 7580000 | H73: BCOL AHO | I73: CREDITO | J73: 1200000 | K73: 400000 | L73: 400000 | M73: 400000 | N73: 0 | O73: 400000 | P73: 400000 | Q73: 0 | R73: 0 | V73: =SUM(J73:U73) -> 3200000 | W73: =V73/400000 -> 8 | X73: =COUNTIF(J73:U73,">0") -> 6 | Y73: =ROUNDUP(W73,0) -> 8
A74: 70 | B74: IG. EN TULUA GUILLERMO HERRERA MURCIA | E74: Tulua | G74: 2800000 | H74: BCOL AHO | I74: CREDITO | J74: 0 | K74: 0 | L74: 400000 | M74: 0 | N74: 0 | O74: 0 | P74: 800000 | Q74: 400000 | R74: 0 | V74: =SUM(J74:U74) -> 1600000 | W74: =V74/400000 -> 4 | X74: =COUNTIF(J74:U74,">0") -> 3 | Y74: =ROUNDUP(W74,0) -> 4
A75: 71 | B75: IG. EN ARMENIA | E75: Armenia | G75: 3600000 | I75: CREDITO | J75: 0 | K75: 0 | L75: 0 | M75: 0 | N75: 0 | O75: 0 | P75: 800000 | Q75: 0 | R75: 0 | V75: =SUM(J75:U75) -> 800000 | W75: =V75/400000 -> 2 | X75: =COUNTIF(J75:U75,">0") -> 1 | Y75: =ROUNDUP(W75,0) -> 2
A76: 72 | B76: IG. EN CARTAGENA | E76: CARTAGENA | G76: 12090000 | I76: CREDITO | J76: 0 | K76: 2000000 | L76: 800000 | M76: 0 | N76: 2000000 | O76: 2400000 | P76: 2400000 | Q76: 2000000 | R76: 2000000 | V76: =SUM(J76:U76) -> 13600000 | W76: =V76/400000 -> 34 | X76: =COUNTIF(J76:U76,">0") -> 7 | Y76: =ROUNDUP(W76,0) -> 34
A77: 73 | B77: IG. EN LOS PATIOS | C77: 900474240-1 | D77: 3222616473 | E77: LOS PATIOS | G77: 8200000 | I77: CREDITO | J77: 800000 | K77: 800000 | L77: 800000 | M77: 800000 | N77: 800000 | O77: 800000 | P77: 800000 | Q77: 1200000 | R77: 800000 | V77: =SUM(J77:U77) -> 7600000 | W77: =V77/400000 -> 19 | X77: =COUNTIF(J77:U77,">0") -> 9 | Y77: =ROUNDUP(W77,0) -> 19
A78: 74 | B78: IG. EN MONTERIA y STA LUCIA | E78: MONTERIA | F78: 1 | G78: 14000000 | H78: BCOL AHO 2 | I78: CREDITO | J78: 7200000 | K78: 0 | L78: 0 | M78: 0 | N78: 0 | O78: 8000000 | P78: 8000000 | Q78: 0 | R78: 0 | V78: =SUM(J78:U78) -> 23200000 | W78: =V78/400000 -> 58 | X78: =COUNTIF(J78:U78,">0") -> 3 | Y78: =ROUNDUP(W78,0) -> 58
A79: 75 | B79: INDIRA ESTRADA | E79: BOGOTA | G79: 200000 | H79: EFECTIVO | I79: CREDITO | J79: 0 | K79: 0 | L79: 0 | M79: 0 | N79: 0 | O79: 0 | P79: 0 | Q79: 0 | R79: 0 | V79: =SUM(J79:U79) -> 0 | W79: =V79/400000 -> 0 | X79: =COUNTIF(J79:U79,">0") -> 0 | Y79: =ROUNDUP(W79,0) -> 0
A80: 76 | B80: ISABEL TORRIJAS | E80: Medellin | F80: 1 | G80: 50000 | H80: BCOL AHO 2 | I80: CREDITO | J80: 0 | K80: 0 | L80: 0 | M80: 0 | N80: 0 | O80: 0 | P80: 0 | Q80: 0 | R80: 0 | V80: =SUM(J80:U80) -> 0 | W80: =V80/400000 -> 0 | X80: =COUNTIF(J80:U80,">0") -> 0 | Y80: =ROUNDUP(W80,0) -> 0
A81: 77 | B81: JAMES GAMBOA | E81: BOGOTA | G81: 1762000 | H81: BCOL AHO | I81: CREDITO | J81: 0 | K81: 0 | L81: 0 | M81: 0 | N81: 0 | O81: 0 | P81: 0 | Q81: 0 | R81: 0 | V81: =SUM(J81:U81) -> 0 | W81: =V81/400000 -> 0 | X81: =COUNTIF(J81:U81,">0") -> 0 | Y81: =ROUNDUP(W81,0) -> 0
A82: 78 | B82: JAVIER BLOOM | E82: Medellin | G82: 800000 | H82: BCOL AHO | I82: CREDITO | J82: 0 | K82: 0 | L82: 0 | M82: 420982 | N82: 0 | O82: 0 | P82: 0 | Q82: 0 | R82: 0 | V82: =SUM(J82:U82) -> 420982 | W82: =V82/400000 -> 1.052455 | X82: =COUNTIF(J82:U82,">0") -> 1 | Y82: =ROUNDUP(W82,0) -> 2
A83: 79 | B83: JEAN CARLOS BLANCO | C83: 1093783625 | D83: 3223202421 | E83: LOS PATIOS | G83: 6000000 | H83: BCOL AHO | I83: CREDITO | J83: 400000 | K83: 1600000 | L83: 800000 | M83: 1200000 | N83: 1200000 | O83: 1200000 | P83: 1200000 | Q83: 1200000 | R83: 1200000 | V83: =SUM(J83:U83) -> 10000000 | W83: =V83/400000 -> 25 | X83: =COUNTIF(J83:U83,">0") -> 9 | Y83: =ROUNDUP(W83,0) -> 25
A84: 80 | B84: JHOJAS QUINTERO | C84: 79477468 | D84: 3185861284 | E84: SOACHA | G84: 4240000 | H84: BCOL AHO | I84: CREDITO | J84: 400000 | K84: 400000 | L84: 300000 | M84: 0 | N84: 300000 | O84: 300000 | P84: 400000 | Q84: 300000 | R84: 600000 | V84: =SUM(J84:U84) -> 3000000 | W84: =V84/400000 -> 7.5 | X84: =COUNTIF(J84:U84,">0") -> 8 | Y84: =ROUNDUP(W84,0) -> 8
A85: 81 | B85: JHON ROJAS | C85: 12135690 | E85: Neiva | G85: 1300000 | H85: BCOL AHO 2 | I85: CREDITO | J85: 401000 | K85: 0 | L85: 0 | M85: 1000000 | N85: 0 | O85: 400000 | P85: 800000 | Q85: 0 | R85: 800000 | V85: =SUM(J85:U85) -> 3401000 | W85: =V85/400000 -> 8.5025 | X85: =COUNTIF(J85:U85,">0") -> 5 | Y85: =ROUNDUP(W85,0) -> 9
A86: 82 | B86: JOEL ARIAS | E86: Medellin | G86: 420000 | H86: BCOL AHO | I86: CREDITO | J86: 0 | K86: 0 | L86: 0 | M86: 0 | N86: 0 | O86: 0 | P86: 0 | Q86: 0 | R86: 0 | V86: =SUM(J86:U86) -> 0 | W86: =V86/400000 -> 0 | X86: =COUNTIF(J86:U86,">0") -> 0 | Y86: =ROUNDUP(W86,0) -> 0
A87: 83 | B87: JOHAN GOMEZ ZAPATA | C87: 1128400756 | D87: 3043640493 | E87: MEDELLIN | G87: 2000000 | H87: BCOL AHO | I87: CREDITO | J87: 0 | K87: 0 | L87: 0 | M87: 400000 | N87: 0 | O87: 0 | P87: 0 | Q87: 0 | R87: 0 | V87: =SUM(J87:U87) -> 400000 | W87: =V87/400000 -> 1 | X87: =COUNTIF(J87:U87,">0") -> 1 | Y87: =ROUNDUP(W87,0) -> 1
A88: 84 | B88: JOHANA SANTIESTEBAN | G88: 4000000 | I88: CREDITO | J88: 0 | K88: 0 | L88: 0 | M88: 0 | N88: 0 | O88: 0 | P88: 0 | Q88: 0 | R88: 0 | V88: =SUM(J88:U88) -> 0 | W88: =V88/400000 -> 0 | X88: =COUNTIF(J88:U88,">0") -> 0 | Y88: =ROUNDUP(W88,0) -> 0
A89: 85 | B89: JORGE GOMEZ | C89: 13838106 | D89: 3158359949 | E89: BUCARAMANGA | F89: 2 | G89: 4300000 | H89: No Registra | I89: CREDITO | J89: 0 | K89: 0 | L89: 0 | M89: 0 | N89: 0 | O89: 0 | P89: 0 | Q89: 0 | R89: 0 | V89: =SUM(J89:U89) -> 0 | W89: =V89/400000 -> 0 | X89: =COUNTIF(J89:U89,">0") -> 0 | Y89: =ROUNDUP(W89,0) -> 0
A90: 86 | B90: JORGE LUIS BARRIOS | C90: 91249777 | G90: 3600000 | H90: BCOL AHO | I90: CREDITO | J90: 0 | K90: 0 | L90: 0 | M90: 0 | N90: 0 | O90: 0 | P90: 0 | Q90: 0 | R90: 0 | V90: =SUM(J90:U90) -> 0 | W90: =V90/400000 -> 0 | X90: =COUNTIF(J90:U90,">0") -> 0 | Y90: =ROUNDUP(W90,0) -> 0
A91: 87 | B91: JORGE RODRIGUEZ | G91: 400000 | H91: BCOL AHO | I91: CREDITO | J91: 0 | K91: 0 | L91: 0 | M91: 0 | N91: 0 | O91: 0 | P91: 0 | Q91: 0 | R91: 0 | V91: =SUM(J91:U91) -> 0 | W91: =V91/400000 -> 0 | X91: =COUNTIF(J91:U91,">0") -> 0 | Y91: =ROUNDUP(W91,0) -> 0
A92: 88 | B92: JOSE ELBERT GARZON | G92: 860000 | H92: BCOL AHO | I92: CREDITO | J92: 0 | K92: 0 | L92: 0 | M92: 0 | N92: 0 | O92: 0 | P92: 0 | Q92: 0 | R92: 0 | V92: =SUM(J92:U92) -> 0 | W92: =V92/400000 -> 0 | X92: =COUNTIF(J92:U92,">0") -> 0 | Y92: =ROUNDUP(W92,0) -> 0
A93: 89 | B93: JOSE ENRIQUE ARIAS PEREZ | C93: 15374739 | E93: Medellin | G93: 4140000 | H93: BCOL AHO 2 | I93: CREDITO | J93: 0 | K93: 0 | L93: 800000 | M93: 400000 | N93: 0 | O93: 400000 | P93: 0 | Q93: 0 | R93: 0 | V93: =SUM(J93:U93) -> 1600000 | W93: =V93/400000 -> 4 | X93: =COUNTIF(J93:U93,">0") -> 3 | Y93: =ROUNDUP(W93,0) -> 4
A94: 90 | B94: JOSE GONZALEZ | F94: 1 | G94: 400000 | H94: BCOL AHO | I94: CREDITO | J94: 0 | K94: 0 | L94: 0 | M94: 0 | N94: 0 | O94: 0 | P94: 0 | Q94: 0 | R94: 0 | V94: =SUM(J94:U94) -> 0 | W94: =V94/400000 -> 0 | X94: =COUNTIF(J94:U94,">0") -> 0 | Y94: =ROUNDUP(W94,0) -> 0
A95: 91 | B95: JUAN VALENCIA | G95: 1600000 | H95: BCOL AHO 2 | I95: CREDITO | J95: 0 | K95: 0 | L95: 0 | M95: 0 | N95: 0 | O95: 0 | P95: 0 | Q95: 0 | R95: 0 | V95: =SUM(J95:U95) -> 0 | W95: =V95/400000 -> 0 | X95: =COUNTIF(J95:U95,">0") -> 0 | Y95: =ROUNDUP(W95,0) -> 0
A96: 92 | B96: JUAN C. MORENO | C96: 1077426534 | D96: 3113654554 | E96: QUIBDO | F96: 1 | G96: 1600000 | H96: BCOL AHO | I96: CREDITO | J96: 0 | K96: 0 | L96: 0 | M96: 800000 | N96: 0 | O96: 0 | P96: 0 | Q96: 0 | R96: 0 | V96: =SUM(J96:U96) -> 800000 | W96: =V96/400000 -> 2 | X96: =COUNTIF(J96:U96,">0") -> 1 | Y96: =ROUNDUP(W96,0) -> 2
A97: 93 | B97: JUAN GUILLERMO MUÑOZ GIRARDOTA | C97: 70326161 | D97: 3017435330 | E97: Girardota | G97: 1200000 | H97: BCOL AHO | I97: CREDITO | J97: 400000 | K97: 400000 | L97: 400000 | M97: 400000 | N97: 400000 | O97: 400000 | P97: 0 | Q97: 400000 | R97: 0 | V97: =SUM(J97:U97) -> 2800000 | W97: =V97/400000 -> 7 | X97: =COUNTIF(J97:U97,">0") -> 7 | Y97: =ROUNDUP(W97,0) -> 7
A98: 94 | B98: JUAN MINA | E98: Juan Mina | G98: 400000 | I98: CREDITO | J98: 0 | K98: 0 | L98: 0 | M98: 0 | N98: 0 | O98: 0 | P98: 400000 | Q98: 400000 | R98: 0 | V98: =SUM(J98:U98) -> 800000 | W98: =V98/400000 -> 2 | X98: =COUNTIF(J98:U98,">0") -> 2 | Y98: =ROUNDUP(W98,0) -> 2
A99: 95 | B99: JUAN PABLO OLIVELLA | C99: 77037962 | D99: 3108469718 | E99: VALLEDUPAR | G99: 8000000 | H99: BCOL AHO | I99: CREDITO | J99: 2400000 | K99: 2400000 | L99: 0 | M99: 0 | N99: 2400000 | O99: 2400000 | P99: 0 | Q99: 0 | R99: 0 | V99: =SUM(J99:U99) -> 9600000 | W99: =V99/400000 -> 24 | X99: =COUNTIF(J99:U99,">0") -> 4 | Y99: =ROUNDUP(W99,0) -> 24
A100: 96 | B100: JUAN PABLO OLIVELLA (HNO. DONG) | G100: 10000000 | H100: BCOL AHO | I100: CREDITO | J100: 0 | K100: 0 | L100: 0 | M100: 0 | N100: 0 | O100: 0 | P100: 0 | Q100: 0 | R100: 0 | V100: =SUM(J100:U100) -> 0 | W100: =V100/400000 -> 0 | X100: =COUNTIF(J100:U100,">0") -> 0 | Y100: =ROUNDUP(W100,0) -> 0
A101: 97 | B101: JUAN SEBASTIAN MONTES PINZON | G101: 800000 | H101: BCOL AHO | I101: CREDITO | J101: 0 | K101: 0 | L101: 0 | M101: 0 | N101: 0 | O101: 0 | P101: 0 | Q101: 0 | R101: 0 | V101: =SUM(J101:U101) -> 0 | W101: =V101/400000 -> 0 | X101: =COUNTIF(J101:U101,">0") -> 0 | Y101: =ROUNDUP(W101,0) -> 0
A102: 98 | B102: JULIAN CADAVID | F102: 3 | G102: 0 | H102: No Registra | I102: CREDITO | J102: 0 | K102: 0 | L102: 0 | M102: 0 | N102: 0 | O102: 0 | P102: 0 | Q102: 0 | R102: 0 | V102: =SUM(J102:U102) -> 0 | W102: =V102/400000 -> 0 | X102: =COUNTIF(J102:U102,">0") -> 0 | Y102: =ROUNDUP(W102,0) -> 0
...

Sheet Gastos 26
A4: NO. | B4: CLASIF | C4: NOMBRES | D4: NO. IDENTIFICACION | E4: NO. CELULAR | F4: LOCALIDAD | G4: No. Cuotas | H4: SALDO A DIC2024 | I4: FORMA | J4: TIPO DE MOVIMIENTO | K4: ENERO | L4: FEBRERO | M4: MARZO | N4: ABRIL | O4: MAYO | P4: JUNIO | Q4: JULIO | R4: AGOSTO | S4: SEPTIEMBRE | T4: OCTUBRE | U4: NOVIEMBRE | V4: DICIEMBRE | W4: ENERO
A5: 1 | B5: OFRENDA | C5: OFRENDA JORGE LUIS BARRIOS | J5: DEBITO
A6: =A5+1 -> 2 | B6: DEUDA FONDO | C6: DEUDA COLPORTAJE | J6: DEBITO | K6: -6498740
A7: =A6+1 -> 3 | B7: PAC | C7: APOYO CASA PAC | H7: -12000000 | J7: DEBITO
A8: =A7+1 -> 4 | B8: PAC | C8: APOYO CASA PAC | H8: -5231807 | I8: BCOL AHO | J8: DEBITO
A9: =A8+1 -> 5 | B9: PAC | C9: APOYO CASA PAC | H9: -3500000 | I9: BCOL ALHO | J9: DEBITO
A10: =A9+1 -> 6 | B10: CEPEV | C10: APOYO CEPPEV | H10: 0 | I10: BCOL AHO | J10: DEBITO
A11: =A10+1 -> 7 | B11: BRASIL | C11: APOYO HNOS. EN BRASIL | H11: -20000000 | I11: BCOL AHO | J11: DEBITO
A12: =A11+1 -> 8 | B12: PAC | C12: APOYO PERU PAC | J12: DEBITO
A13: =A12+1 -> 9 | B13: PAC | C13: ARRIENDO CASA PAC | H13: 0 | I13: BCOL CTE | J13: DEBITO
A14: =A13+1 -> 10 | B14: PAC | C14: ARRIENDO CASA PAC | H14: 0 | J14: DEBITO
A15: =A14+1 -> 11 | B15: INVERSIONISTAS | C15: COMPRA CELULAR | H15: -6700000 | I15: BCOL AHO | J15: DEBITO
A16: =A15+1 -> 12 | B16: PEDRO D | C16: ENTREGA RESERVA PEDRO DONG | J16: DEBITO
A17: =A16+1 -> 13 | B17: EAV | C17: ENVIO EAV | H17: -12300000 | J17: DEBITO
A18: =A17+1 -> 14 | B18: COSTA RICA | C18: OBRA COSTA RICA | J18: DEBITO
A19: =A18+1 -> 15 | B19: OFRENDA | C19: OFRENDA A JONES COSTA | H19: -400000 | I19: BCOL AHO | J19: DEBITO
A20: =A19+1 -> 16 | B20: PAC | C20: PAGO DEUDA ARRIENDO PAC | H20: 0 | I20: BCOL AHO | J20: DEBITO
A21: =A20+1 -> 17 | B21: CUBA | C21: VIATICOS CUBA | I21: BCOL AHO | J21: DEBITO
A22: =A21+1 -> 18 | B22: OFRENDA | C22: VIATICOS EUROPA DAVID MAESTRE | H22: -6413915 | J22: DEBITO
A23: =A22+1 -> 19 | B23: OFRENDA | C23: VIATICOS JONES | H23: 0 | I23: EFECTIVO | J23: DEBITO
A24: =A23+1 -> 20 | B24: EAV | C24: VIATICOS EAV DE RESERVA PEDRO D | I24: BCOL AHO | J24: DEBITO
A25: =A24+1 -> 21 | B25: IVPT | C25: GASTOS IVPT | H25: 0 | I25: BCOL AHO | J25: DEBITO
A26: =A25+1 -> 22 | B26: PANAMA | C26: ENTREGA A DAVID MAESTRE PANAMA | J26: DEBITO
A27: =A26+1 -> 23 | B27: VUELOS | C27: ENTREGA A DAVID M RESERVA PEDRO | J27: DEBITO
A28: =A27+1 -> 24 | B28: CEPEV | C28: APOYO CENA CEPPEV | J28: DEBITO
A29: =A28+1 -> 25 | B29: PEDRO D | C29: ENTREGA RESERVA PEDRO DONG | J29: DEBITO
A30: =A29+1 -> 26 | B30: PANAMA | C30: APOYO PAC PANAMA | J30: DEBITO
A31: =A30+1 -> 27 | B31: VUELOS | C31: ENTREGA DAVID MIRANDA RESERVA PD | J31: DEBITO
A32: =A31+1 -> 28 | B32: VUELOS | C32: ENTREGA DAVID MIRANDA RESERVA PD | J32: DEBITO
A33: =A32+1 -> 29 | B33: PANAMA | C33: APOYO PAC PANAMA | J33: DEBITO
A34: =A33+1 -> 30 | B34: PEDRO D | C34: ENTREGA RESERVA PEDRO DONG | J34: DEBITO
A35: =A34+1 -> 31 | B35: PANAMA | C35: LUIS MIGUEL NARANJO APOYO PANAMA | J35: DEBITO
A36: =A35+1 -> 32 | B36: VUELOS | C36: VIATICOS COLPORTORES | J36: DEBITO
A37: =A36+1 -> 33 | B37: OFRENDA | C37: APOYO LUIS GABRIEL BRASIL | J37: DEBITO
... A54: =A53+1 -> 50 | B54: PANAMA | C54: LUIS MIGUEL NARANJO APOYO PANAMA | J54: DEBITO
A55: 51 | B55: CUBA | C55: APOYO CUBA | J55: DEBITO
A56: 52 | B56: INVERSIONISTAS | C56: MOVIL INVERSIONISTAS | J56: DEBITO
A57: 53 | B57: VUELOS | C57: DAVID MIRANDA VUELOS COLPORTORES | J57: DEBITO
A58: 54 | B58: INVERSIONISTAS | C58: MOVIL INVERSIONISTAS | J58: DEBITO | K58: -100800
A59: 55 | B59: PANAMA | C59: LUIS MIGUEL NARANJO APOYO PANAMA | J59: DEBITO
A60: 56 | B60: VALLEDUPAR | C60: IG. EN VALLEDUPAR APOYO COLPORTOR | J60: DEBITO
A61: 57 | B61: CEPEV | C61: IG. EN BUCARAM/APOYO | J61: DEBITO
A62: 58 | B62: PEDRO D | C62: ENTREGA PEDRO DONG | J62: DEBITO
A63: 59 | B63: PANAMA | C63: TRAMITES Y APOYO PANAMA LUIS MIGUEL N | J63: DEBITO | K63: -7624000
A64: 60 | B64: INTERNO | C64: CUOTAS PARTICIPACION BRASIL | J64: DEBITO | K64: 0
A65: 61 | B65: CUBA | C65: OFRENDA HNOS. CUBA | J65: DEBITO | K65: 0
A66: 62 | B66: VUELOS | C66: DAVID MIRANDA VIAJES VARIOS | J66: DEBITO | L66: -4568732
A67: 63 | B67: PANAMA | C67: LUIS MIGUEL NARANJO VIAJES APOYO PANAMA | J67: DEBITO | L67: -6176000
A68: 64 | B68: PEDRO D | C68: ENTREGA RESERVA PEDRO DONG | J68: DEBITO | L68: -60897000
A69: 65 | B69: VUELOS | C69: DAVID MIRANDA VIATICOS VARIOS | J69: DEBITO | L69: -19035649
A70: 66 | B70: JULIO S | C70: JULIO SANCHEZ VIATICOS PERU | J70: DEBITO | L70: -
A71: 67 | B71: INVERSIONISTAS | C71: CLARO PAGO CELULAR INVERSIONISTAS | J71: DEBITO | L71: 0 | M71: -55800
A72: 68 | B72: PANAMA | C72: LUIS MIGUEL NARANJO APOYO PANAMA | J72: DEBITO | M72: -1000000
A73: 69 | B73: VUELOS | C73: DAVID MIRANDA VIATICOS VARIOS | J73: DEBITO | M73: -6843223
A74: 70 | B74: PANAMA | C74: LUIS MIGUEL NARANJO DOCUMENTOS | J74: DEBITO | M74: -6858000
A75: 71 | B75: PAC | C75: DAVID MIRANDA VEHICULO CEPPEV | J75: DEBITO | M75: -40000000
A76: 72 | B76: PANAMA | C76: LUIS MIGUEL NARANJO APOYO PANAMA | J76: DEBITO | M76: 1000000
A77: 73 | B77: PANAMA | C77: LUIS MIGUEL NARANJO APOYO PANAMA | J77: DEBITO | N77: -1000000
A78: 74 | B78: VUELOS | C78: DAVID MIRANDA VUELOS BRASIL, PANAMA | J78: DEBITO | N78: -18289360
A79: 75 | B79: GUATEMALA | C79: ARIANA LOZANO DOCUMENTOS COLPOR-GUATEMALA | J79: DEBITO | N79: -5535000
A80: 76 | B80: PEDRO D | C80: ENTREGA RESERVA PEDRO DONG | J80: DEBITO | N80: -33600000
A81: 77 | B81: INVERSIONISTAS | C81: MOVIL INVERSIONISTAS | J81: DEBITO | N81: -46300
A82: 78 | B82: VUELOS | C82: ANTONIO SAGBINI VUELOS CHILE BOGOTA | J82: DEBITO | N82: -6886290
A83: 79 | B83: VUELOS | C83: DAVID MIRANDA VUELOS OBRA | J83: DEBITO | N83: -3460000
A84: 80 | B84: PANAMA | C84: LUIS MIGUEL NARANJO APOYO PANAMA | J84: DEBITO | N84: -1000000
A85: 81 | B85: INVERSIONISTAS | C85: MOVIL INVERSIONISTAS | J85: DEBITO | O85: -55300
A86: 82 | B86: PEDRO D | C86: ENTREGA RESERVA PEDRO DONG | J86: DEBITO | O86: -67327516
A87: 83 | B87: PANAMA | C87: LUIS MIGUEL NARANJO APOYO PANAMA | J87: DEBITO | P87: -1000000
A88: 84 | B88: INVERSIONISTAS | C88: MOVIL INVERSIONISTAS | J88: DEBITO | P88: -46300
A89: 85 | B89: VUELOS | C89: DAVID MIRANDA VUELOS VARIOS OBRA | J89: DEBITO | P89: -9219069
A90: 86 | B90: PANAMA | C90: LUIS MIGUEL NARANJO APOYO PANAMA | J90: DEBITO | P90: -17920422
A91: 87 | B91: PEDRO D | C91: ENTREGA RESERVA PEDRO DONG | J91: DEBITO | P91: -37882873
A92: 88 | B92: PANAMA | C92: VUELOS PANAMA JULIO SANCHEZ | J92: DEBITO | P92: -5699280
A93: 89 | B93: PANAMA | C93: LUIS MIGUEL NARANJO APOYO PANAMA | J93: DEBITO | P93: -3475000
B94: PANAMA | C94: LUILS MIGUEL NARANJO APOYO PANAMA | J94: DEBITO | Q94: -1000000
B95: BRASIL | C95: IVPT OFRENDA GENESIS | J95: DEBITO | Q95: -15487675
B96: PEDRO D | C96: ENTREGA RESERVA PEDRO DONG | J96: DEBITO | Q96: -41493250
B97: VUELOS | C97: DAVID MIRANDA VUELOS QUITO | J97: DEBITO | Q97: -1879708
B98: INVERSIONISTAS | C98: MOVIL INVERSIONISTAS | J98: DEBITO | Q98: -55300
B99: OTROS | C99: EMANUEL FLORES VALENCIA APOYO | J99: DEBITO | Q99: -5000000
B100: OTROS | C100: APOYO A CONFINES | J100: DEBITO | R100: -4000000
B101: PANAMA | C101: LUIS MIGUEL NARANJO APOYO PANAMA | J101: DEBITO | R101: -9661190
B102: VUELOS | C102: DAVID MIRANDA VUELOS | J102: DEBITO | R102: -1861000
B103: PEDRO D | C103: ENTREGA FONDO PEDRO DONG | J103: DEBITO | R103: -39128787
B104: BRASIL | C104: ENTREGA APOYO CENTRO CONVENCIONES IVPT | J104: DEBITO | R104: -5718695
B105: OBRA COL | C105: APOYO VARIOS OBRA COLOMBIA | J105: DEBITO | R105: -9000000
B106: INVERSIONISTAS | C106: MOVIL INVERSIONISTAS | J106: DEBITO | R106: -46300
B107: CEPEV | C107: APYO PERFECCIONAMIENTO CEPPEV Y APOYO ARR | J107: DEBITO | R107: -15000000
B108: PANAMA | C108: APOYO PANAMA MAXIMO EVANGELISTA | J108: DEBITO | R108: -5137100
B109: CEPEV | C109: IGLESIA EN BUCARAMANGA APOYO PERFECCIONAMIENTO | J109: DEBITO | R109: -5000000
B110: PANAMA | C110: LUIS MIGUEL NARANJO APOYO PANAMA | J110: DEBITO | R110: -12400000
B111: CEPEV | C111: IGLESIA EN BUCARAMANGA APOYO CEPPEV | J111: DEBITO | R111: -3000000
B112: PANAMA | C112: LUIS MIGUEL NARANJO APOYO PANAMA | J112: DEBITO | S112: -2000000
B113: OBRA COL | C113: APOYO PARA CONFINES | J113: DEBITO | S113: -12000000
B114: VUELOS | C114: DAVID MIRANDA VUELOS MEXICO | J114: DEBITO | S114: -10786093
B115: BRASIL | C115: APOYO SALON GENESIS | J115: DEBITO | S115: -6194294
B116: PEDRO D | C116: ENTREGA RESERVA PD | J116: DEBITO | S116: -46779164
B117: INVERSIONISTAS | C117: MOVIL INVERSIONISTAS | J117: DEBITO | S117: -57302
B118: OTROS | C118: EIFER ALONSO GALVIS PASAPORTE | J118: DEBITO | S118: -2500000
B119: BRASIL | C119: DAVID MIRANDA QR IVPT | J119: DEBITO | S119: -932000
...

Sheet Resumen 2026
A1: INDICADORES CLAVE
I2: OCT | J2: NOV | K2: DIC | L2: ENE | M2: FEB | N2: MAR | O2: ABR | P2: MAY
A3: MES | B3: TOTAL APORTES | C3: INVERSIONISTAS ACTIVOS | E3: MES | F3: TOTAL GASTOS | H3: NUEVOS INV (OCT) | I3: =COUNTIFS('Base Inversionistas'!R4:R267, "=0", 'Base Inversionistas'!S4:S267, ">0") -> 34 | J3: =COUNTIFS('Base Inversionistas'!S5:S296, "=0", 'Base Inversionistas'!T5:T296, ">0") -> 81 | K3: =COUNTIFS('Base Inversionistas'!T5:T296, "=0", 'Base Inversionistas'!U5:U296, ">0") -> 39 | L3: =COUNTIFS('Base Inversionistas'!U5:U296, "= 0", 'Base Inversionistas 26'!J5:J400, ">0") -> #VALUE! | M3: =COUNTIFS('Base Inversionistas 26'!J5:J400, "=0", 'Base Inversionistas 26'!K5:K400, ">0") -> 45 | N3: =COUNTIFS('Base Inversionistas 26'!K5:K400, "=0", 'Base Inversionistas 26'!L5:L400, ">0") -> 31 | O3: =COUNTIFS('Base Inversionistas 26'!L5:L400, "=0", 'Base Inversionistas 26'!M5:M400, ">0") -> 53 | P3: =COUNTIFS('Base Inversionistas 26'!M5:M400, "=0", 'Base Inversionistas 26'!N5:N400, ">0") -> 41 | Q3: =COUNTIFS('Base Inversionistas 26'!N5:N400, "=0", 'Base Inversionistas 26'!O5:O400, ">0") -> 55 | R3: =COUNTIFS('Base Inversionistas 26'!O5:O400, "=0", 'Base Inversionistas 26'!P5:P400, ">0") -> 41
A4: 2025 | B4: ='Resumen 2025'!B17 -> 740341909 | E4: 2025 | F4: ='Resumen 2025'!F17 -> -531593755 | H4: BAJAS INV | I4: =COUNTIFS('Base Inversionistas'!R4:R267, ">0", 'Base Inversionistas'!S4:S267, "=0") -> 24 | J4: =COUNTIFS('Base Inversionistas'!S4:S296, ">0", 'Base Inversionistas'!T4:T296, "=0") -> 31 | K4: =COUNTIFS('Base Inversionistas'!T4:T296, ">0", 'Base Inversionistas'!U4:U296, "=0") -> 29 | L4: =COUNTIFS('Base Inversionistas'!U4:U296, ">0", 'Base Inversionistas'!V4:V296, "=0") -> 90 | M4: =COUNTIFS('Base Inversionistas 26'!J5:J400, "> 0", 'Base Inversionistas 26'!K5:K400, "=0") -> 33 | N4: =COUNTIFS('Base Inversionistas 26'!K5:K400, "> 0", 'Base Inversionistas 26'!L5:L400, "=0") -> 35 | O4: =COUNTIFS('Base Inversionistas 26'!L5:L400, "> 0", 'Base Inversionistas 26'!M5:M400, "=0") -> 38 | P4: =COUNTIFS('Base Inversionistas 26'!M5:M400, "> 0", 'Base Inversionistas 26'!N5:N400, "=0") -> 68 | Q4: =COUNTIFS('Base Inversionistas 26'!N5:N400, "> 0", 'Base Inversionistas 26'!O5:O400, "=0") -> 35 | R4: =COUNTIFS('Base Inversionistas 26'!O5:O400, "> 0", 'Base Inversionistas 26'!P5:P400, "=0") -> 46
A5: ENERO | B5: ='Base Inversionistas 26'!J401 -> 97408000 | C5: =COUNTIF('Base Inversionistas 26'!J5:J400,">0") -> 107 | E5: ENERO | F5: ='Gastos 26'!K123 -> -14223540
A6: FEBRERO | B6: ='Base Inversionistas 26'!K401 -> 121440243 | C6: =COUNTIF('Base Inversionistas 26'!J5:K400,">0") -> 226 | E6: FEBRERO | F6: ='Gastos 26'!L123 -> -90677381
A7: MARZO | B7: ='Base Inversionistas 26'!L401 -> 102625000 | C7: =COUNTIF('Base Inversionistas 26'!L5:L400,">0") -> 115 | E7: MARZO | F7: ='Gastos 26'!M123 -> -53757023 | H7: CLASIFICACION GASTOS | I7: Suma de ENERO | J7: Suma de FEBRERO | K7: Suma de MARZO | L7: Suma de ABRIL | M7: Suma de MAYO | N7: Suma de JUNIO | O7: Suma de JULIO | P7: Suma de AGOSTO | Q7: Suma de SEPTIEMBRE | R7: Suma de OCTUBRE | S7: Suma de NOVIEMBRE | T7: Suma de DICIEMBRE | U7: TOTAL
A8: ABRIL | B8: ='Base Inversionistas 26'!M401 -> 112685982 | C8: =COUNTIF('Base Inversionistas 26'!M5:M400,">0") -> 130 | E8: ABRIL | F8: ='Gastos 26'!N123 -> -69816950 | H8: BRASIL | O8: -15487675 | P8: -5718695 | U8: =SUM(I8:S8) -> -21206370
A9: MAYO | B9: ='Base Inversionistas 26'!N401 -> 110994000 | C9: =COUNTIF('Base Inversionistas 26'!N6:N401,">0") -> 104 | E9: MAYO | F9: ='Gastos 26'!O123 -> -67382816 | H9: CEPEV | P9: -5000000 | U9: =SUM(I9:S9) -> -5000000
A10: JUNIO | B10: ='Base Inversionistas 26'!O401 -> 120764000 | C10: =COUNTIF('Base Inversionistas 26'!O6:O400,">0") -> 123 | E10: JUNIO | F10: ='Gastos 26'!P123 -> -75242944 | H10: COSTA RICA | U10: =SUM(I10:S10) -> 0
A11: JULIO | B11: ='Base Inversionistas 26'!P401 -> 130541664 | C11: =COUNTIF('Base Inversionistas 26'!P7:P400,">0") -> 118 | E11: JULIO | F11: ='Gastos 26'!Q123 -> -64915933 | H11: CUBA | I11: 0 | U11: =SUM(I11:S11) -> 0
A12: AGOSTO | B12: ='Base Inversionistas 26'!Q401 -> 127888500 | E12: AGOSTO | F12: ='Gastos 26'!R123 -> -109953072 | H12: DEUDA FONDO | I12: -6498740 | U12: =SUM(I12:S12) -> -6498740
A13: SEPTIEMBRE | B13: ='Base Inversionistas 26'!R401 -> 60271000 | E13: SEPTIEMBRE | F13: ='Gastos 26'!S123 -> -81248853 | H13: EAV | U13: =SUM(I13:S13) -> 0
A14: OCTUBRE | E14: OCTUBRE | H14: INVERSIONISTAS | I14: -100800 | J14: 0 | K14: -55800 | L14: -46300 | M14: -55300 | N14: -46300 | O14: -55300 | P14: -46300 | U14: =SUM(I14:S14) -> -406100
A15: NOVIEMBRE | E15: NOVIEMBRE | H15: IVPT | U15: =SUM(I15:S15) -> 0
A16: DICIEMBRE | E16: DICIEMBRE | H16: JULIO S | J16: 0 | U16: =SUM(I16:S16) -> 0
A17: TOTALES | B17: =SUM(B4:B16) -> 1724960298 | E17: TOTALES | F17: =SUM(F4:F16) -> -1158812267 | H17: OFRENDA | U17: =SUM(I17:S17) -> 0
A18: SALDO INVERSIONISTAS | B18: =B17+F17 -> 566148031 | H18: PAC | K18: -40000000 | U18: =SUM(I18:S18) -> -40000000
H19: PANAMA | I19: -7624000 | J19: -6176000 | K19: -6858000 | L19: -2000000 | N19: -28094702 | O19: -1000000 | P19: -9661190 | U19: =SUM(I19:S19) -> -61413892
H20: PEDRO D | J20: -60897000 | L20: -33600000 | M20: -67327516 | N20: -37882873 | O20: -41493250 | P20: -39128787 | U20: =SUM(I20:S20) -> -280329426
H21: VUELOS | J21: -23604381 | K21: -6843223 | L21: -28635650 | N21: -9219069 | O21: -1879708 | P21: -1861000 | U21: =SUM(I21:S21) -> -72043031
H22: VALLEDUPAR | U22: =SUM(I22:T22) -> 0
H23: Total general | I23: -14223540 | J23: -90677381 | K23: -53757023 | L23: -64281950 | M23: -67382816 | N23: -75242944 | O23: -59915933 | P23: -61415972
A25: 400000
A26: Etiquetas de fila | B26: Suma de Cuotas_Enteras | C26: Suma de ABRIL | D26: Suma de MAYO
A27: ANTIOQUIA | B27: 1 | C27: 50000 | D27: 50000
A28: Armenia | B28: 0 | C28: 0 | D28: 0
A29: Barranquilla | B29: 23 | C29: 0 | D29: 2540000
A30: Bayunca | B30: 4 | C30: 0 | D30: 400000
A31: BOGOTA | B31: 186 | C31: 16720000 | D31: 9760000
A32: Bolivar | B32: 6 | C32: 800000 | D32: 400000
A33: BUCARAMANGA | B33: 91 | C33: 6000000 | D33: 400000
A34: CALI | B34: 8 | C34: 400000 | D34: 0
A35: CARTAGENA | B35: 8 | C35: 0 | D35: 400000
A36: Cartago | B36: 18 | C36: 2400000 | D36: 500000
A37: CERETÉ | B37: 0 | C37: 0 | D37: 0
A38: CHIGORODO | B38: 1 | C38: 400000 | D38: 0
... A99: Total general | B99: 1284 | C99: 112685982 | D99: 67715000

Sheet XLOCALIDAD
B2: LOCALIDAD | C2: TOTAL DICIEMBRE | D2: Total Cuotas DICIEMBRE | G2: LOCALIDAD | H2: TOTAL CUOTAS 2025 | J2: LOCALIDAD | K2: TOTAL CUOTAS 2026 | L2: CUOTAS ABRIL | M2: CUOTAS MAYO
B3: VALLEDUPAR | C3: 14000000 | D3: =C3/400000 -> 35 | G3: BOGOTA | H3: 328 | J3: Armenia | K3: 0 | L3: 0 | M3: 0
B4: BOGOTA | C4: 10120000 | D4: =C4/400000 -> 25.3 | G4: VALLEDUPAR | H4: 170 | J4: Barranquilla | K4: 23 | L4: 0 | M4: 6.35
B5: LOS PATIOS | C5: 5000000 | D5: =C5/400000 -> 12.5 | G5: LOS PATIOS | H5: 70 | J5: Bayunca | K5: 4 | L5: 0 | M5: 1
B6: BOGOTA | C6: 4800000 | D6: =C6/400000 -> 12 | G6: BUCARAMANGA | H6: 67 | J6: BOGOTA | K6: 186 | L6: 41.8 | M6: 24.4
B7: CUCUTA | C7: 4700000 | D7: =C7/400000 -> 11.75 | G7: UBATE | H7: 62 | J7: Bolivar | K7: 6 | L7: 2 | M7: 1
B8: OCAÑA | C8: 3200000 | D8: =C8/400000 -> 8 | G8: CUCUTA | H8: 58 | J8: BUCARAMANGA | K8: 91 | L8: 15 | M8: 1
B9: UBATE | C9: 3200000 | D9: =C9/400000 -> 8 | G9: BARRANQUILLA | H9: 55 | J9: CARTAGENA | K9: 8 | L9: 0 | M9: 1
B10: GIRARDOTA | C10: 2800000 | D10: =C10/400000 -> 7 | G10: MEDELLIN | H10: 47 | J10: CERETÉ | K10: 0 | L10: 0 | M10: 0
B11: MONTERÍA | C11: 2800000 | D11: =C11/400000 -> 7 | G11: GIRARDOTA | H11: 43 | J11: CHIGORODO | K11: 1 | L11: 1 | M11: 0
B12: QUIBDO | C12: 2800000 | D12: =C12/400000 -> 7 | G12: CARTAGENA | H12: 40 | J12: CHIQUINQUIRA | K12: 25 | L12: 5 | M12: 5
B13: PUERTO COLOMBIA | C13: 2790000 | D13: =C13/400000 -> 6.975 | G13: PEREIRA | H13: 40 | J13: CUCUNUBA | K13: 0 | L13: 0 | M13: 0
B14: PAMPLONA | C14: 2690000 | D14: =C14/400000 -> 6.725 | G14: MONTERIA | H14: 39 | J14: CUCUTA | K14: 48 | L14: 13 | M14: 3
... B54: RIONEGRO | C54: 80000 | D54: =C54/400000 -> 0.2 | G54: CHIGORODO | H54: 4 | J54: Yopal | K54: 7 | L54: 2 | M54: 0
G55: CHOCO | H55: 4 | J55: Total general | K55: 1284 | L55: 281.71495 | M55: 169.2875
G56: VIOTA | H56: 3
G57: RIONEGRO | H57: 3
G58: SOGAMOSO | H58: 3
G59: CUCUNUBA | H59: 3
G60: La mina | H60: 3
G61: ZIPAQUIRA | H61: 2
G62: FUQUENE | H62: 2
G63: SUTATAUSA | H63: 2
G64: Riohacha | H64: 2
G65: SANTA LUCIA | H65: 2
G66: SAN JUAN | H66: 1
G67: ANTIOQUIA | H67: 1
G68: BELLO | H68: 1

Sheet Nuevos IDR Cepev
A2: Nombre | B2: Localidad | C2: Teléfono | D2: Cuota | E2: Monto
A3: Jonas quintero | B3: Bogotá | D3: 1
A4: Víctor peña | B4: Barranquilla | D4: 2
A5: Eusebio montes | B5: Barranquilla | D5: 1
A6: Carlos Peña | B6: Bucaramanga | D6: 1
A7: Juan Pablo Olivella | B7: Valledupar | D7: 2
A8: Rafael Gutiérrez | B8: Patios | D8: 1
A9: Adrián Hernández | B9: Girardota | D9: 1
A10: David delgado | B10: Patios | D10: 1.5
A11: Héctor Galeano | B11: Bogotá | D11: 2
A12: Sneider | B12: Villavicencio | D12: 1
A13: Daniel mota | B13: Villavicencio | D13: 1
A14: Iglesia en Villavicencio | B14: Villavicencio | D14: 1
... A56: Julio monsalve | B56: Medellín | D56: 0.5

Sheet Central_IDR
A1: NOMBRES | B1: NO. IDENTIFICACION | C1: NO. CELULAR | D1: LOCALIDAD | E1: ENERO | F1: FEBRERO | G1: MARZO | H1: ABRIL | I1: MAYO | J1: JUNIO | K1: JULIO | L1: AGOSTO | N1: 400000
A2: ALBA MARINA ROMERO | E2: ='[2]Base Inversionistas 26'!J5/$N$1 -> 0 | F2: ='[2]Base Inversionistas 26'!K5/$N$1 -> 0 | G2: ='[2]Base Inversionistas 26'!L5/$N$1 -> 0 | H2: ='[2]Base Inversionistas 26'!M5/$N$1 -> 0 | I2: ='[2]Base Inversionistas 26'!N5/$N$1 -> 0 | J2: ='[2]Base Inversionistas 26'!O5/$N$1 -> 0 | K2: ='[2]Base Inversionistas 26'!P5/$N$1 -> 0 | L2: ='[2]Base Inversionistas 26'!Q5/$N$1 -> 0
A3: ANA MISAD | D3: BOGOTA | E3: ='[2]Base Inversionistas 26'!J6/$N$1 -> 0 | F3: ='[2]Base Inversionistas 26'!K6/$N$1 -> 0 | G3: ='[2]Base Inversionistas 26'!L6/$N$1 -> 0 | H3: ='[2]Base Inversionistas 26'!M6/$N$1 -> 0 | I3: ='[2]Base Inversionistas 26'!N6/$N$1 -> 0 | J3: ='[2]Base Inversionistas 26'!O6/$N$1 -> 0 | K3: ='[2]Base Inversionistas 26'!P6/$N$1 -> 0 | L3: ='[2]Base Inversionistas 26'!Q6/$N$1 -> 0
A4: ANA CORTES | D4: BOGOTA | E4: ='[2]Base Inversionistas 26'!J7/$N$1 -> 0 | F4: ='[2]Base Inversionistas 26'!K7/$N$1 -> 0 | G4: ='[2]Base Inversionistas 26'!L7/$N$1 -> 0 | H4: ='[2]Base Inversionistas 26'!M7/$N$1 -> 0 | I4: ='[2]Base Inversionistas 26'!N7/$N$1 -> 0 | J4: ='[2]Base Inversionistas 26'!O7/$N$1 -> 0 | K4: ='[2]Base Inversionistas 26'!P7/$N$1 -> 0 | L4: ='[2]Base Inversionistas 26'!Q7/$N$1 -> 0
A5: ANA MARIA PORTILLA CLAROS | B5: 1114621012 | C5: 3207945735 | D5: BOGOTA | E5: ='[2]Base Inversionistas 26'!J8/$N$1 -> 0 | F5: ='[2]Base Inversionistas 26'!K8/$N$1 -> 0 | G5: ='[2]Base Inversionistas 26'!L8/$N$1 -> 0 | H5: ='[2]Base Inversionistas 26'!M8/$N$1 -> 1.5 | I5: ='[2]Base Inversionistas 26'!N8/$N$1 -> 0 | J5: ='[2]Base Inversionistas 26'!O8/$N$1 -> 0 | K5: ='[2]Base Inversionistas 26'!P8/$N$1 -> 0 | L5: ='[2]Base Inversionistas 26'!Q8/$N$1 -> 0
A6: ANDRES CASTRILLON "GIRARDOTA" | B6: 1035855590 | C6: 3154949282 | D6: Girardota | E6: ='[2]Base Inversionistas 26'!J9/$N$1 -> 1 | F6: ='[2]Base Inversionistas 26'!K9/$N$1 -> 1 | G6: ='[2]Base Inversionistas 26'!L9/$N$1 -> 1 | H6: ='[2]Base Inversionistas 26'!M9/$N$1 -> 1 | I6: ='[2]Base Inversionistas 26'!N9/$N$1 -> 0 | J6: ='[2]Base Inversionistas 26'!O9/$N$1 -> 1 | K6: ='[2]Base Inversionistas 26'!P9/$N$1 -> 0 | L6: ='[2]Base Inversionistas 26'!Q9/$N$1 -> 0
A7: ANDRES MORENO ARRIAGA | B7: 1077465696 | C7: 3207593131 | D7: QUIBDO | E7: ='[2]Base Inversionistas 26'!J10/$N$1 -> 0 | F7: ='[2]Base Inversionistas 26'!K10/$N$1 -> 0 | G7: ='[2]Base Inversionistas 26'!L10/$N$1 -> 0 | H7: ='[2]Base Inversionistas 26'!M10/$N$1 -> 1 | I7: ='[2]Base Inversionistas 26'!N10/$N$1 -> 0 | J7: ='[2]Base Inversionistas 26'!O10/$N$1 -> 2 | K7: ='[2]Base Inversionistas 26'!P10/$N$1 -> 0 | L7: ='[2]Base Inversionistas 26'!Q10/$N$1 -> 0
A8: ANGIE FINO | E8: ='[2]Base Inversionistas 26'!J11/$N$1 -> 0 | F8: ='[2]Base Inversionistas 26'!K11/$N$1 -> 0 | G8: ='[2]Base Inversionistas 26'!L11/$N$1 -> 0 | H8: ='[2]Base Inversionistas 26'!M11/$N$1 -> 0 | I8: ='[2]Base Inversionistas 26'!N11/$N$1 -> 0 | J8: ='[2]Base Inversionistas 26'!O11/$N$1 -> 0 | K8: ='[2]Base Inversionistas 26'!P11/$N$1 -> 0 | L8: ='[2]Base Inversionistas 26'!Q11/$N$1 -> 0
A9: ANONIMO | D9: BOGOTA | E9: ='[2]Base Inversionistas 26'!J12/$N$1 -> 0 | F9: ='[2]Base Inversionistas 26'!K12/$N$1 -> 0 | G9: ='[2]Base Inversionistas 26'!L12/$N$1 -> 0 | H9: ='[2]Base Inversionistas 26'!M12/$N$1 -> 0 | I9: ='[2]Base Inversionistas 26'!N12/$N$1 -> 0 | J9: ='[2]Base Inversionistas 26'!O12/$N$1 -> 1 | K9: ='[2]Base Inversionistas 26'!P12/$N$1 -> 0 | L9: ='[2]Base Inversionistas 26'!Q12/$N$1 -> 0
A10: APOYO CASA PAC | E10: ='[2]Base Inversionistas 26'!J13/$N$1 -> 0 | F10: ='[2]Base Inversionistas 26'!K13/$N$1 -> 0 | G10: ='[2]Base Inversionistas 26'!L13/$N$1 -> 0 | H10: ='[2]Base Inversionistas 26'!M13/$N$1 -> 0 | I10: ='[2]Base Inversionistas 26'!N13/$N$1 -> 0 | J10: ='[2]Base Inversionistas 26'!O13/$N$1 -> 0 | K10: ='[2]Base Inversionistas 26'!P13/$N$1 -> 0 | L10: ='[2]Base Inversionistas 26'!Q13/$N$1 -> 0
A11: BENITO HERRRA | D11: PTO. COLOM | E11: ='[2]Base Inversionistas 26'!J14/$N$1 -> 0 | F11: ='[2]Base Inversionistas 26'!K14/$N$1 -> 0 | G11: ='[2]Base Inversionistas 26'!L14/$N$1 -> 0 | H11: ='[2]Base Inversionistas 26'!M14/$N$1 -> 4 | I11: ='[2]Base Inversionistas 26'!N14/$N$1 -> 0 | J11: ='[2]Base Inversionistas 26'!O14/$N$1 -> 3 | K11: ='[2]Base Inversionistas 26'!P14/$N$1 -> 4 | L11: ='[2]Base Inversionistas 26'!Q14/$N$1 -> 0
A12: BIBIANA MONTOYA RODAS | E12: ='[2]Base Inversionistas 26'!J15/$N$1 -> 0 | F12: ='[2]Base Inversionistas 26'!K15/$N$1 -> 0 | G12: ='[2]Base Inversionistas 26'!L15/$N$1 -> 0 | H12: ='[2]Base Inversionistas 26'!M15/$N$1 -> 0 | I12: ='[2]Base Inversionistas 26'!N15/$N$1 -> 0 | J12: ='[2]Base Inversionistas 26'!O15/$N$1 -> 0 | K12: ='[2]Base Inversionistas 26'!P15/$N$1 -> 0 | L12: ='[2]Base Inversionistas 26'!Q15/$N$1 -> 0
A13: BRAYER ALEXIS QUINTERO FERNANDEZ | B13: 1090395092 | D13: CUCUTA | E13: ='[2]Base Inversionistas 26'!J16/$N$1 -> 1 | F13: ='[2]Base Inversionistas 26'!K16/$N$1 -> 1 | G13: ='[2]Base Inversionistas 26'!L16/$N$1 -> 0 | H13: ='[2]Base Inversionistas 26'!M16/$N$1 -> 3 | I13: ='[2]Base Inversionistas 26'!N16/$N$1 -> 0 | J13: ='[2]Base Inversionistas 26'!O16/$N$1 -> 1 | K13: ='[2]Base Inversionistas 26'!P16/$N$1 -> 1 | L13: ='[2]Base Inversionistas 26'!Q16/$N$1 -> 0
A14: CARLIS MICHELE PEREZ CANO | B14: 1095846194 | C14: 3022962452 | D14: BOGOTA | E14: ='[2]Base Inversionistas 26'!J17/$N$1 -> 1 | F14: ='[2]Base Inversionistas 26'!K17/$N$1 -> 1 | G14: ='[2]Base Inversionistas 26'!L17/$N$1 -> 0 | H14: ='[2]Base Inversionistas 26'!M17/$N$1 -> 0 | I14: ='[2]Base Inversionistas 26'!N17/$N$1 -> 0 | J14: ='[2]Base Inversionistas 26'!O17/$N$1 -> 0 | K14: ='[2]Base Inversionistas 26'!P17/$N$1 -> 0 | L14: ='[2]Base Inversionistas 26'!Q17/$N$1 -> 0
A15: CARLOS CARRASCO | D15: BOGOTA | E15: ='[2]Base Inversionistas 26'!J18/$N$1 -> 1 | F15: ='[2]Base Inversionistas 26'!K18/$N$1 -> 1 | G15: ='[2]Base Inversionistas 26'!L18/$N$1 -> 1 | H15: ='[2]Base Inversionistas 26'!M18/$N$1 -> 1 | I15: ='[2]Base Inversionistas 26'!N18/$N$1 -> 1 | J15: ='[2]Base Inversionistas 26'!O18/$N$1 -> 1.5 | K15: ='[2]Base Inversionistas 26'!P18/$N$1 -> 0 | L15: ='[2]Base Inversionistas 26'!Q18/$N$1 -> 0
A16: CARLOS PALMA | D16: BOGOTA | E16: ='[2]Base Inversionistas 26'!J19/$N$1 -> 0 | F16: ='[2]Base Inversionistas 26'!K19/$N$1 -> 2 | G16: ='[2]Base Inversionistas 26'!L19/$N$1 -> 1 | H16: ='[2]Base Inversionistas 26'!M19/$N$1 -> 1 | I16: ='[2]Base Inversionistas 26'!N19/$N$1 -> 1 | J16: ='[2]Base Inversionistas 26'!O19/$N$1 -> 0 | K16: ='[2]Base Inversionistas 26'!P19/$N$1 -> 0 | L16: ='[2]Base Inversionistas 26'!Q19/$N$1 -> 0
A17: CARLOS ANDRES COCUY | B17: 14797460 | C17: 3160438302 | D17: DOSQUEBRADAS | E17: ='[2]Base Inversionistas 26'!J20/$N$1 -> 1.125 | F17: ='[2]Base Inversionistas 26'!K20/$N$1 -> 1.125 | G17: ='[2]Base Inversionistas 26'!L20/$N$1 -> 1.25 | H17: ='[2]Base Inversionistas 26'!M20/$N$1 -> 1.5 | I17: ='[2]Base Inversionistas 26'!N20/$N$1 -> 0 | J17: ='[2]Base Inversionistas 26'!O20/$N$1 -> 0 | K17: ='[2]Base Inversionistas 26'!P20/$N$1 -> 1.5 | L17: ='[2]Base Inversionistas 26'!Q20/$N$1 -> 1
A18: CAROLINA QUIROGA | E18: ='[2]Base Inversionistas 26'!J21/$N$1 -> 0 | F18: ='[2]Base Inversionistas 26'!K21/$N$1 -> 0 | G18: ='[2]Base Inversionistas 26'!L21/$N$1 -> 0 | H18: ='[2]Base Inversionistas 26'!M21/$N$1 -> 1 | I18: ='[2]Base Inversionistas 26'!N21/$N$1 -> 1 | J18: ='[2]Base Inversionistas 26'!O21/$N$1 -> 0 | K18: ='[2]Base Inversionistas 26'!P21/$N$1 -> 0 | L18: ='[2]Base Inversionistas 26'!Q21/$N$1 -> 0
A19: CESAR VERA | B19: 79333423 | C19: 3166268412 | D19: BOGOTA | E19: ='[2]Base Inversionistas 26'!J22/$N$1 -> 5 | F19: ='[2]Base Inversionistas 26'!K22/$N$1 -> 4 | G19: ='[2]Base Inversionistas 26'!L22/$N$1 -> 4 | H19: ='[2]Base Inversionistas 26'!M22/$N$1 -> 5 | I19: ='[2]Base Inversionistas 26'!N22/$N$1 -> 2 | J19: ='[2]Base Inversionistas 26'!O22/$N$1 -> 10 | K19: ='[2]Base Inversionistas 26'!P22/$N$1 -> 7.75 | L19: ='[2]Base Inversionistas 26'!Q22/$N$1 -> 4
A20: CLAUDIA ARCINIEGAS | D20: CUCUTA | E20: ='[2]Base Inversionistas 26'!J23/$N$1 -> 0 | F20: ='[2]Base Inversionistas 26'!K23/$N$1 -> 0 | G20: ='[2]Base Inversionistas 26'!L23/$N$1 -> 0 | H20: ='[2]Base Inversionistas 26'!M23/$N$1 -> 0 | I20: ='[2]Base Inversionistas 26'!N23/$N$1 -> 1 | J20: ='[2]Base Inversionistas 26'!O23/$N$1 -> 0 | K20: ='[2]Base Inversionistas 26'!P23/$N$1 -> 0 | L20: ='[2]Base Inversionistas 26'!Q23/$N$1 -> 0
A21: DANIEL VARGAS | D21: NEIVA | E21: ='[2]Base Inversionistas 26'!J24/$N$1 -> 1 | F21: ='[2]Base Inversionistas 26'!K24/$N$1 -> 1.5 | G21: ='[2]Base Inversionistas 26'!L24/$N$1 -> 1.5 | H21: ='[2]Base Inversionistas 26'!M24/$N$1 -> 0 | I21: ='[2]Base Inversionistas 26'!N24/$N$1 -> 2 | J21: ='[2]Base Inversionistas 26'!O24/$N$1 -> 1 | K21: ='[2]Base Inversionistas 26'!P24/$N$1 -> 0 | L21: ='[2]Base Inversionistas 26'!Q24/$N$1 -> 0
A22: DANIELA CASTO | E22: ='[2]Base Inversionistas 26'!J25/$N$1 -> 0 | F22: ='[2]Base Inversionistas 26'!K25/$N$1 -> 0 | G22: ='[2]Base Inversionistas 26'!L25/$N$1 -> 0 | H22: ='[2]Base Inversionistas 26'!M25/$N$1 -> 0 | I22: ='[2]Base Inversionistas 26'!N25/$N$1 -> 0 | J22: ='[2]Base Inversionistas 26'!O25/$N$1 -> 0 | K22: ='[2]Base Inversionistas 26'!P25/$N$1 -> 0 | L22: ='[2]Base Inversionistas 26'!Q25/$N$1 -> 0
A23: DAVID MAESTRE | E23: ='[2]Base Inversionistas 26'!J26/$N$1 -> 0 | F23: ='[2]Base Inversionistas 26'!K26/$N$1 -> 0 | G23: ='[2]Base Inversionistas 26'!L26/$N$1 -> 0 | H23: ='[2]Base Inversionistas 26'!M26/$N$1 -> 0 | I23: ='[2]Base Inversionistas 26'!N26/$N$1 -> 0 | J23: ='[2]Base Inversionistas 26'!O26/$N$1 -> 0 | K23: ='[2]Base Inversionistas 26'!P26/$N$1 -> 0 | L23: ='[2]Base Inversionistas 26'!Q26/$N$1 -> 0
A24: DAVID MIRANDA | D24: BOGOTA | E24: ='[2]Base Inversionistas 26'!J27/$N$1 -> 1 | F24: ='[2]Base Inversionistas 26'!K27/$N$1 -> 0 | G24: ='[2]Base Inversionistas 26'!L27/$N$1 -> 0 | H24: ='[2]Base Inversionistas 26'!M27/$N$1 -> 2 | I24: ='[2]Base Inversionistas 26'!N27/$N$1 -> 1 | J24: ='[2]Base Inversionistas 26'!O27/$N$1 -> 0 | K24: ='[2]Base Inversionistas 26'!P27/$N$1 -> 3 | L24: ='[2]Base Inversionistas 26'!Q27/$N$1 -> 0
A25: EDDWARD GARCIA | D25: BOGOTA | E25: ='[2]Base Inversionistas 26'!J28/$N$1 -> 0 | F25: ='[2]Base Inversionistas 26'!K28/$N$1 -> 0 | G25: ='[2]Base Inversionistas 26'!L28/$N$1 -> 0 | H25: ='[2]Base Inversionistas 26'!M28/$N$1 -> 0 | I25: ='[2]Base Inversionistas 26'!N28/$N$1 -> 0 | J25: ='[2]Base Inversionistas 26'!O28/$N$1 -> 0 | K25: ='[2]Base Inversionistas 26'!P28/$N$1 -> 0 | L25: ='[2]Base Inversionistas 26'!Q28/$N$1 -> 0
A26: ERICA PLATA | B26: 60362206 | C26: 3165652640 | D26: LOS PATIOS | E26: ='[2]Base Inversionistas 26'!J29/$N$1 -> 0 | F26: ='[2]Base Inversionistas 26'!K29/$N$1 -> 1 | G26: ='[2]Base Inversionistas 26'!L29/$N$1 -> 1 | H26: ='[2]Base Inversionistas 26'!M29/$N$1 -> 1 | I26: ='[2]Base Inversionistas 26'!N29/$N$1 -> 1 | J26: ='[2]Base Inversionistas 26'!O29/$N$1 -> 0 | K26: ='[2]Base Inversionistas 26'!P29/$N$1 -> 0 | L26: ='[2]Base Inversionistas 26'!Q29/$N$1 -> 0
A27: ERMILGEN RIAÑO | D27: BOGOTA | E27: ='[2]Base Inversionistas 26'!J30/$N$1 -> 0 | F27: ='[2]Base Inversionistas 26'!K30/$N$1 -> 0 | G27: ='[2]Base Inversionistas 26'!L30/$N$1 -> 0 | H27: ='[2]Base Inversionistas 26'!M30/$N$1 -> 0 | I27: ='[2]Base Inversionistas 26'!N30/$N$1 -> 0 | J27: ='[2]Base Inversionistas 26'!O30/$N$1 -> 0 | K27: ='[2]Base Inversionistas 26'!P30/$N$1 -> 0 | L27: ='[2]Base Inversionistas 26'!Q30/$N$1 -> 0
A28: ESTEBAN ISAZA MUÑOZ | B28: 88230239 | C28: 3123933769 | D28: PAMPLONA | E28: ='[2]Base Inversionistas 26'!J31/$N$1 -> 4 | F28: ='[2]Base Inversionistas 26'!K31/$N$1 -> 4 | G28: ='[2]Base Inversionistas 26'!L31/$N$1 -> 3.5 | H28: ='[2]Base Inversionistas 26'!M31/$N$1 -> 3 | I28: ='[2]Base Inversionistas 26'!N31/$N$1 -> 3 | J28: ='[2]Base Inversionistas 26'!O31/$N$1 -> 3 | K28: ='[2]Base Inversionistas 26'!P31/$N$1 -> 3 | L28: ='[2]Base Inversionistas 26'!Q31/$N$1 -> 3
A29: ESTHER TORRES | D29: BOGOTA | E29: ='[2]Base Inversionistas 26'!J32/$N$1 -> 0 | F29: ='[2]Base Inversionistas 26'!K32/$N$1 -> 0 | G29: ='[2]Base Inversionistas 26'!L32/$N$1 -> 0 | H29: ='[2]Base Inversionistas 26'!M32/$N$1 -> 0 | I29: ='[2]Base Inversionistas 26'!N32/$N$1 -> 0 | J29: ='[2]Base Inversionistas 26'!O32/$N$1 -> 0 | K29: ='[2]Base Inversionistas 26'!P32/$N$1 -> 0 | L29: ='[2]Base Inversionistas 26'!Q32/$N$1 -> 0
A30: EUSEBIO MONTES | E30: ='[2]Base Inversionistas 26'!J33/$N$1 -> 0 | F30: ='[2]Base Inversionistas 26'!K33/$N$1 -> 0 | G30: ='[2]Base Inversionistas 26'!L33/$N$1 -> 0 | H30: ='[2]Base Inversionistas 26'!M33/$N$1 -> 0 | I30: ='[2]Base Inversionistas 26'!N33/$N$1 -> 0 | J30: ='[2]Base Inversionistas 26'!O33/$N$1 -> 0 | K30: ='[2]Base Inversionistas 26'!P33/$N$1 -> 0 | L30: ='[2]Base Inversionistas 26'!Q33/$N$1 -> 0
A31: FLOR ACUÑA | D31: BOGOTA | E31: ='[2]Base Inversionistas 26'!J34/$N$1 -> 0 | F31: ='[2]Base Inversionistas 26'!K34/$N$1 -> 0 | G31: ='[2]Base Inversionistas 26'!L34/$N$1 -> 0 | H31: ='[2]Base Inversionistas 26'!M34/$N$1 -> 0 | I31: ='[2]Base Inversionistas 26'!N34/$N$1 -> 0 | J31: ='[2]Base Inversionistas 26'!O34/$N$1 -> 0 | K31: ='[2]Base Inversionistas 26'!P34/$N$1 -> 0 | L31: ='[2]Base Inversionistas 26'!Q34/$N$1 -> 0
A32: FLOR SALAMANCA | B32: 23963745 | C32: 3142385522 | D32: BOGOTA | E32: ='[2]Base Inversionistas 26'!J35/$N$1 -> 9 | F32: ='[2]Base Inversionistas 26'!K35/$N$1 -> 9 | G32: ='[2]Base Inversionistas 26'!L35/$N$1 -> 9 | H32: ='[2]Base Inversionistas 26'!M35/$N$1 -> 14 | I32: ='[2]Base Inversionistas 26'!N35/$N$1 -> 9 | J32: ='[2]Base Inversionistas 26'!O35/$N$1 -> 9 | K32: ='[2]Base Inversionistas 26'!P35/$N$1 -> 9 | L32: ='[2]Base Inversionistas 26'!Q35/$N$1 -> 9
A33: FRANCISCO VILLAMIL | D33: BOGOTA | E33: ='[2]Base Inversionistas 26'!J36/$N$1 -> 1 | F33: ='[2]Base Inversionistas 26'!K36/$N$1 -> 1 | G33: ='[2]Base Inversionistas 26'!L36/$N$1 -> 1 | H33: ='[2]Base Inversionistas 26'!M36/$N$1 -> 1 | I33: ='[2]Base Inversionistas 26'!N36/$N$1 -> 1 | J33: ='[2]Base Inversionistas 26'!O36/$N$1 -> 1 | K33: ='[2]Base Inversionistas 26'!P36/$N$1 -> 1 | L33: ='[2]Base Inversionistas 26'!Q36/$N$1 -> 0
A34: FREIMAN JAIMES | B34: 13177594 | C34: 3107951023 | D34: OCAÑA | E34: ='[2]Base Inversionistas 26'!J37/$N$1 -> 0 | F34: ='[2]Base Inversionistas 26'!K37/$N$1 -> 0 | G34: ='[2]Base Inversionistas 26'!L37/$N$1 -> 1 | H34: ='[2]Base Inversionistas 26'!M37/$N$1 -> 0 | I34: ='[2]Base Inversionistas 26'!N37/$N$1 -> 1 | J34: ='[2]Base Inversionistas 26'!O37/$N$1 -> 0 | K34: ='[2]Base Inversionistas 26'!P37/$N$1 -> 2 | L34: ='[2]Base Inversionistas 26'!Q37/$N$1 -> 1
A35: GISEL DANIELA GUTIERREZ MURILLO | E35: ='[2]Base Inversionistas 26'!J38/$N$1 -> 0 | F35: ='[2]Base Inversionistas 26'!K38/$N$1 -> 0 | G35: ='[2]Base Inversionistas 26'!L38/$N$1 -> 0 | H35: ='[2]Base Inversionistas 26'!M38/$N$1 -> 0 | I35: ='[2]Base Inversionistas 26'!N38/$N$1 -> 0 | J35: ='[2]Base Inversionistas 26'!O38/$N$1 -> 0 | K35: ='[2]Base Inversionistas 26'!P38/$N$1 -> 0 | L35: ='[2]Base Inversionistas 26'!Q38/$N$1 -> 0
A36: GUILLERMO MONSALVE | B36: 4803428 | C36: 3009838761 | D36: SINCELEJO | E36: ='[2]Base Inversionistas 26'!J39/$N$1 -> 0 | F36: ='[2]Base Inversionistas 26'!K39/$N$1 -> 4 | G36: ='[2]Base Inversionistas 26'!L39/$N$1 -> 4 | H36: ='[2]Base Inversionistas 26'!M39/$N$1 -> 0 | I36: ='[2]Base Inversionistas 26'!N39/$N$1 -> 4 | J36: ='[2]Base Inversionistas 26'!O39/$N$1 -> 4 | K36: ='[2]Base Inversionistas 26'!P39/$N$1 -> 4 | L36: ='[2]Base Inversionistas 26'!Q39/$N$1 -> 4
A37: HERMES PATIÑO | B37: 93206783 | C37: 3125188563 | D37: SINCELEJO | E37: ='[2]Base Inversionistas 26'!J40/$N$1 -> 0 | F37: ='[2]Base Inversionistas 26'!K40/$N$1 -> 2 | G37: ='[2]Base Inversionistas 26'!L40/$N$1 -> 2 | H37: ='[2]Base Inversionistas 26'!M40/$N$1 -> 0 | I37: ='[2]Base Inversionistas 26'!N40/$N$1 -> 0 | J37: ='[2]Base Inversionistas 26'!O40/$N$1 -> 2 | K37: ='[2]Base Inversionistas 26'!P40/$N$1 -> 2 | L37: ='[2]Base Inversionistas 26'!Q40/$N$1 -> 2
A38: HUMBERTO OSPINO | B38: 72147202 | C38: 3126317467 | D38: ENVIGADO | E38: ='[2]Base Inversionistas 26'!J41/$N$1 -> 0 | F38: ='[2]Base Inversionistas 26'!K41/$N$1 -> 0 | G38: ='[2]Base Inversionistas 26'!L41/$N$1 -> 0 | H38: ='[2]Base Inversionistas 26'!M41/$N$1 -> 1 | I38: ='[2]Base Inversionistas 26'!N41/$N$1 -> 0 | J38: ='[2]Base Inversionistas 26'!O41/$N$1 -> 0 | K38: ='[2]Base Inversionistas 26'!P41/$N$1 -> 0 | L38: ='[2]Base Inversionistas 26'!Q41/$N$1 -> 2
A39: IG. EN PTO. COLOMBIA | D39: Barranquilla | E39: ='[2]Base Inversionistas 26'!J42/$N$1 -> 0 | F39: ='[2]Base Inversionistas 26'!K42/$N$1 -> 0 | G39: ='[2]Base Inversionistas 26'!L42/$N$1 -> 0 | H39: ='[2]Base Inversionistas 26'!M42/$N$1 -> 0 | I39: ='[2]Base Inversionistas 26'!N42/$N$1 -> 0 | J39: ='[2]Base Inversionistas 26'!O42/$N$1 -> 0 | K39: ='[2]Base Inversionistas 26'!P42/$N$1 -> 0 | L39: ='[2]Base Inversionistas 26'!Q42/$N$1 -> 0
A40: IG. EN BARRANQUILLA | B40: 8742974 | C40: 317889812 | D40: BARRANQUILLA | E40: ='[2]Base Inversionistas 26'!J43/$N$1 -> 5.2125 | F40: ='[2]Base Inversionistas 26'!K43/$N$1 -> 5 | G40: ='[2]Base Inversionistas 26'!L43/$N$1 -> 2.95 | H40: ='[2]Base Inversionistas 26'!M43/$N$1 -> 0 | I40: ='[2]Base Inversionistas 26'!N43/$N$1 -> 5.35 | J40: ='[2]Base Inversionistas 26'!O43/$N$1 -> 3.575 | K40: ='[2]Base Inversionistas 26'!P43/$N$1 -> 0 | L40: ='[2]Base Inversionistas 26'!Q43/$N$1 -> 4.425
A41: IG. EN BAYUNCA JAVIER MIRANDA | D41: Bolivar | E41: ='[2]Base Inversionistas 26'!J44/$N$1 -> 0 | F41: ='[2]Base Inversionistas 26'!K44/$N$1 -> 0 | G41: ='[2]Base Inversionistas 26'!L44/$N$1 -> 0 | H41: ='[2]Base Inversionistas 26'!M44/$N$1 -> 1 | I41: ='[2]Base Inversionistas 26'!N44/$N$1 -> 0 | J41: ='[2]Base Inversionistas 26'!O44/$N$1 -> 0 | K41: ='[2]Base Inversionistas 26'!P44/$N$1 -> 0 | L41: ='[2]Base Inversionistas 26'!Q44/$N$1 -> 0
A42: IG. EN BUCARAMANGA | B42: 900379577 | C42: 31844096518 | D42: BUCARAMANGA | E42: ='[2]Base Inversionistas 26'!J45/$N$1 -> 15 | F42: ='[2]Base Inversionistas 26'!K45/$N$1 -> 37.5 | G42: ='[2]Base Inversionistas 26'!L45/$N$1 -> 22.5 | H42: ='[2]Base Inversionistas 26'!M45/$N$1 -> 15 | I42: ='[2]Base Inversionistas 26'!N45/$N$1 -> 22 | J42: ='[2]Base Inversionistas 26'!O45/$N$1 -> 0 | K42: ='[2]Base Inversionistas 26'!P45/$N$1 -> 14 | L42: ='[2]Base Inversionistas 26'!Q45/$N$1 -> 0
A43: IG. EN CARTAGO | D43: Cartago | E43: ='[2]Base Inversionistas 26'!J46/$N$1 -> 0 | F43: ='[2]Base Inversionistas 26'!K46/$N$1 -> 4.875 | G43: ='[2]Base Inversionistas 26'!L46/$N$1 -> 1 | H43: ='[2]Base Inversionistas 26'!M46/$N$1 -> 4.75 | I43: ='[2]Base Inversionistas 26'!N46/$N$1 -> 0 | J43: ='[2]Base Inversionistas 26'!O46/$N$1 -> 0 | K43: ='[2]Base Inversionistas 26'!P46/$N$1 -> 0 | L43: ='[2]Base Inversionistas 26'!Q46/$N$1 -> 0
A44: IG. EN CORDOBA | D44: Cordoba | E44: ='[2]Base Inversionistas 26'!J47/$N$1 -> 0 | F44: ='[2]Base Inversionistas 26'!K47/$N$1 -> 17 | G44: ='[2]Base Inversionistas 26'!L47/$N$1 -> 18 | H44: ='[2]Base Inversionistas 26'!M47/$N$1 -> 18 | I44: ='[2]Base Inversionistas 26'!N47/$N$1 -> 21 | J44: ='[2]Base Inversionistas 26'!O47/$N$1 -> 0 | K44: ='[2]Base Inversionistas 26'!P47/$N$1 -> 0 | L44: ='[2]Base Inversionistas 26'!Q47/$N$1 -> 0
A45: IG. EN CUCUTA GUSTAVO LEON | B45: 16354014 | C45: 3133884161 | D45: CUCUTA | E45: ='[2]Base Inversionistas 26'!J48/$N$1 -> 2 | F45: ='[2]Base Inversionistas 26'!K48/$N$1 -> 1.0625 | G45: ='[2]Base Inversionistas 26'!L48/$N$1 -> 0 | H45: ='[2]Base Inversionistas 26'!M48/$N$1 -> 4 | I45: ='[2]Base Inversionistas 26'!N48/$N$1 -> 0 | J45: ='[2]Base Inversionistas 26'!O48/$N$1 -> 2 | K45: ='[2]Base Inversionistas 26'!P48/$N$1 -> 0 | L45: ='[2]Base Inversionistas 26'!Q48/$N$1 -> 2
A46: IG. EN DOSQUEBRADAS | D46: Dosquebradas | E46: ='[2]Base Inversionistas 26'!J49/$N$1 -> 0 | F46: ='[2]Base Inversionistas 26'!K49/$N$1 -> 0 | G46: ='[2]Base Inversionistas 26'!L49/$N$1 -> 0.4 | H46: ='[2]Base Inversionistas 26'!M49/$N$1 -> 0.175 | I46: ='[2]Base Inversionistas 26'!N49/$N$1 -> 0.3 | J46: ='[2]Base Inversionistas 26'!O49/$N$1 -> 0.625 | K46: ='[2]Base Inversionistas 26'!P49/$N$1 -> 0.675 | L46: ='[2]Base Inversionistas 26'!Q49/$N$1 -> 0
A47: IG. EN EL D.C. | B47: 900299699 | C47: 3214118979 | D47: BOGOTA | E47: ='[2]Base Inversionistas 26'!J50/$N$1 -> 2 | F47: ='[2]Base Inversionistas 26'!K50/$N$1 -> 2 | G47: ='[2]Base Inversionistas 26'!L50/$N$1 -> 2 | H47: ='[2]Base Inversionistas 26'!M50/$N$1 -> 2 | I47: ='[2]Base Inversionistas 26'!N50/$N$1 -> 2 | J47: ='[2]Base Inversionistas 26'!O50/$N$1 -> 2 | K47: ='[2]Base Inversionistas 26'!P50/$N$1 -> 2 | L47: ='[2]Base Inversionistas 26'!Q50/$N$1 -> 2
A48: IG. EN GIRARDOT | D48: Girardot | E48: ='[2]Base Inversionistas 26'!J51/$N$1 -> 0 | F48: ='[2]Base Inversionistas 26'!K51/$N$1 -> 0 | G48: ='[2]Base Inversionistas 26'!L51/$N$1 -> 0 | H48: ='[2]Base Inversionistas 26'!M51/$N$1 -> 0 | I48: ='[2]Base Inversionistas 26'!N51/$N$1 -> 1 | J48: ='[2]Base Inversionistas 26'!O51/$N$1 -> 0 | K48: ='[2]Base Inversionistas 26'!P51/$N$1 -> 2 | L48: ='[2]Base Inversionistas 26'!Q51/$N$1 -> 0
A49: IG. EN GIRARDOTA | D49: Girardota | E49: ='[2]Base Inversionistas 26'!J52/$N$1 -> 3 | F49: ='[2]Base Inversionistas 26'!K52/$N$1 -> 5 | G49: ='[2]Base Inversionistas 26'!L52/$N$1 -> 3 | H49: ='[2]Base Inversionistas 26'!M52/$N$1 -> 4.375 | I49: ='[2]Base Inversionistas 26'!N52/$N$1 -> 0 | J49: ='[2]Base Inversionistas 26'!O52/$N$1 -> 3.75 | K49: ='[2]Base Inversionistas 26'!P52/$N$1 -> 3 | L49: ='[2]Base Inversionistas 26'!Q52/$N$1 -> 0
A50: IG. EN ITAGUI | D50: Itagui | E50: ='[2]Base Inversionistas 26'!J53/$N$1 -> 0 | F50: ='[2]Base Inversionistas 26'!K53/$N$1 -> 0 | G50: ='[2]Base Inversionistas 26'!L53/$N$1 -> 0 | H50: ='[2]Base Inversionistas 26'!M53/$N$1 -> 6.175 | I50: ='[2]Base Inversionistas 26'!N53/$N$1 -> 0 | J50: ='[2]Base Inversionistas 26'!O53/$N$1 -> 0 | K50: ='[2]Base Inversionistas 26'!P53/$N$1 -> 0 | L50: ='[2]Base Inversionistas 26'!Q53/$N$1 -> 0
A51: IG. EN ITSMINA | B51: 11809146 | C51: 3136811706 | D51: Itsmina | E51: ='[2]Base Inversionistas 26'!J54/$N$1 -> 2 | F51: ='[2]Base Inversionistas 26'!K54/$N$1 -> 0 | G51: ='[2]Base Inversionistas 26'!L54/$N$1 -> 6 | H51: ='[2]Base Inversionistas 26'!M54/$N$1 -> 3 | I51: ='[2]Base Inversionistas 26'!N54/$N$1 -> 0 | J51: ='[2]Base Inversionistas 26'!O54/$N$1 -> 3 | K51: ='[2]Base Inversionistas 26'!P54/$N$1 -> 7 | L51: ='[2]Base Inversionistas 26'!Q54/$N$1 -> 4
A52: IG. EN LA MINA | D52: La mina | E52: ='[2]Base Inversionistas 26'!J55/$N$1 -> 1 | F52: ='[2]Base Inversionistas 26'!K55/$N$1 -> 1 | G52: ='[2]Base Inversionistas 26'!L55/$N$1 -> 0 | H52: ='[2]Base Inversionistas 26'!M55/$N$1 -> 0 | I52: ='[2]Base Inversionistas 26'!N55/$N$1 -> 1 | J52: ='[2]Base Inversionistas 26'!O55/$N$1 -> 0 | K52: ='[2]Base Inversionistas 26'!P55/$N$1 -> 0 | L52: ='[2]Base Inversionistas 26'!Q55/$N$1 -> 0
A53: IG. EN MALAMBO | D53: Malambo | E53: ='[2]Base Inversionistas 26'!J56/$N$1 -> 1 | F53: ='[2]Base Inversionistas 26'!K56/$N$1 -> 0 | G53: ='[2]Base Inversionistas 26'!L56/$N$1 -> 0 | H53: ='[2]Base Inversionistas 26'!M56/$N$1 -> 1 | I53: ='[2]Base Inversionistas 26'!N56/$N$1 -> 1 | J53: ='[2]Base Inversionistas 26'!O56/$N$1 -> 0 | K53: ='[2]Base Inversionistas 26'!P56/$N$1 -> 0 | L53: ='[2]Base Inversionistas 26'!Q56/$N$1 -> 1
A54: IG. EN MEDELLIN | D54: Medellin | E54: ='[2]Base Inversionistas 26'!J57/$N$1 -> 0 | F54: ='[2]Base Inversionistas 26'!K57/$N$1 -> 0 | G54: ='[2]Base Inversionistas 26'!L57/$N$1 -> 1 | H54: ='[2]Base Inversionistas 26'!M57/$N$1 -> 0 | I54: ='[2]Base Inversionistas 26'!N57/$N$1 -> 0 | J54: ='[2]Base Inversionistas 26'!O57/$N$1 -> 0 | K54: ='[2]Base Inversionistas 26'!P57/$N$1 -> 0 | L54: ='[2]Base Inversionistas 26'!Q57/$N$1 -> 1
A55: IG. EN NEIVA | D55: Neiva | E55: ='[2]Base Inversionistas 26'!J58/$N$1 -> 1.5 | F55: ='[2]Base Inversionistas 26'!K58/$N$1 -> 1.5 | G55: ='[2]Base Inversionistas 26'!L58/$N$1 -> 5 | H55: ='[2]Base Inversionistas 26'!M58/$N$1 -> 0 | I55: ='[2]Base Inversionistas 26'!N58/$N$1 -> 0 | J55: ='[2]Base Inversionistas 26'!O58/$N$1 -> 1.5 | K55: ='[2]Base Inversionistas 26'!P58/$N$1 -> 9 | L55: ='[2]Base Inversionistas 26'!Q58/$N$1 -> 9
A56: IG. EN OCAÑA | B56: 900420427-8 | D56: Ocaña | E56: ='[2]Base Inversionistas 26'!J59/$N$1 -> 0 | F56: ='[2]Base Inversionistas 26'!K59/$N$1 -> 3 | G56: ='[2]Base Inversionistas 26'!L59/$N$1 -> 5 | H56: ='[2]Base Inversionistas 26'!M59/$N$1 -> 4 | I56: ='[2]Base Inversionistas 26'!N59/$N$1 -> 0 | J56: ='[2]Base Inversionistas 26'!O59/$N$1 -> 2 | K56: ='[2]Base Inversionistas 26'!P59/$N$1 -> 3 | L56: ='[2]Base Inversionistas 26'!Q59/$N$1 -> 0
A57: IG. EN PEREIRA | D57: Pereira | E57: ='[2]Base Inversionistas 26'!J60/$N$1 -> 0 | F57: ='[2]Base Inversionistas 26'!K60/$N$1 -> 1 | G57: ='[2]Base Inversionistas 26'!L60/$N$1 -> 3 | H57: ='[2]Base Inversionistas 26'!M60/$N$1 -> 1 | I57: ='[2]Base Inversionistas 26'!N60/$N$1 -> 0 | J57: ='[2]Base Inversionistas 26'!O60/$N$1 -> 4 | K57: ='[2]Base Inversionistas 26'!P60/$N$1 -> 2.25 | L57: ='[2]Base Inversionistas 26'!Q60/$N$1 -> 1
A58: IG. EN QUIBDO | B58: 900371129 | C58: 3216464514 | D58: QUIBDO | E58: ='[2]Base Inversionistas 26'!J61/$N$1 -> 2 | F58: ='[2]Base Inversionistas 26'!K61/$N$1 -> 12 | G58: ='[2]Base Inversionistas 26'!L61/$N$1 -> 3 | H58: ='[2]Base Inversionistas 26'!M61/$N$1 -> 1 | I58: ='[2]Base Inversionistas 26'!N61/$N$1 -> 1 | J58: ='[2]Base Inversionistas 26'!O61/$N$1 -> 1 | K58: ='[2]Base Inversionistas 26'!P61/$N$1 -> 2 | L58: ='[2]Base Inversionistas 26'!Q61/$N$1 -> 0
A59: IG. EN RIOHACHA | D59: Riohacha | E59: ='[2]Base Inversionistas 26'!J62/$N$1 -> 0 | F59: ='[2]Base Inversionistas 26'!K62/$N$1 -> 0 | G59: ='[2]Base Inversionistas 26'!L62/$N$1 -> 0 | H59: ='[2]Base Inversionistas 26'!M62/$N$1 -> 0 | I59: ='[2]Base Inversionistas 26'!N62/$N$1 -> 0 | J59: ='[2]Base Inversionistas 26'!O62/$N$1 -> 0 | K59: ='[2]Base Inversionistas 26'!P62/$N$1 -> 0 | L59: ='[2]Base Inversionistas 26'!Q62/$N$1 -> 0
A60: IG. EN RIVERA | D60: Rivera | E60: ='[2]Base Inversionistas 26'!J63/$N$1 -> 0 | F60: ='[2]Base Inversionistas 26'!K63/$N$1 -> 0.25 | G60: ='[2]Base Inversionistas 26'!L63/$N$1 -> 0 | H60: ='[2]Base Inversionistas 26'!M63/$N$1 -> 0.25 | I60: ='[2]Base Inversionistas 26'!N63/$N$1 -> 1 | J60: ='[2]Base Inversionistas 26'!O63/$N$1 -> 0 | K60: ='[2]Base Inversionistas 26'!P63/$N$1 -> 0 | L60: ='[2]Base Inversionistas 26'!Q63/$N$1 -> 0.6
A61: IG. EN SINCELEJO | D61: Sincelejo | E61: ='[2]Base Inversionistas 26'!J64/$N$1 -> 1 | F61: ='[2]Base Inversionistas 26'!K64/$N$1 -> 1 | G61: ='[2]Base Inversionistas 26'!L64/$N$1 -> 0 | H61: ='[2]Base Inversionistas 26'!M64/$N$1 -> 1 | I61: ='[2]Base Inversionistas 26'!N64/$N$1 -> 0 | J61: ='[2]Base Inversionistas 26'!O64/$N$1 -> 0 | K61: ='[2]Base Inversionistas 26'!P64/$N$1 -> 0 | L61: ='[2]Base Inversionistas 26'!Q64/$N$1 -> 0
A62: IG. EN SOLEDAD | D62: Soledad | E62: ='[2]Base Inversionistas 26'!J65/$N$1 -> 0 | F62: ='[2]Base Inversionistas 26'!K65/$N$1 -> 0 | G62: ='[2]Base Inversionistas 26'!L65/$N$1 -> 0 | H62: ='[2]Base Inversionistas 26'!M65/$N$1 -> 7 | I62: ='[2]Base Inversionistas 26'!N65/$N$1 -> 0 | J62: ='[2]Base Inversionistas 26'!O65/$N$1 -> 4 | K62: ='[2]Base Inversionistas 26'!P65/$N$1 -> 4 | L62: ='[2]Base Inversionistas 26'!Q65/$N$1 -> 4
A63: IG. EN STA MARTA JOSE LUIS TERAN | B63: 900-380-4931 | C63: 3233712038 | D63: Sta marta | E63: ='[2]Base Inversionistas 26'!J66/$N$1 -> 5.325 | F63: ='[2]Base Inversionistas 26'!K66/$N$1 -> 5.3375 | G63: ='[2]Base Inversionistas 26'!L66/$N$1 -> 5.2 | H63: ='[2]Base Inversionistas 26'!M66/$N$1 -> 0 | I63: ='[2]Base Inversionistas 26'!N66/$N$1 -> 4.775 | J63: ='[2]Base Inversionistas 26'!O66/$N$1 -> 5.175 | K63: ='[2]Base Inversionistas 26'!P66/$N$1 -> 5.25 | L63: ='[2]Base Inversionistas 26'!Q66/$N$1 -> 4.75
A64: IG. EN SUAN | D64: Suan | E64: ='[2]Base Inversionistas 26'!J67/$N$1 -> 1.425 | F64: ='[2]Base Inversionistas 26'!K67/$N$1 -> 1 | G64: ='[2]Base Inversionistas 26'!L67/$N$1 -> 0 | H64: ='[2]Base Inversionistas 26'!M67/$N$1 -> 0 | I64: ='[2]Base Inversionistas 26'!N67/$N$1 -> 0 | J64: ='[2]Base Inversionistas 26'!O67/$N$1 -> 0 | K64: ='[2]Base Inversionistas 26'!P67/$N$1 -> 1 | L64: ='[2]Base Inversionistas 26'!Q67/$N$1 -> 1
A65: IG. EN TURBACO | D65: Turbaco | E65: ='[2]Base Inversionistas 26'!J68/$N$1 -> 0 | F65: ='[2]Base Inversionistas 26'!K68/$N$1 -> 5.6356075 | G65: ='[2]Base Inversionistas 26'!L68/$N$1 -> 0 | H65: ='[2]Base Inversionistas 26'!M68/$N$1 -> 0 | I65: ='[2]Base Inversionistas 26'!N68/$N$1 -> 0 | J65: ='[2]Base Inversionistas 26'!O68/$N$1 -> 0 | K65: ='[2]Base Inversionistas 26'!P68/$N$1 -> 0 | L65: ='[2]Base Inversionistas 26'!Q68/$N$1 -> 0
A66: IG. EN UBATE | B66: 900384157 | C66: 3103160465 | D66: Ubate | E66: ='[2]Base Inversionistas 26'!J69/$N$1 -> 12 | F66: ='[2]Base Inversionistas 26'!K69/$N$1 -> 13.6 | G66: ='[2]Base Inversionistas 26'!L69/$N$1 -> 12.5 | H66: ='[2]Base Inversionistas 26'!M69/$N$1 -> 15 | I66: ='[2]Base Inversionistas 26'!N69/$N$1 -> 0 | J66: ='[2]Base Inversionistas 26'!O69/$N$1 -> 12.65 | K66: ='[2]Base Inversionistas 26'!P69/$N$1 -> 10.75 | L66: ='[2]Base Inversionistas 26'!Q69/$N$1 -> 2.125
A67: IG. EN VALLEDUPAR | B67: 900406774 | D67: Valledupar | E67: ='[2]Base Inversionistas 26'!J70/$N$1 -> 0 | F67: ='[2]Base Inversionistas 26'!K70/$N$1 -> 25.015 | G67: ='[2]Base Inversionistas 26'!L70/$N$1 -> 0 | H67: ='[2]Base Inversionistas 26'!M70/$N$1 -> 30 | I67: ='[2]Base Inversionistas 26'!N70/$N$1 -> 31 | J67: ='[2]Base Inversionistas 26'!O70/$N$1 -> 25.535 | K67: ='[2]Base Inversionistas 26'!P70/$N$1 -> 25 | L67: ='[2]Base Inversionistas 26'!Q70/$N$1 -> 27.5
A68: IG. EN VILLAVICENCIO | D68: Villavicencio | E68: ='[2]Base Inversionistas 26'!J71/$N$1 -> 0 | F68: ='[2]Base Inversionistas 26'!K71/$N$1 -> 0 | G68: ='[2]Base Inversionistas 26'!L71/$N$1 -> 0 | H68: ='[2]Base Inversionistas 26'!M71/$N$1 -> 0 | I68: ='[2]Base Inversionistas 26'!N71/$N$1 -> 0 | J68: ='[2]Base Inversionistas 26'!O71/$N$1 -> 0 | K68: ='[2]Base Inversionistas 26'!P71/$N$1 -> 0 | L68: ='[2]Base Inversionistas 26'!Q71/$N$1 -> 0
A69: IG. EN VILLA DEL ROSARIO | D69: V. ROSARIO | E69: ='[2]Base Inversionistas 26'!J72/$N$1 -> 3 | F69: ='[2]Base Inversionistas 26'!K72/$N$1 -> 1 | G69: ='[2]Base Inversionistas 26'!L72/$N$1 -> 1 | H69: ='[2]Base Inversionistas 26'!M72/$N$1 -> 1 | I69: ='[2]Base Inversionistas 26'!N72/$N$1 -> 0 | J69: ='[2]Base Inversionistas 26'!O72/$N$1 -> 1 | K69: ='[2]Base Inversionistas 26'!P72/$N$1 -> 1 | L69: ='[2]Base Inversionistas 26'!Q72/$N$1 -> 0
A70: IG. EN TULUA GUILLERMO HERRERA MURCIA | D70: Tulua | E70: ='[2]Base Inversionistas 26'!J73/$N$1 -> 0 | F70: ='[2]Base Inversionistas 26'!K73/$N$1 -> 0 | G70: ='[2]Base Inversionistas 26'!L73/$N$1 -> 1 | H70: ='[2]Base Inversionistas 26'!M73/$N$1 -> 0 | I70: ='[2]Base Inversionistas 26'!N73/$N$1 -> 0 | J70: ='[2]Base Inversionistas 26'!O73/$N$1 -> 0 | K70: ='[2]Base Inversionistas 26'!P73/$N$1 -> 2 | L70: ='[2]Base Inversionistas 26'!Q73/$N$1 -> 1
A71: IG. EN ARMENIA | D71: Armenia | E71: ='[2]Base Inversionistas 26'!J74/$N$1 -> 0 | F71: ='[2]Base Inversionistas 26'!K74/$N$1 -> 0 | G71: ='[2]Base Inversionistas 26'!L74/$N$1 -> 0 | H71: ='[2]Base Inversionistas 26'!M74/$N$1 -> 0 | I71: ='[2]Base Inversionistas 26'!N74/$N$1 -> 0 | J71: ='[2]Base Inversionistas 26'!O74/$N$1 -> 0 | K71: ='[2]Base Inversionistas 26'!P74/$N$1 -> 2 | L71: ='[2]Base Inversionistas 26'!Q74/$N$1 -> 0
A72: IG. EN CARTAGENA | D72: CARTAGENA | E72: ='[2]Base Inversionistas 26'!J75/$N$1 -> 0 | F72: ='[2]Base Inversionistas 26'!K75/$N$1 -> 5 | G72: ='[2]Base Inversionistas 26'!L75/$N$1 -> 2 | H72: ='[2]Base Inversionistas 26'!M75/$N$1 -> 0 | I72: ='[2]Base Inversionistas 26'!N75/$N$1 -> 5 | J72: ='[2]Base Inversionistas 26'!O75/$N$1 -> 6 | K72: ='[2]Base Inversionistas 26'!P75/$N$1 -> 6 | L72: ='[2]Base Inversionistas 26'!Q75/$N$1 -> 5
A73: IG. EN LOS PATIOS | B73: 900474240-1 | C73: 3222616473 | D73: LOS PATIOS | E73: ='[2]Base Inversionistas 26'!J76/$N$1 -> 2 | F73: ='[2]Base Inversionistas 26'!K76/$N$1 -> 2 | G73: ='[2]Base Inversionistas 26'!L76/$N$1 -> 2 | H73: ='[2]Base Inversionistas 26'!M76/$N$1 -> 2 | I73: ='[2]Base Inversionistas 26'!N76/$N$1 -> 2 | J73: ='[2]Base Inversionistas 26'!O76/$N$1 -> 2 | K73: ='[2]Base Inversionistas 26'!P76/$N$1 -> 2 | L73: ='[2]Base Inversionistas 26'!Q76/$N$1 -> 3
A74: IG. EN MONTERIA y STA LUCIA | D74: MONTERIA | E74: ='[2]Base Inversionistas 26'!J77/$N$1 -> 18 | F74: ='[2]Base Inversionistas 26'!K77/$N$1 -> 0 | G74: ='[2]Base Inversionistas 26'!L77/$N$1 -> 0 | H74: ='[2]Base Inversionistas 26'!M77/$N$1 -> 0 | I74: ='[2]Base Inversionistas 26'!N77/$N$1 -> 0 | J74: ='[2]Base Inversionistas 26'!O77/$N$1 -> 20 | K74: ='[2]Base Inversionistas 26'!P77/$N$1 -> 20 | L74: ='[2]Base Inversionistas 26'!Q77/$N$1 -> 0
A75: INDIRA ESTRADA | D75: BOGOTA | E75: ='[2]Base Inversionistas 26'!J78/$N$1 -> 0 | F75: ='[2]Base Inversionistas 26'!K78/$N$1 -> 0 | G75: ='[2]Base Inversionistas 26'!L78/$N$1 -> 0 | H75: ='[2]Base Inversionistas 26'!M78/$N$1 -> 0 | I75: ='[2]Base Inversionistas 26'!N78/$N$1 -> 0 | J75: ='[2]Base Inversionistas 26'!O78/$N$1 -> 0 | K75: ='[2]Base Inversionistas 26'!P78/$N$1 -> 0 | L75: ='[2]Base Inversionistas 26'!Q78/$N$1 -> 0
A76: ISABEL TORRIJAS | D76: Medellin | E76: ='[2]Base Inversionistas 26'!J79/$N$1 -> 0 | F76: ='[2]Base Inversionistas 26'!K79/$N$1 -> 0 | G76: ='[2]Base Inversionistas 26'!L79/$N$1 -> 0 | H76: ='[2]Base Inversionistas 26'!M79/$N$1 -> 0 | I76: ='[2]Base Inversionistas 26'!N79/$N$1 -> 0 | J76: ='[2]Base Inversionistas 26'!O79/$N$1 -> 0 | K76: ='[2]Base Inversionistas 26'!P79/$N$1 -> 0 | L76: ='[2]Base Inversionistas 26'!Q79/$N$1 -> 0
A77: JAMES GAMBOA | D77: BOGOTA | E77: ='[2]Base Inversionistas 26'!J80/$N$1 -> 0 | F77: ='[2]Base Inversionistas 26'!K80/$N$1 -> 0 | G77: ='[2]Base Inversionistas 26'!L80/$N$1 -> 0 | H77: ='[2]Base Inversionistas 26'!M80/$N$1 -> 0 | I77: ='[2]Base Inversionistas 26'!N80/$N$1 -> 0 | J77: ='[2]Base Inversionistas 26'!O80/$N$1 -> 0 | K77: ='[2]Base Inversionistas 26'!P80/$N$1 -> 0 | L77: ='[2]Base Inversionistas 26'!Q80/$N$1 -> 0
A78: JAVIER BLOOM | D78: Medellin | E78: ='[2]Base Inversionistas 26'!J81/$N$1 -> 0 | F78: ='[2]Base Inversionistas 26'!K81/$N$1 -> 0 | G78: ='[2]Base Inversionistas 26'!L81/$N$1 -> 0 | H78: ='[2]Base Inversionistas 26'!M81/$N$1 -> 1.052455 | I78: ='[2]Base Inversionistas 26'!N81/$N$1 -> 0 | J78: ='[2]Base Inversionistas 26'!O81/$N$1 -> 0 | K78: ='[2]Base Inversionistas 26'!P81/$N$1 -> 0 | L78: ='[2]Base Inversionistas 26'!Q81/$N$1 -> 0
A79: JEAN CARLOS BLANCO | B79: 1093783625 | C79: 3223202421 | D79: LOS PATIOS | E79: ='[2]Base Inversionistas 26'!J82/$N$1 -> 1 | F79: ='[2]Base Inversionistas 26'!K82/$N$1 -> 4 | G79: ='[2]Base Inversionistas 26'!L82/$N$1 -> 2 | H79: ='[2]Base Inversionistas 26'!M82/$N$1 -> 3 | I79: ='[2]Base Inversionistas 26'!N82/$N$1 -> 3 | J79: ='[2]Base Inversionistas 26'!O82/$N$1 -> 3 | K79: ='[2]Base Inversionistas 26'!P82/$N$1 -> 3 | L79: ='[2]Base Inversionistas 26'!Q82/$N$1 -> 3
A80: JHOJAS QUINTERO | B80: 79477468 | C80: 3185861284 | D80: SOACHA | E80: ='[2]Base Inversionistas 26'!J83/$N$1 -> 1 | F80: ='[2]Base Inversionistas 26'!K83/$N$1 -> 1 | G80: ='[2]Base Inversionistas 26'!L83/$N$1 -> 0.75 | H80: ='[2]Base Inversionistas 26'!M83/$N$1 -> 0 | I80: ='[2]Base Inversionistas 26'!N83/$N$1 -> 0.75 | J80: ='[2]Base Inversionistas 26'!O83/$N$1 -> 0.75 | K80: ='[2]Base Inversionistas 26'!P83/$N$1 -> 1 | L80: ='[2]Base Inversionistas 26'!Q83/$N$1 -> 0.75
A81: JHON ROJAS | B81: 12135690 | D81: Neiva | E81: ='[2]Base Inversionistas 26'!J84/$N$1 -> 1.0025 | F81: ='[2]Base Inversionistas 26'!K84/$N$1 -> 0 | G81: ='[2]Base Inversionistas 26'!L84/$N$1 -> 0 | H81: ='[2]Base Inversionistas 26'!M84/$N$1 -> 2.5 | I81: ='[2]Base Inversionistas 26'!N84/$N$1 -> 0 | J81: ='[2]Base Inversionistas 26'!O84/$N$1 -> 1 | K81: ='[2]Base Inversionistas 26'!P84/$N$1 -> 2 | L81: ='[2]Base Inversionistas 26'!Q84/$N$1 -> 0
A82: JOEL ARIAS | D82: Medellin | E82: ='[2]Base Inversionistas 26'!J85/$N$1 -> 0 | F82: ='[2]Base Inversionistas 26'!K85/$N$1 -> 0 | G82: ='[2]Base Inversionistas 26'!L85/$N$1 -> 0 | H82: ='[2]Base Inversionistas 26'!M85/$N$1 -> 0 | I82: ='[2]Base Inversionistas 26'!N85/$N$1 -> 0 | J82: ='[2]Base Inversionistas 26'!O85/$N$1 -> 0 | K82: ='[2]Base Inversionistas 26'!P85/$N$1 -> 0 | L82: ='[2]Base Inversionistas 26'!Q85/$N$1 -> 0
A83: JOHAN GOMEZ ZAPATA | B83: 1128400756 | C83: 3043640493 | D83: MEDELLIN | E83: ='[2]Base Inversionistas 26'!J86/$N$1 -> 0 | F83: ='[2]Base Inversionistas 26'!K86/$N$1 -> 0 | G83: ='[2]Base Inversionistas 26'!L86/$N$1 -> 0 | H83: ='[2]Base Inversionistas 26'!M86/$N$1 -> 1 | I83: ='[2]Base Inversionistas 26'!N86/$N$1 -> 0 | J83: ='[2]Base Inversionistas 26'!O86/$N$1 -> 0 | K83: ='[2]Base Inversionistas 26'!P86/$N$1 -> 0 | L83: ='[2]Base Inversionistas 26'!Q86/$N$1 -> 0
A84: JOHANA SANTIESTEBAN | E84: ='[2]Base Inversionistas 26'!J87/$N$1 -> 0 | F84: ='[2]Base Inversionistas 26'!K87/$N$1 -> 0 | G84: ='[2]Base Inversionistas 26'!L87/$N$1 -> 0 | H84: ='[2]Base Inversionistas 26'!M87/$N$1 -> 0 | I84: ='[2]Base Inversionistas 26'!N87/$N$1 -> 0 | J84: ='[2]Base Inversionistas 26'!O87/$N$1 -> 0 | K84: ='[2]Base Inversionistas 26'!P87/$N$1 -> 0 | L84: ='[2]Base Inversionistas 26'!Q87/$N$1 -> 0
A85: JORGE GOMEZ | B85: 13838106 | C85: 3158359949 | D85: BUCARAMANGA | E85: ='[2]Base Inversionistas 26'!J88/$N$1 -> 0 | F85: ='[2]Base Inversionistas 26'!K88/$N$1 -> 0 | G85: ='[2]Base Inversionistas 26'!L88/$N$1 -> 0 | H85: ='[2]Base Inversionistas 26'!M88/$N$1 -> 0 | I85: ='[2]Base Inversionistas 26'!N88/$N$1 -> 0 | J85: ='[2]Base Inversionistas 26'!O88/$N$1 -> 0 | K85: ='[2]Base Inversionistas 26'!P88/$N$1 -> 0 | L85: ='[2]Base Inversionistas 26'!Q88/$N$1 -> 0
A86: JORGE LUIS BARRIOS | B86: 91249777 | E86: ='[2]Base Inversionistas 26'!J89/$N$1 -> 0 | F86: ='[2]Base Inversionistas 26'!K89/$N$1 -> 0 | G86: ='[2]Base Inversionistas 26'!L89/$N$1 -> 0 | H86: ='[2]Base Inversionistas 26'!M89/$N$1 -> 0 | I86: ='[2]Base Inversionistas 26'!N89/$N$1 -> 0 | J86: ='[2]Base Inversionistas 26'!O89/$N$1 -> 0 | K86: ='[2]Base Inversionistas 26'!P89/$N$1 -> 0 | L86: ='[2]Base Inversionistas 26'!Q89/$N$1 -> 0
A87: JORGE RODRIGUEZ | E87: ='[2]Base Inversionistas 26'!J90/$N$1 -> 0 | F87: ='[2]Base Inversionistas 26'!K90/$N$1 -> 0 | G87: ='[2]Base Inversionistas 26'!L90/$N$1 -> 0 | H87: ='[2]Base Inversionistas 26'!M90/$N$1 -> 0 | I87: ='[2]Base Inversionistas 26'!N90/$N$1 -> 0 | J87: ='[2]Base Inversionistas 26'!O90/$N$1 -> 0 | K87: ='[2]Base Inversionistas 26'!P90/$N$1 -> 0 | L87: ='[2]Base Inversionistas 26'!Q90/$N$1 -> 0
A88: JOSE ELBERT GARZON | E88: ='[2]Base Inversionistas 26'!J91/$N$1 -> 0 | F88: ='[2]Base Inversionistas 26'!K91/$N$1 -> 0 | G88: ='[2]Base Inversionistas 26'!L91/$N$1 -> 0 | H88: ='[2]Base Inversionistas 26'!M91/$N$1 -> 0 | I88: ='[2]Base Inversionistas 26'!N91/$N$1 -> 0 | J88: ='[2]Base Inversionistas 26'!O91/$N$1 -> 0 | K88: ='[2]Base Inversionistas 26'!P91/$N$1 -> 0 | L88: ='[2]Base Inversionistas 26'!Q91/$N$1 -> 0
A89: JOSE ENRIQUE ARIAS PEREZ | B89: 15374739 | D89: MEDELLIN | E89: ='[2]Base Inversionistas 26'!J92/$N$1 -> 0 | F89: ='[2]Base Inversionistas 26'!K92/$N$1 -> 0 | G89: ='[2]Base Inversionistas 26'!L92/$N$1 -> 2 | H89: ='[2]Base Inversionistas 26'!M92/$N$1 -> 1 | I89: ='[2]Base Inversionistas 26'!N92/$N$1 -> 0 | J89: ='[2]Base Inversionistas 26'!O92/$N$1 -> 1 | K89: ='[2]Base Inversionistas 26'!P92/$N$1 -> 0 | L89: ='[2]Base Inversionistas 26'!Q92/$N$1 -> 0
A90: JOSE GONZALEZ | E90: ='[2]Base Inversionistas 26'!J93/$N$1 -> 0 | F90: ='[2]Base Inversionistas 26'!K93/$N$1 -> 0 | G90: ='[2]Base Inversionistas 26'!L93/$N$1 -> 0 | H90: ='[2]Base Inversionistas 26'!M93/$N$1 -> 0 | I90: ='[2]Base Inversionistas 26'!N93/$N$1 -> 0 | J90: ='[2]Base Inversionistas 26'!O93/$N$1 -> 0 | K90: ='[2]Base Inversionistas 26'!P93/$N$1 -> 0 | L90: ='[2]Base Inversionistas 26'!Q93/$N$1 -> 0
A91: JUAN VALENCIA | E91: ='[2]Base Inversionistas 26'!J94/$N$1 -> 0 | F91: ='[2]Base Inversionistas 26'!K94/$N$1 -> 0 | G91: ='[2]Base Inversionistas 26'!L94/$N$1 -> 0 | H91: ='[2]Base Inversionistas 26'!M94/$N$1 -> 0 | I91: ='[2]Base Inversionistas 26'!N94/$N$1 -> 0 | J91: ='[2]Base Inversionistas 26'!O94/$N$1 -> 0 | K91: ='[2]Base Inversionistas 26'!P94/$N$1 -> 0 | L91: ='[2]Base Inversionistas 26'!Q94/$N$1 -> 0
A92: JUAN C. MORENO | B92: 1077426534 | C92: 3113654554 | D92: QUIBDO | E92: ='[2]Base Inversionistas 26'!J95/$N$1 -> 0 | F92: ='[2]Base Inversionistas 26'!K95/$N$1 -> 0 | G92: ='[2]Base Inversionistas 26'!L95/$N$1 -> 0 | H92: ='[2]Base Inversionistas 26'!M95/$N$1 -> 2 | I92: ='[2]Base Inversionistas 26'!N95/$N$1 -> 0 | J92: ='[2]Base Inversionistas 26'!O95/$N$1 -> 0 | K92: ='[2]Base Inversionistas 26'!P95/$N$1 -> 0 | L92: ='[2]Base Inversionistas 26'!Q95/$N$1 -> 0
A93: JUAN GUILLERMO MUÑOZ GIRARDOTA | B93: 70326161 | C93: 3017435330 | D93: Girardota | E93: ='[2]Base Inversionistas 26'!J96/$N$1 -> 1 | F93: ='[2]Base Inversionistas 26'!K96/$N$1 -> 1 | G93: ='[2]Base Inversionistas 26'!L96/$N$1 -> 1 | H93: ='[2]Base Inversionistas 26'!M96/$N$1 -> 1 | I93: ='[2]Base Inversionistas 26'!N96/$N$1 -> 1 | J93: ='[2]Base Inversionistas 26'!O96/$N$1 -> 1 | K93: ='[2]Base Inversionistas 26'!P96/$N$1 -> 0 | L93: ='[2]Base Inversionistas 26'!Q96/$N$1 -> 0
A94: JUAN MINA | E94: ='[2]Base Inversionistas 26'!J97/$N$1 -> 0 | F94: ='[2]Base Inversionistas 26'!K97/$N$1 -> 0 | G94: ='[2]Base Inversionistas 26'!L97/$N$1 -> 0 | H94: ='[2]Base Inversionistas 26'!M97/$N$1 -> 0 | I94: ='[2]Base Inversionistas 26'!N97/$N$1 -> 0 | J94: ='[2]Base Inversionistas 26'!O97/$N$1 -> 0 | K94: ='[2]Base Inversionistas 26'!P97/$N$1 -> 1 | L94: ='[2]Base Inversionistas 26'!Q97/$N$1 -> 1
A95: JUAN PABLO OLIVELLA | B95: 77037962 | C95: 3108469718 | D95: VALLEDUPAR | E95: ='[2]Base Inversionistas 26'!J98/$N$1 -> 6 | F95: ='[2]Base Inversionistas 26'!K98/$N$1 -> 6 | G95: ='[2]Base Inversionistas 26'!L98/$N$1 -> 0 | H95: ='[2]Base Inversionistas 26'!M98/$N$1 -> 0 | I95: ='[2]Base Inversionistas 26'!N98/$N$1 -> 6 | J95: ='[2]Base Inversionistas 26'!O98/$N$1 -> 6 | K95: ='[2]Base Inversionistas 26'!P98/$N$1 -> 0 | L95: ='[2]Base Inversionistas 26'!Q98/$N$1 -> 0
A96: JUAN PABLO OLIVELLA (HNO. DONG) | E96: ='[2]Base Inversionistas 26'!J99/$N$1 -> 0 | F96: ='[2]Base Inversionistas 26'!K99/$N$1 -> 0 | G96: ='[2]Base Inversionistas 26'!L99/$N$1 -> 0 | H96: ='[2]Base Inversionistas 26'!M99/$N$1 -> 0 | I96: ='[2]Base Inversionistas 26'!N99/$N$1 -> 0 | J96: ='[2]Base Inversionistas 26'!O99/$N$1 -> 0 | K96: ='[2]Base Inversionistas 26'!P99/$N$1 -> 0 | L96: ='[2]Base Inversionistas 26'!Q99/$N$1 -> 0
A97: JUAN SEBASTIAN MONTES PINZON | E97: ='[2]Base Inversionistas 26'!J100/$N$1 -> 0 | F97: ='[2]Base Inversionistas 26'!K100/$N$1 -> 0 | G97: ='[2]Base Inversionistas 26'!L100/$N$1 -> 0 | H97: ='[2]Base Inversionistas 26'!M100/$N$1 -> 0 | I97: ='[2]Base Inversionistas 26'!N100/$N$1 -> 0 | J97: ='[2]Base Inversionistas 26'!O100/$N$1 -> 0 | K97: ='[2]Base Inversionistas 26'!P100/$N$1 -> 0 | L97: ='[2]Base Inversionistas 26'!Q100/$N$1 -> 0
A98: JULIAN CADAVID | E98: ='[2]Base Inversionistas 26'!J101/$N$1 -> 0 | F98: ='[2]Base Inversionistas 26'!K101/$N$1 -> 0 | G98: ='[2]Base Inversionistas 26'!L101/$N$1 -> 0 | H98: ='[2]Base Inversionistas 26'!M101/$N$1 -> 0 | I98: ='[2]Base Inversionistas 26'!N101/$N$1 -> 0 | J98: ='[2]Base Inversionistas 26'!O101/$N$1 -> 0 | K98: ='[2]Base Inversionistas 26'!P101/$N$1 -> 0 | L98: ='[2]Base Inversionistas 26'!Q101/$N$1 -> 0
A99: JULIAN FRANCO IG. B/MANGA | D99: BUCARAMANGA | E99: ='[2]Base Inversionistas 26'!J102/$N$1 -> 0 | F99: ='[2]Base Inversionistas 26'!K102/$N$1 -> 0 | G99: ='[2]Base Inversionistas 26'!L102/$N$1 -> 0 | H99: ='[2]Base Inversionistas 26'!M102/$N$1 -> 0 | I99: ='[2]Base Inversionistas 26'!N102/$N$1 -> 0 | J99: ='[2]Base Inversionistas 26'!O102/$N$1 -> 0 | K99: ='[2]Base Inversionistas 26'!P102/$N$1 -> 0 | L99: ='[2]Base Inversionistas 26'!Q102/$N$1 -> 0
A100: JULIO LONDOÑO | B100: 1077424658 | C100: 3216464514 | D100: QUIBDO | E100: ='[2]Base Inversionistas 26'!J103/$N$1 -> 0 | F100: ='[2]Base Inversionistas 26'!K103/$N$1 -> 3 | G100: ='[2]Base Inversionistas 26'!L103/$N$1 -> 0 | H100: ='[2]Base Inversionistas 26'!M103/$N$1 -> 0 | I100: ='[2]Base Inversionistas 26'!N103/$N$1 -> 0 | J100: ='[2]Base Inversionistas 26'!O103/$N$1 -> 0 | K100: ='[2]Base Inversionistas 26'!P103/$N$1 -> 0 | L100: ='[2]Base Inversionistas 26'!Q103/$N$1 -> 0
...
